Workbook

Sheet SS27
C1: 1 | D1: 2 | E1: 3 | F1: 4 | G1: 5 | H1: 6 | I1: 7 | J1: 8 | K1: 9 | L1: 10 | M1: 11 | N1: 12 | O1: 13 | P1: 14 | Q1: 15 | R1: 16 | S1: 17 | T1: 18 | U1: 19 | V1: 20 | W1: 21 | X1: 22 | Y1: 23 | Z1: 24 | AA1: 25 | AB1: 26 | AC1: 27
A2: Season | B2: Active | C2: Code | D2: Style | E2: Business Area | F2: Product Concept | G2: Category/Layer | H2: Collection Type | I2: Gender | J2: Proposed Drop Week | K2: Carry Over | L2: Update | M2: Target RRP | N2: Mark-up | O2: WP | P2: GM0% | Q2: Product Hierarchy | R2: Distribution Segmentation | S2: Main technology platform | T2: Secondary technology platform | U2: Style Comment | V2: ABS Customer | W2: STATUS | X2: LANDED COST SEK | Y2: REF_CODE | Z2: REF_NAME | AA2: Classification ABC | AB2: MOQ Style | AC2: MOQ Color | AD2: Check Pricing | AE2: Color Options | AF2: Collection | AG2: NEW MAPPING: Activity | AH2: PPT Collection / Activity (deck) | AI2: Category/Layer(V2) | AJ2: Silhouette | AK2: Category/Layer Subtype | AL2: Waterproof | AM2: Attribution Review | AN2: Franchise/Family
A3: SS27 | B3: TRUE | C3: 608172 | D3: Alert GTX Jacket Men | E3: Apparel | F3: OUT | G3: Shell | H3: Inline | I3: Men | K3: TRUE | L3: FALSE | M3: 3800 | N3: 2.1 | O3: 1809.52 | P3: 0.60502233 | Q3: Good | R3: SPECIALIST, GENERALIST MULTISPORT, INTERSPORT NORDIC, Lifestyle/DAY | S3: Gore-Tex | T3: None | W3: CO | X3: 714.72 | AA3: A | AB3: 1000 | AC3: 300 | AD3: 608172 | AE3: 4 | AF3: Outdoor | AG3: Day Hiking | AH3: Outdoor / Hiking [MATCH] | AI3: Shell | AJ3: Jacket | AK3: 2L | AL3: Y
A4: SS27 | B4: TRUE | C4: 608596 | D4: Alert GTX Jacket Men AF | E4: Apparel | F4: OUT | G4: Shell | H4: ABS Exclusive | I4: Men | K4: TRUE | L4: FALSE | M4: 3800 | N4: 2.1 | O4: 1809.52 | P4: 0.61495866 | Q4: Good | R4: ASIA | S4: Gore-Tex | T4: None | U4: Asia Fit version of Alert GTX Jacket Men 608172 | V4: ASIA | W4: CO | X4: 696.74 | AA4: C | AB4: 1000 | AC4: 300 | AD4: 608596 | AE4: 4 | AF4: Outdoor | AG4: Day Hiking | AH4: Outdoor / Hiking [MATCH] | AI4: Shell | AJ4: Jacket | AK4: 2L | AL4: Y
A5: SS27 | B5: TRUE | C5: 608192 | D5: Alert GTX Jacket Women | E5: Apparel | F5: OUT | G5: Shell | H5: Inline | I5: Women | K5: TRUE | L5: FALSE | M5: 3800 | N5: 2.1 | O5: 1809.52 | P5: 0.65159269 | Q5: Good | R5: SPECIALIST, GENERALIST MULTISPORT, INTERSPORT NORDIC, Lifestyle/DAY | S5: Gore-Tex | T5: None | W5: CO | X5: 630.45 | AA5: A | AB5: 1000 | AC5: 300 | AD5: 608192 | AE5: 4 | AF5: Outdoor | AG5: Day Hiking | AH5: Outdoor / Hiking [MATCH] | AI5: Shell | AJ5: Jacket | AK5: 2L | AL5: Y
A6: SS27 | B6: TRUE | C6: 607645 | D6: Alert Mid Pant Men | E6: Apparel | F6: OUT | G6: Legwear | H6: Inline | I6: Men | K6: TRUE | L6: FALSE | M6: 1700 | N6: 2.1 | O6: 809.52 | P6: 0.61785997 | Q6: Better | R6: SPECIALIST, GENERALIST MULTISPORT, INTERSPORT NORDIC, Lifestyle/DAY | S6: None | T6: None | W6: CO | X6: 309.35 | AA6: A | AB6: 2000 | AC6: 500 | AD6: 607645 | AE6: 4 | AF6: Outdoor | AG6: Trekking | AH6: Outdoor / Mountaineering [CHECK - activity] | AI6: Softshell | AJ6: Pant | AK6: Classic Softshell | AL6: N
A7: SS27 | B7: TRUE | C7: 607649 | D7: Alert Mid Pant Women | E7: Apparel | F7: OUT | G7: Legwear | H7: Inline | I7: Women | K7: TRUE | L7: FALSE | M7: 1700 | N7: 2.1 | O7: 809.52 | P7: 0.64852011 | Q7: Better | R7: SPECIALIST, GENERALIST MULTISPORT, INTERSPORT NORDIC, Lifestyle/DAY | S7: None | T7: None | W7: CO | X7: 284.53 | AA7: A | AB7: 2000 | AC7: 500 | AD7: 607649 | AE7: 4 | AF7: Outdoor | AG7: Trekking | AH7: Outdoor / Mountaineering [CHECK - activity] | AI7: Softshell | AJ7: Pant | AK7: Classic Softshell | AL7: N
A8: SS27 | B8: TRUE | C8: 608158 | D8: Alert Mid Shorts Men | E8: Apparel | F8: OUT | G8: Legwear | H8: Inline | I8: Men | K8: TRUE | L8: FALSE | M8: 1200 | N8: 2.1 | O8: 571.43 | Q8: Better | R8: SPECIALIST, GENERALIST MULTISPORT, INTERSPORT NORDIC | S8: None | T8: None | W8: CO | X8: 212.18 | AA8: A | AB8: 2000 | AC8: 500 | AD8: 608158 | AE8: 5 | AF8: Essentials | AG8: Trekking | AI8: Softshell | AJ8: Shorts | AK8: Classic Softshell | AL8: N
A9: SS27 | B9: TRUE | C9: 608178 | D9: Alert Mid Shorts Women | E9: Apparel | F9: OUT | G9: Legwear | H9: Inline | I9: Women | K9: TRUE | L9: FALSE | M9: 1200 | N9: 2.1 | O9: 571.43 | Q9: Better | R9: SPECIALIST, GENERALIST MULTISPORT, INTERSPORT NORDIC | S9: None | T9: None | W9: CO | X9: 198.41 | AA9: A | AB9: 2000 | AC9: 500 | AD9: 608178 | AE9: 5 | AF9: Essentials | AG9: Trekking | AI9: Softshell | AJ9: Shorts | AK9: Classic Softshell | AL9: N
A10: SS27 | B10: TRUE | C10: 608250 | D10: Apex II Hood Men | E10: Apparel | F10: OUT | G10: Softshell | H10: ABS | I10: Men | K10: TRUE | L10: FALSE | M10: 2200 | N10: 2.1 | O10: 1047.62 | Q10: Better | R10: BIG BOX, SPECIALIST, GENERALIST MULTISPORT | S10: None | T10: None | V10: XXL | W10: CO | X10: 342 | AA10: C | AB10: 800 | AC10: 500 | AD10: 608250 | AE10: 1 | AF10: Essentials | AG10: Active Essentials | AI10: Softshell | AJ10: Hooded Jacket | AK10: Classic Softshell | AL10: N
A11: SS27 | B11: TRUE | C11: 608249 | D11: Apex II Hood Women | E11: Apparel | F11: OUT | G11: Softshell | H11: ABS | I11: Women | K11: TRUE | L11: FALSE | M11: 2200 | N11: 2.1 | O11: 1047.62 | Q11: Better | R11: BIG BOX, SPECIALIST, GENERALIST MULTISPORT | S11: None | T11: None | V11: XXL | W11: CO | X11: 319.09 | AA11: C | AB11: 800 | AC11: 500 | AD11: 608249 | AE11: 1 | AF11: Essentials | AG11: Active Essentials | AI11: Softshell | AJ11: Hooded Jacket | AK11: Classic Softshell | AL11: N
A12: SS27 | B12: TRUE | C12: 607766 | D12: Aria Proof Parka Women | E12: Apparel | F12: OUT | G12: Shell | H12: Inline | I12: Women | K12: TRUE | L12: FALSE | M12: 2500 | N12: 2.1 | O12: 1190.48 | Q12: Better | R12: SPECIALIST, GENERALIST MULTISPORT, INTERSPORT NORDIC | S12: Proof | T12: None | V12: XXL | W12: CO | X12: 498.54 | AA12: B | AB12: 1000 | AC12: 300 | AD12: 607766 | AE12: 3 | AF12: Essentials | AG12: Daily Essentials | AI12: Shell | AJ12: Parka | AK12: 2L | AL12: Y
A13: SS27 | B13: TRUE | C13: 608395 | D13: Aska Proof Jacket Men | E13: Apparel | F13: OUT | G13: Shell | H13: ABS | I13: Men | K13: TRUE | L13: FALSE | M13: 2200 | N13: 2.1 | O13: 1047.62 | Q13: Good | R13: INTERSPORT NORDIC | S13: Proof | T13: None | U13: Copy of Breeze Proof Jacket 607680 | V13: Intersport | W13: CO | X13: 345.72 | AA13: A | AB13: 1000 | AC13: 300 | AD13: 608395 | AE13: 3 | AF13: Essentials | AG13: Active Essentials | AI13: Shell | AJ13: Jacket | AK13: 2L | AL13: Y
A14: SS27 | B14: TRUE | C14: 608396 | D14: Aska Proof Jacket Women | E14: Apparel | F14: OUT | G14: Shell | H14: ABS | I14: Women | K14: TRUE | L14: FALSE | M14: 2200 | N14: 2.1 | O14: 1047.62 | Q14: Good | R14: INTERSPORT NORDIC | S14: Proof | T14: None | U14: Copy of Breeze Proof Jacket 607681 | V14: Intersport | W14: CO | X14: 322.11 | AA14: A | AB14: 1000 | AC14: 300 | AD14: 608396 | AE14: 4 | AF14: Essentials | AG14: Active Essentials | AI14: Shell | AJ14: Jacket | AK14: 2L | AL14: Y
A15: SS27 | B15: TRUE | C15: 608397 | D15: Aska Proof Pant Men | E15: Apparel | F15: OUT | G15: Shell | H15: ABS | I15: Men | K15: TRUE | L15: FALSE | M15: 1700 | N15: 2.1 | O15: 809.52 | Q15: Good | R15: INTERSPORT NORDIC | S15: Proof | T15: None | V15: Intersport | W15: CO | X15: 269.65 | AA15: A | AB15: 1000 | AC15: 300 | AD15: 608397 | AE15: 1 | AF15: Essentials | AG15: Active Essentials | AI15: Shell | AJ15: Pant | AK15: 2L | AL15: Y
A16: SS27 | B16: TRUE | C16: 608398 | D16: Aska Proof Pant Women | E16: Apparel | F16: OUT | G16: Shell | H16: ABS | I16: Women | K16: TRUE | L16: FALSE | M16: 1700 | N16: 2.1 | O16: 809.52 | Q16: Good | R16: INTERSPORT NORDIC | S16: Proof | T16: None | V16: Intersport | W16: CO | X16: 263.72 | AA16: A | AB16: 1000 | AC16: 300 | AD16: 608398 | AE16: 1 | AF16: Essentials | AG16: Active Essentials | AI16: Shell | AJ16: Pant | AK16: 2L | AL16: Y
A17: SS27 | B17: TRUE | C17: 608656 | D17: Aska Softshell Hood Men | E17: Apparel | F17: OUT | G17: Softshell | H17: ABS | I17: Men | K17: FALSE | L17: FALSE | M17: 1800 | N17: 2.1 | O17: 714.29 | Q17: Good | R17: INTERSPORT NORDIC | S17: None | T17: None | U17: copy of korp softshell hood 608552 | V17: Intersport | W17: NEW | X17: 241.92 | AA17: A | AB17: 1000 | AC17: 300 | AD17: 608656 | AE17: 4 | AF17: Outdoor | AG17: Day Hiking | AH17: Outdoor / Hiking [MATCH] | AI17: Softshell | AJ17: Hooded Jacket | AK17: Classic Softshell | AL17: N | AM17: Check - Day Hike? | WB: not in this workbook — cannot verify
A18: SS27 | B18: TRUE | C18: 608658 | D18: Aska Softshell Hood Women | E18: Apparel | F18: OUT | G18: Softshell | H18: ABS | I18: Women | K18: FALSE | L18: FALSE | M18: 1800 | N18: 2.1 | O18: 714.29 | Q18: Good | R18: INTERSPORT NORDIC | S18: None | T18: None | U18: copy of korp softshell hood 608553 | V18: Intersport | W18: NEW | X18: 221.62 | AA18: A | AB18: 1000 | AC18: 300 | AD18: 608658 | AE18: 4 | AF18: Outdoor | AG18: Day Hiking | AH18: Outdoor / Hiking [MATCH] | AI18: Softshell | AJ18: Hooded Jacket | AK18: Classic Softshell | AL18: N | AM18: Check - Day Hike? | WB: not in this workbook — cannot verify
A19: SS27 | B19: TRUE | C19: 608657 | D19: Aska Softshell Pant Men | E19: Apparel | F19: OUT | G19: Softshell | H19: ABS | I19: Men | K19: FALSE | L19: FALSE | M19: 1400 | N19: 2.1 | O19: 571.43 | Q19: Good | R19: INTERSPORT NORDIC | S19: None | T19: None | U19: copy of korp softshell Pant 608554 | V19: Intersport | W19: NEW | X19: 200.22 | AA19: A | AB19: 1000 | AC19: 300 | AD19: 608657 | AE19: 1 | AF19: Outdoor | AG19: Day Hiking | AH19: Outdoor / Hiking [MATCH] | AI19: Softshell | AJ19: Pant | AK19: Classic Softshell | AL19: N | AM19: Check - Day Hike? | WB: not in this workbook — cannot verify
A20: SS27 | B20: TRUE | C20: 608659 | D20: Aska Softshell Pant Women | E20: Apparel | F20: OUT | G20: Softshell | H20: ABS | I20: Women | K20: FALSE | L20: FALSE | M20: 1400 | N20: 2.1 | O20: 571.43 | Q20: Good | R20: INTERSPORT NORDIC | S20: None | T20: None | U20: copy of korp softshell Pant 608555 | V20: Intersport | W20: NEW | X20: 193.69 | AA20: A | AB20: 1000 | AC20: 300 | AD20: 608659 | AE20: 1 | AF20: Outdoor | AG20: Day Hiking | AH20: Outdoor / Hiking [MATCH] | AI20: Softshell | AJ20: Pant | AK20: Classic Softshell | AL20: N | AM20: Check - Day Hike? | WB: not in this workbook — cannot verify
A21: SS27 | B21: TRUE | C21: 607593 | D21: Astral GTX II Jacket Men | E21: Apparel | F21: OUT | G21: Shell | H21: Inline | I21: Men | K21: TRUE | L21: FALSE | M21: 4500 | N21: 2.1 | O21: 2142.86 | Q21: Better | R21: SPECIALIST, GENERALIST MULTISPORT, INTERSPORT NORDIC | S21: Gore-Tex | T21: None | W21: CO | X21: 1032.36 | AA21: A | AB21: 1000 | AC21: 300 | AD21: 607593 | AE21: 5 | AF21: Essentials | AG21: Active Essentials | AH21: Essentials / Essentials/Everyday [MATCH] | AI21: Shell | AJ21: Jacket | AK21: 2L | AL21: Y
A22: SS27 | B22: TRUE | C22: 607563 | D22: Astral GTX II Jacket Women | E22: Apparel | F22: OUT | G22: Shell | H22: Inline | I22: Women | K22: TRUE | L22: FALSE | M22: 4500 | N22: 2.1 | O22: 2142.86 | Q22: Better | R22: SPECIALIST, GENERALIST MULTISPORT, INTERSPORT NORDIC | S22: Gore-Tex | T22: None | W22: CO | X22: 919.5 | AA22: A | AB22: 1000 | AC22: 300 | AD22: 607563 | AE22: 5 | AF22: Essentials | AG22: Active Essentials | AH22: Essentials / Essentials/Everyday [MATCH] | AI22: Shell | AJ22: Jacket | AK22: 2L | AL22: Y
A23: SS27 | B23: TRUE | C23: 608587 | D23: Brand Five Panel Cap | E23: Apparel | F23: DAY | G23: Accessories | H23: Inline | I23: Unisex | K23: TRUE | L23: FALSE | M23: 450 | N23: 2.1 | O23: 214.29 | Q23: Better | R23: SPECIALIST, GENERALIST MULTISPORT, INTERSPORT NORDIC, BIG BOX | S23: None | T23: None | W23: CO | X23: 67.26 | AA23: B | AB23: 600 | AC23: 600 | AD23: 608587 | AE23: 6 | AF23: Essentials | AG23: Active Essentials | AI23: Accessories | AJ23: Headwear | AK23: Cap | AL23: N
A24: SS27 | B24: TRUE | C24: 607680 | D24: Breeze Proof Jacket Men | E24: Apparel | F24: OUT | G24: Shell | H24: Inline | I24: Men | K24: TRUE | L24: FALSE | M24: 2000 | N24: 2.1 | O24: 952.38 | Q24: Good | R24: SPECIALIST, GENERALIST MULTISPORT, INTERSPORT NORDIC, Lifestyle/DAY | S24: Proof | T24: None | W24: CO | X24: 334.57 | AA24: A | AB24: 1000 | AC24: 300 | AD24: 607680 | AE24: 7 | AF24: Essentials | AG24: Daily Essentials | AH24: Outdoor / Hiking [CHECK - collection + activity] | AI24: Shell | AJ24: Jacket | AK24: 2L | AL24: Y
A25: SS27 | B25: TRUE | C25: 607681 | D25: Breeze Proof Jacket Women | E25: Apparel | F25: OUT | G25: Shell | H25: Inline | I25: Women | K25: TRUE | L25: FALSE | M25: 2000 | N25: 2.1 | O25: 952.38 | Q25: Good | R25: SPECIALIST, GENERALIST MULTISPORT, INTERSPORT NORDIC, Lifestyle/DAY | S25: Proof | T25: None | W25: CO | X25: 314.78 | AA25: A | AB25: 1000 | AC25: 300 | AD25: 607681 | AE25: 6 | AF25: Essentials | AG25: Daily Essentials | AH25: Outdoor / Hiking [CHECK - collection + activity] | AI25: Shell | AJ25: Jacket | AK25: 2L | AL25: Y
A26: SS27 | B26: TRUE | C26: 608351 | D26: Buteo Mid II Jacket Men | E26: Apparel | F26: OUT | G26: Midlayer | H26: Inline | I26: Men | K26: TRUE | L26: FALSE | M26: 900 | N26: 2.1 | O26: 428.57 | Q26: Good | R26: SPECIALIST, GENERALIST MULTISPORT, INTERSPORT NORDIC, Lifestyle/DAY | S26: Polartec | T26: None | W26: CO | X26: 145.36 | Y26: 605073 | Z26: Buteo Mid Jacket Men | AA26: A | AB26: 1000 | AC26: 300 | AD26: 608351 | AE26: 6 | AF26: Essentials | AG26: Active Essentials | AH26: Essentials / Essentials/Everyday [MATCH] | AI26: Fleece/Midlayer | AJ26: Jacket | AK26: Midweight | AL26: N
A27: SS27 | B27: TRUE | C27: 608352 | D27: Buteo Mid II Jacket Women | E27: Apparel | F27: OUT | G27: Midlayer | H27: Inline | I27: Women | K27: TRUE | L27: FALSE | M27: 900 | N27: 2.1 | O27: 428.57 | Q27: Good | R27: SPECIALIST, GENERALIST MULTISPORT, INTERSPORT NORDIC, Lifestyle/DAY | S27: Polartec | T27: None | W27: CO | X27: 137.49 | Y27: 605074 | Z27: Buteo Mid Jacket Women | AA27: A | AB27: 1000 | AC27: 300 | AD27: 608352 | AE27: 6 | AF27: Essentials | AG27: Active Essentials | AH27: Essentials / Essentials/Everyday [MATCH] | AI27: Fleece/Midlayer | AJ27: Jacket | AK27: Midweight | AL27: N
A28: SS27 | B28: TRUE | C28: 608421 | D28: Chaos GTX II Jacket Men | E28: Apparel | F28: OUT | G28: Shell | H28: ABS | I28: Men | K28: TRUE | L28: FALSE | M28: 3500 | N28: 2.1 | O28: 1666.67 | Q28: Good | R28: INTERSPORT NORDIC | S28: Gore-Tex | T28: None | V28: Intersport | W28: CO | X28: 545.72 | AA28: B | AB28: 1000 | AC28: 300 | AD28: 608421 | AE28: 3 | AF28: Essentials | AG28: Active Essentials | AH28: Essentials / Essentials/Everyday [MATCH] | AI28: Shell | AJ28: Jacket | AK28: 2L | AL28: Y
A29: SS27 | B29: TRUE | C29: 608422 | D29: Chaos GTX II Jacket Women | E29: Apparel | F29: OUT | G29: Shell | H29: ABS | I29: Women | K29: TRUE | L29: FALSE | M29: 3500 | N29: 2.1 | O29: 1666.67 | Q29: Good | R29: INTERSPORT NORDIC | S29: Gore-Tex | T29: None | V29: Intersport | W29: CO | X29: 515.04 | AA29: B | AB29: 1000 | AC29: 300 | AD29: 608422 | AE29: 3 | AF29: Outdoor | AG29: Active Essentials | AH29: Essentials / Essentials/Everyday [CHECK - collection] | AI29: Shell | AJ29: Jacket | AK29: 2L | AL29: Y
A30: SS27 | B30: TRUE | C30: 607646 | D30: Front Flex Pant Men | E30: Apparel | F30: OUT | G30: Legwear | H30: Inline | I30: Men | K30: TRUE | L30: FALSE | M30: 1500 | N30: 2.1 | O30: 714.29 | Q30: Better | R30: SPECIALIST, GENERALIST MULTISPORT, INTERSPORT NORDIC | S30: None | T30: None | W30: CO | X30: 290.96 | AA30: B | AB30: 2000 | AC30: 500 | AD30: 607646 | AE30: 1 | AF30: Outdoor | AG30: Trekking | AH30: Outdoor / Mountaineering [CHECK - activity] | AI30: Softshell | AJ30: Pant | AK30: Classic Softshell | AL30: N
A31: SS27 | B31: TRUE | C31: 607650 | D31: Front Flex Pant Women | E31: Apparel | F31: OUT | G31: Legwear | H31: Inline | I31: Women | K31: TRUE | L31: FALSE | M31: 1500 | N31: 2.1 | O31: 714.29 | Q31: Better | R31: SPECIALIST, GENERALIST MULTISPORT, INTERSPORT NORDIC | S31: None | T31: None | W31: CO | X31: 274.38 | AA31: B | AB31: 2000 | AC31: 500 | AD31: 607650 | AE31: 1 | AF31: Outdoor | AG31: Trekking | AH31: Outdoor / Mountaineering [CHECK - activity] | AI31: Softshell | AJ31: Pant | AK31: Classic Softshell | AL31: N
A32: SS27 | B32: TRUE | C32: 607823 | D32: Front Proof II Jacket Men | E32: Apparel | F32: OUT | G32: Shell | H32: Inline | I32: Men | K32: TRUE | L32: FALSE | M32: 3300 | N32: 2.1 | O32: 1571.43 | Q32: Better | R32: SPECIALIST, GENERALIST MULTISPORT, INTERSPORT NORDIC, Lifestyle/DAY | S32: Proof | T32: None | W32: CO | X32: 671.22 | AA32: A | AB32: 1000 | AC32: 300 | AD32: 607823 | AE32: 5 | AF32: Outdoor | AG32: Trekking | AH32: Outdoor / Trekking [MATCH] | AI32: Shell | AJ32: Jacket | AK32: 3L | AL32: Y
A33: SS27 | B33: TRUE | C33: 607821 | D33: Front Proof II Jacket Women | E33: Apparel | F33: OUT | G33: Shell | H33: Inline | I33: Women | K33: TRUE | L33: FALSE | M33: 3300 | N33: 2.1 | O33: 1571.43 | Q33: Better | R33: SPECIALIST, GENERALIST MULTISPORT, INTERSPORT NORDIC, Lifestyle/DAY | S33: Proof | T33: None | W33: CO | X33: 637.9 | AA33: A | AB33: 1000 | AC33: 300 | AD33: 607821 | AE33: 5 | AF33: Outdoor | AG33: Trekking | AH33: Outdoor / Trekking [MATCH] | AI33: Shell | AJ33: Jacket | AK33: 3L | AL33: Y
A34: SS27 | B34: TRUE | C34: 608652 | D34: Gabbro II Pant Men | E34: Apparel | F34: OUT | G34: Softshell | H34: ABS | I34: Men | K34: TRUE | L34: FALSE | M34: 2200 | N34: 2.1 | O34: 1047.62 | Q34: Better | R34: BIG BOX, SPECIALIST, GENERALIST MULTISPORT | S34: None | T34: None | V34: XXL | W34: CO | X34: 323.46 | Y34: 608247 | Z34: Gabbro Pant Men | AA34: C | AB34: 1000 | AC34: 300 | AD34: 608652 | AE34: 1 | AF34: Essentials | AG34: Active Essentials | AI34: Softshell | AJ34: Pant | AK34: Classic Softshell | AL34: N
A35: SS27 | B35: TRUE | C35: 608653 | D35: Gabbro II Pant Women | E35: Apparel | F35: OUT | G35: Softshell | H35: ABS | I35: Women | K35: TRUE | L35: FALSE | M35: 2200 | N35: 2.1 | O35: 1047.62 | Q35: Better | R35: BIG BOX, SPECIALIST, GENERALIST MULTISPORT | S35: None | T35: None | V35: XXL | W35: CO | X35: 301.45 | Y35: 608248 | Z35: Gabbro Pant Women | AA35: C | AB35: 1000 | AC35: 300 | AD35: 608653 | AE35: 1 | AF35: Essentials | AG35: Active Essentials | AI35: Softshell | AJ35: Pant | AK35: Classic Softshell | AL35: N
A36: SS27 | B36: TRUE | C36: 608204 | D36: Haglöfs Bandana | E36: Apparel | F36: DAY | G36: Accessories | H36: Inline | I36: Unisex | K36: TRUE | L36: FALSE | M36: 400 | N36: 2.1 | O36: 190.48 | Q36: Better | R36: SPECIALIST, GENERALIST MULTISPORT, INTERSPORT NORDIC | S36: None | T36: None | W36: CO | X36: 76.85 | AA36: B | AB36: 500 | AC36: 500 | AD36: 608204 | AE36: 4 | AF36: Essentials | AG36: Daily Essentials | AI36: Accessories | AJ36: Headwear | AK36: Bandana | AL36: N
A37: SS27 | B37: TRUE | C37: 607656 | D37: Haglöfs Cap | E37: Apparel | F37: DAY | G37: Accessories | H37: Inline | I37: Unisex | K37: TRUE | L37: FALSE | M37: 400 | N37: 2.1 | O37: 190.48 | Q37: Good | R37: SPECIALIST, GENERALIST MULTISPORT, INTERSPORT NORDIC, BIG BOX | S37: None | T37: None | W37: CO | X37: 68.88 | AA37: A | AB37: 600 | AC37: 600 | AD37: 607656 | AE37: 5 | AF37: Essentials | AG37: Daily Essentials | AI37: Accessories | AJ37: Headwear | AK37: Cap | AL37: N
A38: SS27 | B38: TRUE | C38: 608164 | D38: Haglöfs Hoodie Men | E38: Apparel | F38: DAY | G38: Midlayer | H38: Inline | I38: Men | K38: TRUE | L38: FALSE | M38: 1500 | N38: 2.1 | O38: 714.29 | Q38: Better | R38: SPECIALIST, GENERALIST MULTISPORT, INTERSPORT NORDIC | S38: None | T38: None | W38: CO | X38: 318.03 | AA38: B | AB38: 500 | AC38: 500 | AD38: 608164 | AE38: 3 | AF38: Essentials | AG38: Daily Essentials | AH38: Essentials / Essentials/Everyday [MATCH] | AI38: Fleece/Midlayer | AJ38: Hooded Jacket | AK38: Midweight | AL38: N
A39: SS27 | B39: TRUE | C39: 608184 | D39: Haglöfs Hoodie Women | E39: Apparel | F39: DAY | G39: Midlayer | H39: Inline | I39: Women | K39: TRUE | L39: FALSE | M39: 1500 | N39: 2.1 | O39: 714.29 | Q39: Better | R39: SPECIALIST, GENERALIST MULTISPORT, INTERSPORT NORDIC | S39: None | T39: None | W39: CO | X39: 285.58 | AA39: B | AB39: 500 | AC39: 500 | AD39: 608184 | AE39: 3 | AF39: Essentials | AG39: Daily Essentials | AH39: Essentials / Essentials/Everyday [MATCH] | AI39: Fleece/Midlayer | AJ39: Hooded Jacket | AK39: Midweight | AL39: N
A40: SS27 | B40: TRUE | C40: 607660 | D40: Haglöfs LS Tee Men | E40: Apparel | F40: DAY | G40: Tops | H40: Inline | I40: Men | K40: TRUE | L40: FALSE | M40: 800 | N40: 2.1 | O40: 380.95 | Q40: Better | R40: SPECIALIST, GENERALIST MULTISPORT, INTERSPORT NORDIC, BIG BOX, Lifestyle/DAY | S40: None | T40: None | W40: CO | X40: 159.59 | AA40: B | AB40: 500 | AC40: 500 | AD40: 607660 | AE40: 5 | AF40: Essentials | AG40: Daily Essentials | AH40: Essentials / Essentials/Everyday [MATCH] | AI40: Tops | AJ40: Long Sleeve | AK40: Cotton/Graphic Tee | AL40: N
A41: SS27 | B41: TRUE | C41: 607663 | D41: Haglöfs LS Tee Women | E41: Apparel | F41: DAY | G41: Tops | H41: Inline | I41: Women | K41: TRUE | L41: FALSE | M41: 800 | N41: 2.1 | O41: 380.95 | Q41: Best | R41: SPECIALIST, GENERALIST MULTISPORT, INTERSPORT NORDIC, BIG BOX, Lifestyle/DAY | S41: None | T41: None | W41: CO | X41: 149.86 | AA41: B | AB41: 500 | AC41: 500 | AD41: 607663 | AE41: 5 | AF41: Essentials | AG41: Daily Essentials | AH41: Essentials / Essentials/Everyday [MATCH] | AI41: Tops | AJ41: Long Sleeve | AK41: Cotton/Graphic Tee | AL41: N
A42: SS27 | B42: TRUE | C42: 607868 | D42: Haglöfs LX Hat | E42: Apparel | F42: DAY | G42: Accessories | H42: Inline | I42: Unisex | K42: TRUE | L42: FALSE | M42: 500 | N42: 2.1 | O42: 238.1 | Q42: Better | R42: SPECIALIST, GENERALIST MULTISPORT, INTERSPORT NORDIC | S42: None | T42: None | W42: CO | X42: 78.47 | AA42: A | AB42: 600 | AC42: 600 | AD42: 607868 | AE42: 4 | AF42: Essentials | AG42: Daily Essentials | AI42: Accessories | AJ42: Headwear | AK42: Cap | AL42: N
A43: SS27 | B43: TRUE | C43: 607658 | D43: Haglöfs Tee Men | E43: Apparel | F43: DAY | G43: Tops | H43: Inline | I43: Men | K43: TRUE | L43: FALSE | M43: 700 | N43: 2.1 | O43: 333.33 | Q43: Best | R43: SPECIALIST, GENERALIST MULTISPORT, INTERSPORT NORDIC, BIG BOX, Lifestyle/DAY | S43: None | T43: None | W43: CO | X43: 127.15 | AA43: A | AB43: 500 | AC43: 500 | AD43: 607658 | AE43: 5 | AF43: Essentials | AG43: Daily Essentials | AH43: Essentials / Essentials/Everyday [MATCH] | AI43: Tops | AJ43: Tee | AK43: Cotton/Graphic Tee | AL43: N
A44: SS27 | B44: TRUE | C44: 607665 | D44: Haglöfs Tee Women | E44: Apparel | F44: DAY | G44: Tops | H44: Inline | I44: Women | K44: TRUE | L44: FALSE | M44: 700 | N44: 2.1 | O44: 333.33 | Q44: Best | R44: SPECIALIST, GENERALIST MULTISPORT, INTERSPORT NORDIC, BIG BOX, Lifestyle/DAY | S44: None | T44: None | W44: CO | X44: 120.66 | AA44: A | AB44: 500 | AC44: 500 | AD44: 607665 | AE44: 5 | AF44: Essentials | AG44: Daily Essentials | AH44: Essentials / Essentials/Everyday [MATCH] | AI44: Tops | AJ44: Tee | AK44: Cotton/Graphic Tee | AL44: N
A45: SS27 | B45: TRUE | C45: 607867 | D45: Haglöfs Trucker Cap | E45: Apparel | F45: DAY | G45: Accessories | H45: Inline | I45: Unisex | K45: TRUE | L45: FALSE | M45: 400 | N45: 2.1 | O45: 190.48 | Q45: Better | R45: SPECIALIST, GENERALIST MULTISPORT, INTERSPORT NORDIC | S45: None | T45: None | V45: XXL | W45: CO | X45: 67.87 | AA45: B | AB45: 600 | AC45: 600 | AD45: 607867 | AE45: 4 | AF45: Essentials | AG45: Daily Essentials | AI45: Accessories | AJ45: Headwear | AK45: Cap | AL45: N
A46: SS27 | B46: TRUE | C46: 608097 | D46: Hede Down Hood Men | E46: Apparel | F46: DAY | G46: Insulation | H46: Inline | I46: Men | K46: TRUE | L46: FALSE | M46: 2800 | N46: 2.1 | O46: 1333.33 | Q46: Better | R46: SPECIALIST, Lifestyle/DAY | S46: Down | T46: None | W46: CO | X46: 510.16 | AA46: B | AB46: 800 | AC46: 100 | AD46: 608097 | AE46: 3 | AF46: Essentials | AG46: Active Essentials | AH46: Essentials / Essentials/Everyday [MATCH] | AI46: Insulation | AJ46: Hooded Jacket | AK46: Lightweight Down | AL46: N
A47: SS27 | B47: TRUE | C47: 608098 | D47: Hede Down Hood Women | E47: Apparel | F47: DAY | G47: Insulation | H47: Inline | I47: Women | K47: TRUE | L47: FALSE | M47: 2800 | N47: 2.1 | O47: 1333.33 | Q47: Better | R47: SPECIALIST, Lifestyle/DAY | S47: Down | T47: None | W47: CO | X47: 455.64 | AA47: B | AB47: 800 | AC47: 100 | AD47: 608098 | AE47: 3 | AF47: Essentials | AG47: Active Essentials | AH47: Essentials / Essentials/Everyday [MATCH] | AI47: Insulation | AJ47: Hooded Jacket | AK47: Lightweight Down | AL47: N
A48: SS27 | B48: FALSE | C48: 608100 | D48: Hede Down Vest Men | E48: Apparel | F48: DAY | G48: Insulation | H48: Inline | I48: Men | K48: TRUE | L48: FALSE | M48: 2000 | N48: 2.1 | O48: 952.38 | Q48: Better | R48: SPECIALIST, Lifestyle/DAY | S48: Down | T48: None | U48: Sell from FW26 Stock | W48: CO | X48: 335.12 | AA48: B | AB48: 800 | AC48: 100 | AD48: 608100 | AE48: 0 | AF48: Essentials | AG48: Active Essentials | AH48: Essentials / Essentials/Everyday [MATCH] | AI48: Insulation | AJ48: Vest | AK48: Lightweight Down | AL48: N
A49: SS27 | B49: FALSE | C49: 608101 | D49: Hede Down Vest Women | E49: Apparel | F49: DAY | G49: Insulation | H49: Inline | I49: Women | K49: TRUE | L49: FALSE | M49: 2000 | N49: 2.1 | O49: 952.38 | Q49: Better | R49: SPECIALIST, Lifestyle/DAY | S49: Down | T49: None | U49: Sell from FW26 Stock | W49: CO | X49: 301.81 | AA49: B | AB49: 800 | AC49: 100 | AD49: 608101 | AE49: 0 | AF49: Essentials | AG49: Active Essentials | AH49: Essentials / Essentials/Everyday [MATCH] | AI49: Insulation | AJ49: Vest | AK49: Lightweight Down | AL49: N
A50: SS27 | B50: TRUE | C50: 608545 | D50: Holm GTX Pant Men | E50: Apparel | F50: OUT | G50: Shell | H50: Inline | I50: Men | K50: FALSE | L50: FALSE | M50: 2800 | N50: 2.1 | O50: 1190.48 | Q50: Better | R50: SPECIALIST, GENERALIST MULTISPORT, INTERSPORT NORDIC | S50: Gore-Tex | T50: None | W50: NEW | X50: 560.79 | AA50: A | AB50: 1000 | AC50: 300 | AD50: 608545 | AE50: 1 | AF50: Outdoor | AG50: Day Hiking | AH50: Essentials / Essentials/Everyday [CHECK - collection + activity] | AI50: Shell | AJ50: Pant | AK50: 2L | AL50: Y
A51: SS27 | B51: TRUE | C51: 608548 | D51: Holm GTX Pant Women | E51: Apparel | F51: OUT | G51: Shell | H51: Inline | I51: Women | K51: FALSE | L51: FALSE | M51: 2800 | N51: 2.1 | O51: 1190.48 | Q51: Better | R51: SPECIALIST, GENERALIST MULTISPORT, INTERSPORT NORDIC | S51: Gore-Tex | T51: None | W51: NEW | X51: 536.73 | AA51: A | AB51: 1000 | AC51: 300 | AD51: 608548 | AE51: 1 | AF51: Outdoor | AG51: Day Hiking | AH51: Essentials / Essentials/Everyday [CHECK - collection + activity] | AI51: Shell | AJ51: Pant | AK51: 2L | AL51: Y
A52: SS27 | B52: TRUE | C52: 607625 | D52: Kaise Wool LS Tee Men | E52: Apparel | F52: OUT | G52: Tops | H52: Inline | I52: Men | K52: TRUE | L52: FALSE | M52: 900 | N52: 2.1 | O52: 428.57 | Q52: Better | R52: DTC | S52: None | T52: None | V52: DTC | W52: CO | X52: 164.45 | AA52: C | AB52: 1000 | AC52: 300 | AD52: 607625 | AE52: 3 | AF52: Essentials | AG52: Active Essentials | AH52: Essentials / Essentials/Everyday [MATCH] | AI52: Tops | AJ52: Long Sleeve | AK52: Lightweight Wool | AL52: N
A53: SS27 | B53: TRUE | C53: 607627 | D53: Kaise Wool LS Tee Women | E53: Apparel | F53: OUT | G53: Tops | H53: Inline | I53: Women | K53: TRUE | L53: FALSE | M53: 900 | N53: 2.1 | O53: 428.57 | Q53: Better | R53: DTC | S53: None | T53: None | V53: DTC | W53: CO | X53: 145.25 | AA53: C | AB53: 1000 | AC53: 300 | AD53: 607627 | AE53: 3 | AF53: Essentials | AG53: Active Essentials | AH53: Essentials / Essentials/Everyday [MATCH] | AI53: Tops | AJ53: Long Sleeve | AK53: Lightweight Wool | AL53: N
A54: SS27 | B54: TRUE | C54: 607626 | D54: Kaise Wool Tee Men | E54: Apparel | F54: OUT | G54: Tops | H54: Inline | I54: Men | K54: TRUE | L54: FALSE | M54: 750 | N54: 2.1 | O54: 357.14 | Q54: Better | R54: DTC | S54: None | T54: None | V54: DTC | W54: CO | X54: 134.4 | AA54: C | AB54: 1000 | AC54: 300 | AD54: 607626 | AE54: 3 | AF54: Essentials | AG54: Active Essentials | AH54: Essentials / Essentials/Everyday [MATCH] | AI54: Tops | AJ54: Tee | AK54: Cotton/Graphic Tee | AL54: N
A55: SS27 | B55: TRUE | C55: 607628 | D55: Kaise Wool Tee Women | E55: Apparel | F55: OUT | G55: Tops | H55: Inline | I55: Women | K55: TRUE | L55: FALSE | M55: 750 | N55: 2.1 | O55: 357.14 | Q55: Better | R55: DTC | S55: None | T55: None | V55: DTC | W55: CO | X55: 124.05 | AA55: C | AB55: 1000 | AC55: 300 | AD55: 607628 | AE55: 3 | AF55: Essentials | AG55: Active Essentials | AH55: Essentials / Essentials/Everyday [MATCH] | AI55: Tops | AJ55: Tee | AK55: Cotton/Graphic Tee | AL55: N
A56: SS27 | B56: TRUE | C56: 608487 | D56: Steep 2.5L Jacket Men | E56: Apparel | F56: OUT | G56: Shell | H56: Inline | I56: Men | K56: FALSE | L56: FALSE | M56: 2500 | N56: 2.1 | O56: 1190.48 | Q56: Good | R56: BIG BOX, SPECIALIST, GENERALIST MULTISPORT | S56: Proof | T56: None | W56: NEW | X56: 454.36 | AA56: C | AB56: 1000 | AC56: 300 | AD56: 608487 | AE56: 3 | AF56: Essentials | AG56: Active Essentials | AI56: Shell | AJ56: Hooded Jacket | AK56: 2.5L | AL56: Y | AM56: Check | WB: 'waterproof shell for multi-season hiking' → consider Day Hiking. NAME mismatch: workbook lists code as 'Kaja Proof II Jacket'
A57: SS27 | B57: TRUE | C57: 608486 | D57: Steep 2.5L Jacket Women | E57: Apparel | F57: OUT | G57: Shell | H57: Inline | I57: Women | K57: FALSE | L57: FALSE | M57: 2500 | N57: 2.1 | O57: 1190.48 | Q57: Good | R57: BIG BOX, SPECIALIST, GENERALIST MULTISPORT | S57: Proof | T57: None | W57: NEW | X57: 423.81 | AA57: C | AB57: 1000 | AC57: 300 | AD57: 608486 | AE57: 3 | AF57: Essentials | AG57: Active Essentials | AI57: Shell | AJ57: Hooded Jacket | AK57: 2.5L | AL57: Y | AM57: Check | WB: 'waterproof shell for multi-season hiking' → consider Day Hiking. NAME mismatch: workbook lists code as 'Kaja Proof II Jacket'
A58: SS27 | B58: TRUE | C58: 608531 | D58: Klyva GTX Jacket Men | E58: Apparel | F58: OUT | G58: Shell | H58: Inline | I58: Men | K58: TRUE | L58: FALSE | M58: 3500 | N58: 2.1 | O58: 1523.81 | Q58: Good | R58: BIG BOX, SPECIALIST, GENERALIST MULTISPORT | S58: Gore-Tex | T58: None | W58: CO | X58: 613.48 | AA58: C | AB58: 1000 | AC58: 300 | AD58: 608531 | AE58: 2 | AF58: Essentials | AG58: Active Essentials | AH58: Essentials / Essentials/Everyday | Outdoor / Hiking [MATCH] | AI58: Shell | AJ58: Hooded Jacket | AK58: 2L | AL58: Y
A59: SS27 | B59: TRUE | C59: 608532 | D59: Klyva GTX Jacket Women | E59: Apparel | F59: OUT | G59: Shell | H59: Inline | I59: Women | K59: TRUE | L59: FALSE | M59: 3500 | N59: 2.1 | O59: 1523.81 | Q59: Good | R59: BIG BOX, SPECIALIST, GENERALIST MULTISPORT | S59: Gore-Tex | T59: None | W59: CO | X59: 547.3 | AA59: C | AB59: 1000 | AC59: 300 | AD59: 608532 | AE59: 3 | AF59: Essentials | AG59: Active Essentials | AH59: Essentials / Essentials/Everyday | Outdoor / Hiking [MATCH] | AI59: Shell | AJ59: Hooded Jacket | AK59: 2L | AL59: Y
A60: SS27 | B60: TRUE | C60: 608654 | D60: Klyva GTX Pant Men | E60: Apparel | F60: OUT | G60: Shell | H60: ABS | I60: Men | K60: FALSE | L60: FALSE | M60: 2800 | N60: 2.1 | O60: 1190.48 | Q60: Better | R60: BIG BOX, SPECIALIST, GENERALIST MULTISPORT | S60: Gore-Tex | T60: None | U60: Copy of Haglöfs 2L GTX Pant 608545 | W60: NEW | X60: 573.7 | AA60: C | AB60: 1000 | AC60: 300 | AD60: 608654 | AE60: 1 | AF60: Essentials | AG60: Active Essentials | AI60: Shell | AJ60: Pant | AK60: 2L | AL60: Y | AM60: WB review: AI 3L→2L (fabric = GORE-TEX 2L ePE, HH 28,000mm; matches Klyva GTX Jacket)
A61: SS27 | B61: TRUE | C61: 608655 | D61: Klyva GTX Pant Women | E61: Apparel | F61: OUT | G61: Shell | H61: ABS | I61: Women | K61: FALSE | L61: FALSE | M61: 2800 | N61: 2.1 | O61: 1190.48 | Q61: Better | R61: BIG BOX, SPECIALIST, GENERALIST MULTISPORT | S61: Gore-Tex | T61: None | U61: Copy of Haglöfs 2L GTX Pant 608548 | W61: NEW | X61: 540.67 | AA61: C | AB61: 1000 | AC61: 300 | AD61: 608655 | AE61: 1 | AF61: Essentials | AG61: Active Essentials | AI61: Shell | AJ61: Pant | AK61: 2L | AL61: Y | AM61: WB review: AI 3L→2L (fabric = GORE-TEX 2L ePE, HH 28,000mm; matches Klyva GTX Jacket)
A62: SS27 | B62: TRUE | C62: 607759 | D62: Korp Lite Pant Men | E62: Apparel | F62: OUT | G62: Legwear | H62: Inline | I62: Men | K62: TRUE | L62: FALSE | M62: 1300 | N62: 2.1 | O62: 619.05 | Q62: Good | R62: SPECIALIST, GENERALIST MULTISPORT, INTERSPORT NORDIC | S62: None | T62: None | W62: CO | X62: 202.13 | AA62: A | AB62: 1000 | AC62: 300 | AD62: 607759 | AE62: 5 | AF62: Outdoor | AG62: Day Hiking | AH62: Outdoor / Trekking [CHECK - activity] | AI62: Softshell | AJ62: Pant | AK62: Classic Softshell | AL62: N
A63: SS27 | B63: TRUE | C63: 608600 | D63: Korp Lite Pant Men AF | E63: Apparel | F63: OUT | G63: Legwear | H63: ABS Exclusive | I63: Men | K63: TRUE | L63: FALSE | M63: 1300 | N63: 2.1 | O63: 619.05 | Q63: Good | R63: ASIA | S63: None | T63: None | U63: Asia Fit version of Korp Lite Pant Men 607759 | V63: ASIA | W63: CO | X63: 207.35 | AA63: C | AB63: 1000 | AC63: 300 | AD63: 608600 | AE63: 5 | AF63: Outdoor | AG63: Day Hiking | AH63: Outdoor / Trekking [CHECK - activity] | AI63: Softshell | AJ63: Pant | AK63: Classic Softshell | AL63: N
A64: SS27 | B64: TRUE | C64: 607760 | D64: Korp Lite Pant Women | E64: Apparel | F64: OUT | G64: Legwear | H64: Inline | I64: Women | K64: TRUE | L64: FALSE | M64: 1300 | N64: 2.1 | O64: 619.05 | Q64: Good | R64: SPECIALIST, GENERALIST MULTISPORT, INTERSPORT NORDIC | S64: None | T64: None | W64: CO | X64: 194.29 | AA64: A | AB64: 1000 | AC64: 300 | AD64: 607760 | AE64: 5 | AF64: Outdoor | AG64: Day Hiking | AH64: Outdoor / Trekking [CHECK - activity] | AI64: Softshell | AJ64: Pant | AK64: Classic Softshell | AL64: N
A65: SS27 | B65: TRUE | C65: 607876 | D65: Korp Lite Shorts Men | E65: Apparel | F65: OUT | G65: Legwear | H65: Inline | I65: Men | K65: TRUE | L65: FALSE | M65: 1000 | N65: 2.1 | O65: 476.19 | Q65: Better | R65: SPECIALIST, GENERALIST MULTISPORT, INTERSPORT NORDIC | S65: None | T65: None | W65: CO | X65: 155.6 | AA65: A | AB65: 1000 | AC65: 300 | AD65: 607876 | AE65: 5 | AF65: Outdoor | AG65: Day Hiking | AH65: Outdoor / Hiking [MATCH] | AI65: Softshell | AJ65: Shorts | AK65: Classic Softshell | AL65: N
A66: SS27 | B66: TRUE | C66: 607877 | D66: Korp Lite Shorts Women | E66: Apparel | F66: OUT | G66: Legwear | H66: Inline | I66: Women | K66: TRUE | L66: FALSE | M66: 1000 | N66: 2.1 | O66: 476.19 | Q66: Better | R66: SPECIALIST, GENERALIST MULTISPORT, INTERSPORT NORDIC | S66: None | T66: None | W66: CO | X66: 149.96 | AA66: A | AB66: 1000 | AC66: 300 | AD66: 607877 | AE66: 5 | AF66: Outdoor | AG66: Day Hiking | AH66: Outdoor / Hiking [MATCH] | AI66: Softshell | AJ66: Shorts | AK66: Classic Softshell | AL66: N
A67: SS27 | B67: TRUE | C67: 607779 | D67: Korp Mid Halfzip Men | E67: Apparel | F67: OUT | G67: Midlayer | H67: Inline | I67: Men | K67: TRUE | L67: FALSE | M67: 800 | N67: 2.1 | O67: 380.95 | Q67: Good | R67: SPECIALIST, GENERALIST MULTISPORT, INTERSPORT NORDIC | S67: None | T67: None | W67: CO | X67: 138.42 | AA67: B | AB67: 1000 | AC67: 300 | AD67: 607779 | AE67: 4 | AF67: Essentials | AG67: Active Essentials | AH67: Outdoor / Hiking [CHECK - collection + activity] | AI67: Fleece/Midlayer | AJ67: 1/2 Zip | AK67: Midweight | AL67: N
A68: SS27 | B68: TRUE | C68: 607782 | D68: Korp Mid Halfzip Women | E68: Apparel | F68: OUT | G68: Midlayer | H68: Inline | I68: Women | K68: TRUE | L68: FALSE | M68: 800 | N68: 2.1 | O68: 380.95 | Q68: Good | R68: SPECIALIST, GENERALIST MULTISPORT, INTERSPORT NORDIC | S68: None | T68: None | W68: CO | X68: 126.26 | AA68: B | AB68: 1000 | AC68: 300 | AD68: 607782 | AE68: 4 | AF68: Essentials | AG68: Active Essentials | AH68: Outdoor / Hiking [CHECK - collection + activity] | AI68: Fleece/Midlayer | AJ68: 1/2 Zip | AK68: Midweight | AL68: N
A69: SS27 | B69: TRUE | C69: 607777 | D69: Korp Mid Hood Men | E69: Apparel | F69: OUT | G69: Midlayer | H69: Inline | I69: Men | K69: TRUE | L69: FALSE | M69: 1000 | N69: 2.1 | O69: 476.19 | Q69: Good | R69: SPECIALIST, GENERALIST MULTISPORT, INTERSPORT NORDIC | S69: None | T69: None | W69: CO | X69: 166.76 | AA69: B | AB69: 1000 | AC69: 300 | AD69: 607777 | AE69: 6 | AF69: Essentials | AG69: Active Essentials | AH69: Outdoor / Hiking [CHECK - collection + activity] | AI69: Fleece/Midlayer | AJ69: Hooded Jacket | AK69: Midweight | AL69: N
A70: SS27 | B70: TRUE | C70: 607780 | D70: Korp Mid Hood Women | E70: Apparel | F70: OUT | G70: Midlayer | H70: Inline | I70: Women | K70: TRUE | L70: FALSE | M70: 1000 | N70: 2.1 | O70: 476.19 | Q70: Good | R70: SPECIALIST, GENERALIST MULTISPORT, INTERSPORT NORDIC | S70: None | T70: None | W70: CO | X70: 151.79 | AA70: B | AB70: 1000 | AC70: 300 | AD70: 607780 | AE70: 5 | AF70: Essentials | AG70: Active Essentials | AH70: Outdoor / Hiking [CHECK - collection + activity] | AI70: Fleece/Midlayer | AJ70: Hooded Jacket | AK70: Midweight | AL70: N
A71: SS27 | B71: TRUE | C71: 607778 | D71: Korp Mid Jacket Men | E71: Apparel | F71: OUT | G71: Midlayer | H71: Inline | I71: Men | K71: TRUE | L71: FALSE | M71: 900 | N71: 2.1 | O71: 428.57 | Q71: Good | R71: SPECIALIST, GENERALIST MULTISPORT, INTERSPORT NORDIC | S71: None | T71: None | W71: CO | X71: 161.13 | AA71: B | AB71: 1000 | AC71: 300 | AD71: 607778 | AE71: 4 | AF71: Essentials | AG71: Active Essentials | AH71: Outdoor / Hiking [CHECK - collection + activity] | AI71: Fleece/Midlayer | AJ71: Jacket | AK71: Midweight | AL71: N
A72: SS27 | B72: TRUE | C72: 607781 | D72: Korp Mid Jacket Women | E72: Apparel | F72: OUT | G72: Midlayer | H72: Inline | I72: Women | K72: TRUE | L72: FALSE | M72: 900 | N72: 2.1 | O72: 428.57 | Q72: Good | R72: SPECIALIST, GENERALIST MULTISPORT, INTERSPORT NORDIC | S72: None | T72: None | W72: CO | X72: 146.05 | AA72: B | AB72: 1000 | AC72: 300 | AD72: 607781 | AE72: 4 | AF72: Essentials | AG72: Active Essentials | AH72: Outdoor / Hiking [CHECK - collection + activity] | AI72: Fleece/Midlayer | AJ72: Jacket | AK72: Midweight | AL72: N
A73: SS27 | B73: TRUE | C73: 608095 | D73: Korp Proof II Pant Men | E73: Apparel | F73: OUT | G73: Shell | H73: Inline | I73: Men | K73: TRUE | L73: FALSE | M73: 1300 | N73: 2.1 | O73: 619.05 | Q73: Good | R73: SPECIALIST, GENERALIST MULTISPORT, INTERSPORT NORDIC | S73: Proof | T73: None | W73: CO | X73: 215.69 | AA73: B | AB73: 1000 | AC73: 300 | AD73: 608095 | AE73: 1 | AF73: Essentials | AG73: Active Essentials | AH73: Essentials / Essentials/Everyday [MATCH] | AI73: Shell | AJ73: Pant | AK73: 2L | AL73: Y
A74: SS27 | B74: TRUE | C74: 608096 | D74: Korp Proof II Pant Women | E74: Apparel | F74: OUT | G74: Shell | H74: Inline | I74: Women | K74: TRUE | L74: FALSE | M74: 1300 | N74: 2.1 | O74: 619.05 | Q74: Good | R74: SPECIALIST, GENERALIST MULTISPORT, INTERSPORT NORDIC | S74: Proof | T74: None | W74: CO | X74: 209.46 | AA74: B | AB74: 1000 | AC74: 300 | AD74: 608096 | AE74: 1 | AF74: Essentials | AG74: Active Essentials | AH74: Essentials / Essentials/Everyday [MATCH] | AI74: Shell | AJ74: Pant | AK74: 2L | AL74: Y
A75: SS27 | B75: TRUE | C75: 607958 | D75: Korp Proof Jacket Men | E75: Apparel | F75: OUT | G75: Shell | H75: Inline | I75: Men | K75: TRUE | L75: FALSE | M75: 1800 | N75: 2.1 | O75: 857.14 | Q75: Good | R75: SPECIALIST, GENERALIST MULTISPORT, INTERSPORT NORDIC | S75: Proof | T75: None | W75: CO | X75: 268.05 | AA75: A | AB75: 1000 | AC75: 300 | AD75: 607958 | AE75: 3 | AF75: Essentials | AG75: Active Essentials | AH75: Essentials / Essentials/Everyday [MATCH] | AI75: Shell | AJ75: Jacket | AK75: 2L | AL75: Y
... A88: SS27 | B88: TRUE | C88: 608215 | D88: L.I.M Delta Tee Men | E88: Apparel | F88: L.I.M | G88: Tops | H88: Inline | I88: Men | K88: TRUE | L88: FALSE | M88: 700 | N88: 2.1 | O88: 333.33 | Q88: Better | R88: SPECIALIST, GENERALIST MULTISPORT, INTERSPORT NORDIC | S88: Polartec | T88: None | W88: CO | X88: 141.23 | AA88: B | AB88: 800 | AC88: 500 | AD88: 608215 | AE88: 4 | AF88: Outdoor | AG88: Trail Run & Fast Hike | AH88: Outdoor / Hiking [MATCH] | AI88: Tops | AJ88: Tee | AK88: Lightweight Synthetic | AL88: N
A89: SS27 | B89: TRUE | C89: 607640 | D89: L.I.M Fuse II Pant Men | E89: Apparel | F89: L.I.M | G89: Legwear | H89: Inline | I89: Men | K89: TRUE | L89: FALSE | M89: 1200 | N89: 2.1 | O89: 571.43 | Q89: Good | R89: SPECIALIST, GENERALIST MULTISPORT, INTERSPORT NORDIC | S89: Climatic | T89: None | W89: CO | X89: 200.72 | AA89: B | AB89: 1000 | AC89: 300 | AD89: 607640 | AE89: 4 | AF89: Outdoor | AG89: Trail Run & Fast Hike | AI89: Softshell | AJ89: Pant | AK89: Classic Softshell | AL89: N
A90: SS27 | B90: TRUE | C90: 607641 | D90: L.I.M Fuse II Pant Women | E90: Apparel | F90: L.I.M | G90: Legwear | H90: Inline | I90: Women | K90: TRUE | L90: FALSE | M90: 1200 | N90: 2.1 | O90: 571.43 | Q90: Good | R90: SPECIALIST, GENERALIST MULTISPORT, INTERSPORT NORDIC | S90: Climatic | T90: None | W90: CO | X90: 205.22 | AA90: B | AB90: 1000 | AC90: 300 | AD90: 607641 | AE90: 4 | AF90: Outdoor | AG90: Trail Run & Fast Hike | AI90: Softshell | AJ90: Pant | AK90: Classic Softshell | AL90: N
A91: SS27 | B91: TRUE | C91: 607709 | D91: L.I.M Fuse II Shorts Men | E91: Apparel | F91: L.I.M | G91: Legwear | H91: Inline | I91: Men | K91: TRUE | L91: FALSE | M91: 1000 | N91: 2.1 | O91: 476.19 | Q91: Good | R91: SPECIALIST, GENERALIST MULTISPORT, INTERSPORT NORDIC | S91: Climatic | T91: None | W91: CO | X91: 163.04 | AA91: B | AB91: 1000 | AC91: 300 | AD91: 607709 | AE91: 4 | AF91: Outdoor | AG91: Trail Run & Fast Hike | AI91: Softshell | AJ91: Shorts | AK91: Classic Softshell | AL91: N
A92: SS27 | B92: TRUE | C92: 607710 | D92: L.I.M Fuse II Shorts Women | E92: Apparel | F92: L.I.M | G92: Legwear | H92: Inline | I92: Women | K92: TRUE | L92: FALSE | M92: 1000 | N92: 2.1 | O92: 476.19 | Q92: Good | R92: SPECIALIST, GENERALIST MULTISPORT, INTERSPORT NORDIC | S92: Climatic | T92: None | W92: CO | X92: 160.15 | AA92: B | AB92: 1000 | AC92: 300 | AD92: 607710 | AE92: 5 | AF92: Outdoor | AG92: Trail Run & Fast Hike | AI92: Softshell | AJ92: Shorts | AK92: Classic Softshell | AL92: N
A93: SS27 | B93: TRUE | C93: 607631 | D93: L.I.M Mid Multi II Hood Men | E93: Apparel | F93: L.I.M | G93: Midlayer | H93: Inline | I93: Men | K93: TRUE | L93: FALSE | M93: 1200 | N93: 2.1 | O93: 571.43 | Q93: Better | R93: SPECIALIST, GENERALIST MULTISPORT, INTERSPORT NORDIC | S93: None | T93: None | W93: CO | X93: 251.48 | AA93: B | AB93: 800 | AC93: 500 | AD93: 607631 | AE93: 4 | AF93: Outdoor | AG93: Trail Run & Fast Hike | AH93: Outdoor / Hiking [MATCH] | AI93: Fleece/Midlayer | AJ93: Hooded Jacket | AK93: Midweight | AL93: N
A94: SS27 | B94: TRUE | C94: 607634 | D94: L.I.M Mid Multi II Hood Women | E94: Apparel | F94: L.I.M | G94: Midlayer | H94: Inline | I94: Women | K94: TRUE | L94: FALSE | M94: 1200 | N94: 2.1 | O94: 571.43 | Q94: Better | R94: SPECIALIST, GENERALIST MULTISPORT, INTERSPORT NORDIC | S94: None | T94: None | W94: CO | X94: 235.68 | AA94: B | AB94: 800 | AC94: 500 | AD94: 607634 | AE94: 4 | AF94: Outdoor | AG94: Trail Run & Fast Hike | AH94: Outdoor / Hiking [MATCH] | AI94: Fleece/Midlayer | AJ94: Hooded Jacket | AK94: Midweight | AL94: N
A95: SS27 | B95: TRUE | C95: 608417 | D95: L.I.M Mid Multi Jacket Men | E95: Apparel | F95: L.I.M | G95: Midlayer | H95: Inline | I95: Men | K95: TRUE | L95: FALSE | M95: 1100 | N95: 2.1 | O95: 523.81 | Q95: Better | R95: SPECIALIST, GENERALIST MULTISPORT, INTERSPORT NORDIC | S95: None | T95: None | W95: CO | X95: 226.08 | AA95: B | AB95: 800 | AC95: 500 | AD95: 608417 | AE95: 3 | AF95: Outdoor | AG95: Trail Run & Fast Hike | AH95: Outdoor / Hiking [MATCH] | AI95: Fleece/Midlayer | AJ95: Jacket | AK95: Midweight | AL95: N
A96: SS27 | B96: TRUE | C96: 608418 | D96: L.I.M Mid Multi Jacket Women | E96: Apparel | F96: L.I.M | G96: Midlayer | H96: Inline | I96: Women | K96: TRUE | L96: FALSE | M96: 1100 | N96: 2.1 | O96: 523.81 | Q96: Better | R96: SPECIALIST, GENERALIST MULTISPORT, INTERSPORT NORDIC | S96: None | T96: None | W96: CO | X96: 214.35 | AA96: B | AB96: 800 | AC96: 500 | AD96: 608418 | AE96: 3 | AF96: Outdoor | AG96: Trail Run & Fast Hike | AH96: Outdoor / Hiking [MATCH] | AI96: Fleece/Midlayer | AJ96: Jacket | AK96: Midweight | AL96: N
A97: SS27 | B97: TRUE | C97: 607964 | D97: L.I.M Mimic Barrier Hood Men | E97: Apparel | F97: L.I.M | G97: Insulation | H97: Inline | I97: Men | K97: TRUE | L97: FALSE | M97: 2500 | N97: 2.1 | O97: 1190.48 | Q97: Better | R97: SPECIALIST, GENERALIST MULTISPORT, INTERSPORT NORDIC | S97: Mimic | T97: None | W97: CO | X97: 494.01 | AA97: A | AB97: 800 | AC97: 100 | AD97: 607964 | AE97: 4 | AF97: Outdoor | AG97: Trail Run & Fast Hike | AH97: Outdoor / Mountaineering [CHECK - activity] | AI97: Insulation | AJ97: Hooded Jacket | AK97: Lightweight Synthetic | AL97: N
A98: SS27 | B98: TRUE | C98: 607967 | D98: L.I.M Mimic Barrier Hood Women | E98: Apparel | F98: L.I.M | G98: Insulation | H98: Inline | I98: Women | K98: TRUE | L98: FALSE | M98: 2500 | N98: 2.1 | O98: 1190.48 | Q98: Better | R98: SPECIALIST, GENERALIST MULTISPORT, INTERSPORT NORDIC | S98: Mimic | T98: None | W98: CO | X98: 460.16 | AA98: A | AB98: 800 | AC98: 100 | AD98: 607967 | AE98: 3 | AF98: Outdoor | AG98: Trail Run & Fast Hike | AH98: Outdoor / Mountaineering [CHECK - activity] | AI98: Insulation | AJ98: Hooded Jacket | AK98: Lightweight Synthetic | AL98: N
A99: SS27 | B99: TRUE | C99: 607966 | D99: L.I.M Mimic Barrier Vest Men | E99: Apparel | F99: L.I.M | G99: Insulation | H99: Inline | I99: Men | K99: TRUE | L99: FALSE | M99: 1800 | N99: 2.1 | O99: 857.14 | Q99: Better | R99: SPECIALIST, GENERALIST MULTISPORT, INTERSPORT NORDIC | S99: Mimic | T99: None | W99: CO | X99: 333.75 | AA99: A | AB99: 800 | AC99: 100 | AD99: 607966 | AE99: 2 | AF99: Outdoor | AG99: Trail Run & Fast Hike | AH99: Skiing/Snowboarding / Touring [CHECK - collection + activity] | AI99: Insulation | AJ99: Vest | AK99: Lightweight Synthetic | AL99: N
A100: SS27 | B100: TRUE | C100: 607969 | D100: L.I.M Mimic Barrier Vest Women | E100: Apparel | F100: L.I.M | G100: Insulation | H100: Inline | I100: Women | K100: TRUE | L100: FALSE | M100: 1800 | N100: 2.1 | O100: 857.14 | Q100: Better | R100: SPECIALIST, GENERALIST MULTISPORT, INTERSPORT NORDIC | S100: Mimic | T100: None | W100: CO | X100: 310.06 | AA100: A | AB100: 800 | AC100: 100 | AD100: 607969 | AE100: 2 | AF100: Outdoor | AG100: Trail Run & Fast Hike | AH100: Skiing/Snowboarding / Touring [CHECK - collection + activity] | AI100: Insulation | AJ100: Vest | AK100: Lightweight Synthetic | AL100: N
A101: SS27 | B101: TRUE | C101: 608202 | D101: L.I.M Pace Cap | E101: Apparel | F101: L.I.M | G101: Accessories | H101: Inline | I101: Unisex | K101: TRUE | L101: FALSE | M101: 500 | N101: 2.1 | O101: 238.1 | Q101: Better | R101: SPECIALIST, GENERALIST MULTISPORT, INTERSPORT NORDIC | S101: None | T101: None | W101: CO | X101: 76.45 | AA101: B | AB101: 600 | AC101: 600 | AD101: 608202 | AE101: 5 | AF101: Outdoor | AG101: Trail Run & Fast Hike | AI101: Accessories | AJ101: Headwear | AK101: Cap | AL101: N
A102: SS27 | B102: TRUE | C102: 608159 | D102: L.I.M Pace Shorts Men | E102: Apparel | F102: L.I.M | G102: Legwear | H102: Inline | I102: Men | K102: TRUE | L102: FALSE | M102: 900 | N102: 2.1 | O102: 428.57 | Q102: Better | R102: SPECIALIST, GENERALIST MULTISPORT, INTERSPORT NORDIC | S102: None | T102: None | W102: CO | X102: 163.04 | AA102: B | AB102: 1000 | AC102: 300 | AD102: 608159 | AE102: 4 | AF102: Outdoor | AG102: Trail Run & Fast Hike | AH102: Essentials / Essentials/Everyday [CHECK - collection + activity] | AI102: Softshell | AJ102: Shorts | AK102: Lightweight Synthetic | AL102: N
A103: SS27 | B103: TRUE | C103: 608179 | D103: L.I.M Pace Shorts Women | E103: Apparel | F103: L.I.M | G103: Legwear | H103: Inline | I103: Women | K103: TRUE | L103: FALSE | M103: 900 | N103: 2.1 | O103: 428.57 | Q103: Better | R103: SPECIALIST, GENERALIST MULTISPORT, INTERSPORT NORDIC | S103: None | T103: None | W103: CO | X103: 134.25 | AA103: B | AB103: 1000 | AC103: 300 | AD103: 608179 | AE103: 4 | AF103: Outdoor | AG103: Trail Run & Fast Hike | AH103: Essentials / Essentials/Everyday [CHECK - collection + activity] | AI103: Softshell | AJ103: Shorts | AK103: Lightweight Synthetic | AL103: N
A104: SS27 | B104: TRUE | C104: 608420 | D104: L.I.M Ridge Tank Women | E104: Apparel | F104: L.I.M | G104: Tops | H104: Inline | I104: Women | K104: TRUE | L104: FALSE | M104: 450 | N104: 2.1 | O104: 214.29 | Q104: Better | R104: SPECIALIST, GENERALIST MULTISPORT, INTERSPORT NORDIC | S104: None | T104: None | W104: CO | X104: 112.55 | AA104: B | AB104: 800 | AC104: 500 | AD104: 608420 | AE104: 4 | AF104: Outdoor | AG104: Trail Run & Fast Hike | AH104: Essentials / Essentials/Everyday [CHECK - collection + activity] | AI104: Tops | AJ104: Tank | AK104: Lightweight Synthetic | AL104: N
A105: SS27 | B105: TRUE | C105: 607685 | D105: L.I.M Ridge Tee Men | E105: Apparel | F105: L.I.M | G105: Tops | H105: Inline | I105: Men | K105: TRUE | L105: FALSE | M105: 500 | N105: 2.1 | O105: 238.1 | Q105: Better | R105: SPECIALIST, GENERALIST MULTISPORT, INTERSPORT NORDIC | S105: None | T105: None | W105: CO | X105: 112.55 | AA105: B | AB105: 800 | AC105: 500 | AD105: 607685 | AE105: 5 | AF105: Outdoor | AG105: Trail Run & Fast Hike | AI105: Tops | AJ105: Tee | AK105: Lightweight Synthetic | AL105: N
A106: SS27 | B106: TRUE | C106: 607686 | D106: L.I.M Ridge Tee Women | E106: Apparel | F106: L.I.M | G106: Tops | H106: Inline | I106: Women | K106: TRUE | L106: FALSE | M106: 500 | N106: 2.1 | O106: 238.1 | Q106: Better | R106: SPECIALIST, GENERALIST MULTISPORT, INTERSPORT NORDIC | S106: None | T106: None | W106: CO | X106: 105.78 | AA106: B | AB106: 800 | AC106: 500 | AD106: 607686 | AE106: 4 | AF106: Outdoor | AG106: Trail Run & Fast Hike | AI106: Tops | AJ106: Tee | AK106: Lightweight Synthetic | AL106: N
A107: SS27 | B107: TRUE | C107: 608170 | D107: L.I.M Sunpack Hoodie Men | E107: Apparel | F107: L.I.M | G107: Tops | H107: Inline | I107: Men | K107: TRUE | L107: FALSE | M107: 1500 | N107: 2.1 | O107: 714.29 | Q107: Better | R107: SPECIALIST | S107: None | T107: None | W107: CO | X107: 269.42 | AA107: B | AB107: 800 | AC107: 100 | AD107: 608170 | AE107: 3 | AF107: Outdoor | AG107: Trail Run & Fast Hike | AH107: Essentials / Essentials/Everyday [CHECK - collection + activity] | AI107: Tops | AJ107: Hooded Jacket | AK107: Windbreaker | AL107: N
A108: SS27 | B108: TRUE | C108: 608190 | D108: L.I.M Sunpack Hoodie Women | E108: Apparel | F108: L.I.M | G108: Tops | H108: Inline | I108: Women | K108: TRUE | L108: FALSE | M108: 1500 | N108: 2.1 | O108: 714.29 | Q108: Better | R108: SPECIALIST | S108: None | T108: None | W108: CO | X108: 246.3 | AA108: B | AB108: 800 | AC108: 100 | AD108: 608190 | AE108: 3 | AF108: Outdoor | AG108: Trail Run & Fast Hike | AH108: Essentials / Essentials/Everyday [CHECK - collection + activity] | AI108: Tops | AJ108: Hooded Jacket | AK108: Windbreaker | AL108: N
A109: SS27 | B109: TRUE | C109: 608160 | D109: Levante Pant Men | E109: Apparel | F109: DAY | G109: Legwear | H109: Inline | I109: Men | K109: TRUE | L109: FALSE | M109: 1500 | N109: 2.1 | O109: 714.29 | Q109: Best | R109: SPECIALIST, Lifestyle/DAY | S109: None | T109: None | W109: CO | X109: 295.82 | AA109: B | AB109: 1000 | AC109: 300 | AD109: 608160 | AE109: 3 | AF109: Essentials | AG109: Active Essentials | AH109: Essentials / Essentials/Everyday [MATCH] | AI109: Softshell | AJ109: Pant | AK109: Classic Softshell | AL109: N
A110: SS27 | B110: TRUE | C110: 608176 | D110: Levante Pant Women | E110: Apparel | F110: DAY | G110: Legwear | H110: Inline | I110: Women | K110: TRUE | L110: FALSE | M110: 1500 | N110: 2.1 | O110: 714.29 | Q110: Best | R110: SPECIALIST, Lifestyle/DAY | S110: None | T110: None | W110: CO | X110: 276.27 | AA110: B | AB110: 1000 | AC110: 300 | AD110: 608176 | AE110: 2 | AF110: Essentials | AG110: Active Essentials | AH110: Essentials / Essentials/Everyday [MATCH] | AI110: Softshell | AJ110: Pant | AK110: Classic Softshell | AL110: N
A111: SS27 | B111: TRUE | C111: 608161 | D111: Levante Shorts Men | E111: Apparel | F111: DAY | G111: Legwear | H111: Inline | I111: Men | K111: FALSE | L111: FALSE | M111: 1200 | N111: 2.1 | O111: 571.43 | Q111: Best | R111: SPECIALIST, Lifestyle/DAY | S111: None | T111: None | W111: NEW | X111: 241.32 | AA111: B | AB111: 1000 | AC111: 300 | AD111: 608161 | AE111: 3 | AF111: Essentials | AG111: Daily Essentials | AH111: Essentials / Essentials/Everyday [MATCH] | AI111: Softshell | AJ111: Shorts | AK111: Classic Softshell | AL111: N
A112: SS27 | B112: TRUE | C112: 608180 | D112: Levante Shorts Women | E112: Apparel | F112: DAY | G112: Legwear | H112: Inline | I112: Women | K112: FALSE | L112: FALSE | M112: 1200 | N112: 2.1 | O112: 571.43 | Q112: Best | R112: SPECIALIST, Lifestyle/DAY | S112: None | T112: None | W112: NEW | X112: 193.79 | AA112: B | AB112: 1000 | AC112: 300 | AD112: 608180 | AE112: 3 | AF112: Essentials | AG112: Daily Essentials | AH112: Essentials / Essentials/Everyday [MATCH] | AI112: Softshell | AJ112: Shorts | AK112: Classic Softshell | AL112: N
...

Sheet FW27
B1: =COLUMN()-1 -> 1 | C1: =COLUMN()-1 -> 2 | D1: =COLUMN()-1 -> 3 | G1: =COLUMN()-1 -> 6 | I1: =COLUMN()-1 -> 8 | J1: =COLUMN()-1 -> 9 | K1: =COLUMN()-1 -> 10 | L1: =COLUMN()-1 -> 11 | M1: =COLUMN()-1 -> 12 | N1: =COLUMN()-1 -> 13 | O1: =COLUMN()-1 -> 14 | P1: =COLUMN()-1 -> 15 | ... AE1: =COLUMN()-1 -> 30 | AK1: Product Life Cycle: Launch Season, Update Season, Last Season Offered (TOBIAS) | AM1: ORIGINAL | AN1: ORIGINAL | AO1: CENTRIC | AP1: CENTRIC | AQ1: CENTRIC | BA1: Product Life Cycle: Launch Season, Update Season, Last Season Offered
A2: Active | B2: Code | C2: Style | D2: Business Area | G2: Product Concept | I2: Category/Layer | J2: Collection Type | K2: Gender | L2: Proposed Drop Week | M2: Carry Over | N2: Update | O2: Target RRP | P2: Mark-up | Q2: WP | R2: GM0% | S2: Product Hierarchy | T2: Distribution Segmentation | U2: Main technology platform | V2: Secondary technology platform | W2: Style Comment | X2: ABS Customer | Y2: STATUS | Z2: LANDED COST SEK | AA2: REF_CODE | AB2: REF_NAME | AC2: Classification ABC | AD2: MOQ Style | AE2: MOQ Color | AF2: Check Pricing | AG2: Color Options | AH2: AF EXIST | AI2: LSO / Exit Season | AJ2: Product Life Cycle: Launch Season, Update Season, Last Season Offered | AK2: LS | AL2: US | AM2: Collection | AN2: NEW MAPPING: Activity | AO2: Collection | AP2: Activity | AQ2: Concept | AR2: COMMENT | AS2: Category/Layer(V2) | AT2: Silhouette | AU2: Category/Layer Subtype | AV2: Waterproof | AW2: Attribution Review | AX2: Franchise/Family | AY2: Note | BA2: LS | BB2: US | BC2: LSO
A3: TRUE | B3: 608656 | C3: Aska Softshell Hood Men | D3: Apparel | G3: OUT | I3: Softshell | J3: ABS | K3: Men | M3: TRUE | N3: FALSE | O3: 1800 | P3: 2.1 | Q3: 857.14 | R3: 0.72276408 | S3: Good | U3: None | V3: None | X3: Intersport | Y3: =IF(M3=TRUE,"CO",IF(N3=TRUE,"UPDATE","NEW")) -> CO | Z3: =_xlfn.XLOOKUP($B3,[1]F27!$C:$C,[1]F27!$BV:$BV) -> #ERROR! | AD3: =_xlfn.XLOOKUP($B3,[1]F27!$C:$C,[1]F27!$Y:$Y) -> #ERROR! | AE3: =_xlfn.XLOOKUP($B3,[1]F27!$C:$C,[1]F27!$Z:$Z) -> #ERROR! | AF3: =_xlfn.XLOOKUP($B3,[2]PRICING!$B:$B,[2]PRICING!$B:$B,"MISSING") -> #ERROR! | AG3: =COUNTIFS([2]ACTIVE_SCO!$B:$B,$B3,[2]ACTIVE_SCO!$P:$P,"Y") -> #ERROR! | AI3: FW28+ | AJ3: PLC: LS?? US-?? LSO-?? | AK3: SS27 | AM3: Outdoor | AN3: Day Hiking | AO3: Outdoor | AP3: Hiking | AS3: Softshell | AT3: Hooded Jacket | AU3: Classic Softshell | AV3: N | BA3: SS27
A4: TRUE | B4: 608658 | C4: Aska Softshell Hood Women | D4: Apparel | G4: OUT | I4: Softshell | J4: ABS | K4: Women | M4: TRUE | N4: FALSE | O4: 1800 | P4: 2.1 | Q4: 857.14 | R4: 0.74220081 | S4: Good | U4: None | V4: None | X4: Intersport | Y4: =IF(M4=TRUE,"CO",IF(N4=TRUE,"UPDATE","NEW")) -> CO | Z4: =_xlfn.XLOOKUP($B4,[1]F27!$C:$C,[1]F27!$BV:$BV) -> #ERROR! | AD4: =_xlfn.XLOOKUP($B4,[1]F27!$C:$C,[1]F27!$Y:$Y) -> #ERROR! | AE4: =_xlfn.XLOOKUP($B4,[1]F27!$C:$C,[1]F27!$Z:$Z) -> #ERROR! | AF4: =_xlfn.XLOOKUP($B4,[2]PRICING!$B:$B,[2]PRICING!$B:$B,"MISSING") -> #ERROR! | AG4: =COUNTIFS([2]ACTIVE_SCO!$B:$B,$B4,[2]ACTIVE_SCO!$P:$P,"Y") -> #ERROR! | AI4: FW28+ | AJ4: PLC: LS?? US-?? LSO-?? | AK4: SS27 | AM4: Outdoor | AN4: Day Hiking | AO4: Outdoor | AP4: Hiking | AS4: Softshell | AT4: Hooded Jacket | AU4: Classic Softshell | AV4: N | BA4: SS27
A5: TRUE | B5: 608363 | C5: Aska Insulated Jacket Men | D5: Apparel | G5: OUT | I5: Shell | J5: ABS | K5: Men | M5: TRUE | N5: FALSE | O5: 2500 | P5: 2.1 | Q5: 1190.48 | R5: 0.6562395 | S5: Good | U5: Proof | V5: Mimic | X5: Intersport | Y5: =IF(M5=TRUE,"CO",IF(N5=TRUE,"UPDATE","NEW")) -> CO | Z5: =_xlfn.XLOOKUP($B5,[1]F27!$C:$C,[1]F27!$BV:$BV) -> #ERROR! | AD5: =_xlfn.XLOOKUP($B5,[1]F27!$C:$C,[1]F27!$Y:$Y) -> #ERROR! | AE5: =_xlfn.XLOOKUP($B5,[1]F27!$C:$C,[1]F27!$Z:$Z) -> #ERROR! | AF5: =_xlfn.XLOOKUP($B5,[2]PRICING!$B:$B,[2]PRICING!$B:$B,"MISSING") -> #ERROR! | AG5: =COUNTIFS([2]ACTIVE_SCO!$B:$B,$B5,[2]ACTIVE_SCO!$P:$P,"Y") -> #ERROR! | AI5: FW28+ | AJ5: PLC: LS?? US-?? LSO-?? | AK5: FW26 | AM5: Essentials | AN5: Active Essentials | AO5: Essentials | AS5: Shell | AT5: Jacket | AU5: Insulated | AV5: Y | BA5: FW26
A6: TRUE | B6: 608365 | C6: Aska Insulated Jacket Women | D6: Apparel | G6: OUT | I6: Shell | J6: ABS | K6: Women | M6: TRUE | N6: FALSE | O6: 2500 | P6: 2.1 | Q6: 1190.48 | R6: 0.68080942 | S6: Good | U6: Proof | V6: Mimic | X6: Intersport | Y6: =IF(M6=TRUE,"CO",IF(N6=TRUE,"UPDATE","NEW")) -> CO | Z6: =_xlfn.XLOOKUP($B6,[1]F27!$C:$C,[1]F27!$BV:$BV) -> #ERROR! | AD6: =_xlfn.XLOOKUP($B6,[1]F27!$C:$C,[1]F27!$Y:$Y) -> #ERROR! | AE6: =_xlfn.XLOOKUP($B6,[1]F27!$C:$C,[1]F27!$Z:$Z) -> #ERROR! | AF6: =_xlfn.XLOOKUP($B6,[2]PRICING!$B:$B,[2]PRICING!$B:$B,"MISSING") -> #ERROR! | AG6: =COUNTIFS([2]ACTIVE_SCO!$B:$B,$B6,[2]ACTIVE_SCO!$P:$P,"Y") -> #ERROR! | AI6: FW28+ | AJ6: PLC: LS?? US-?? LSO-?? | AK6: FW26 | AM6: Essentials | AN6: Active Essentials | AO6: Essentials | AS6: Shell | AT6: Jacket | AU6: Insulated | AV6: Y | BA6: FW26
A7: TRUE | B7: 608530 | C7: Aska Insulated Pant Men | D7: Apparel | G7: OUT | I7: Shell | J7: ABS | K7: Men | M7: TRUE | N7: FALSE | O7: 2000 | P7: 2.1 | Q7: 952.38 | R7: 0.7045822 | S7: Good | U7: Proof | V7: Mimic | X7: Intersport | Y7: =IF(M7=TRUE,"CO",IF(N7=TRUE,"UPDATE","NEW")) -> CO | Z7: =_xlfn.XLOOKUP($B7,[1]F27!$C:$C,[1]F27!$BV:$BV) -> #ERROR! | AD7: =_xlfn.XLOOKUP($B7,[1]F27!$C:$C,[1]F27!$Y:$Y) -> #ERROR! | AE7: =_xlfn.XLOOKUP($B7,[1]F27!$C:$C,[1]F27!$Z:$Z) -> #ERROR! | AF7: =_xlfn.XLOOKUP($B7,[2]PRICING!$B:$B,[2]PRICING!$B:$B,"MISSING") -> #ERROR! | AG7: =COUNTIFS([2]ACTIVE_SCO!$B:$B,$B7,[2]ACTIVE_SCO!$P:$P,"Y") -> #ERROR! | AI7: FW28+ | AJ7: PLC: LS?? US-?? LSO-?? | AK7: FW26 | AM7: Essentials | AN7: Active Essentials | AO7: Essentials | AS7: Shell | AT7: Pant | AU7: Insulated | AV7: Y | BA7: FW26
A8: TRUE | B8: 608529 | C8: Aska Insulated Pant Women | D8: Apparel | G8: OUT | I8: Shell | J8: ABS | K8: Women | M8: TRUE | N8: FALSE | O8: 2000 | P8: 2.1 | Q8: 952.38 | R8: 0.71275121 | S8: Good | U8: Proof | V8: Mimic | X8: Intersport | Y8: =IF(M8=TRUE,"CO",IF(N8=TRUE,"UPDATE","NEW")) -> CO | Z8: =_xlfn.XLOOKUP($B8,[1]F27!$C:$C,[1]F27!$BV:$BV) -> #ERROR! | AD8: =_xlfn.XLOOKUP($B8,[1]F27!$C:$C,[1]F27!$Y:$Y) -> #ERROR! | AE8: =_xlfn.XLOOKUP($B8,[1]F27!$C:$C,[1]F27!$Z:$Z) -> #ERROR! | AF8: =_xlfn.XLOOKUP($B8,[2]PRICING!$B:$B,[2]PRICING!$B:$B,"MISSING") -> #ERROR! | AG8: =COUNTIFS([2]ACTIVE_SCO!$B:$B,$B8,[2]ACTIVE_SCO!$P:$P,"Y") -> #ERROR! | AI8: FW28+ | AJ8: PLC: LS?? US-?? LSO-?? | AK8: FW26 | AM8: Essentials | AN8: Active Essentials | AO8: Essentials | AS8: Shell | AT8: Pant | AU8: Insulated | AV8: Y | BA8: FW26
A9: TRUE | B9: 608395 | C9: Aska Proof Jacket Men | D9: Apparel | G9: OUT | I9: Shell | J9: ABS | K9: Men | M9: TRUE | N9: FALSE | O9: 2200 | P9: 2.1 | Q9: 1047.62 | R9: 0.67609439 | S9: Good | U9: Proof | V9: None | X9: Intersport | Y9: =IF(M9=TRUE,"CO",IF(N9=TRUE,"UPDATE","NEW")) -> CO | Z9: =_xlfn.XLOOKUP($B9,[1]F27!$C:$C,[1]F27!$BV:$BV) -> #ERROR! | AD9: =_xlfn.XLOOKUP($B9,[1]F27!$C:$C,[1]F27!$Y:$Y) -> #ERROR! | AE9: =_xlfn.XLOOKUP($B9,[1]F27!$C:$C,[1]F27!$Z:$Z) -> #ERROR! | AF9: =_xlfn.XLOOKUP($B9,[2]PRICING!$B:$B,[2]PRICING!$B:$B,"MISSING") -> #ERROR! | AG9: =COUNTIFS([2]ACTIVE_SCO!$B:$B,$B9,[2]ACTIVE_SCO!$P:$P,"Y") -> #ERROR! | AI9: FW28+ | AJ9: PLC: LS?? US-?? LSO-?? | AK9: SS26 | AM9: Essentials | AN9: Active Essentials | AO9: Essentials | AS9: Shell | AT9: Jacket | AU9: 2L | AV9: Y | BA9: SS26
A10: TRUE | B10: 608396 | C10: Aska Proof Jacket Women | D10: Apparel | G10: OUT | I10: Shell | J10: ABS | K10: Women | M10: TRUE | N10: FALSE | O10: 2200 | P10: 2.1 | Q10: 1047.62 | R10: 0.698173 | S10: Good | U10: Proof | V10: None | X10: Intersport | Y10: =IF(M10=TRUE,"CO",IF(N10=TRUE,"UPDATE","NEW")) -> CO | Z10: =_xlfn.XLOOKUP($B10,[1]F27!$C:$C,[1]F27!$BV:$BV) -> #ERROR! | AD10: =_xlfn.XLOOKUP($B10,[1]F27!$C:$C,[1]F27!$Y:$Y) -> #ERROR! | AE10: =_xlfn.XLOOKUP($B10,[1]F27!$C:$C,[1]F27!$Z:$Z) -> #ERROR! | AF10: =_xlfn.XLOOKUP($B10,[2]PRICING!$B:$B,[2]PRICING!$B:$B,"MISSING") -> #ERROR! | AG10: =COUNTIFS([2]ACTIVE_SCO!$B:$B,$B10,[2]ACTIVE_SCO!$P:$P,"Y") -> #ERROR! | AI10: FW28+ | AJ10: PLC: LS?? US-?? LSO-?? | AK10: SS26 | AM10: Essentials | AN10: Active Essentials | AO10: Essentials | AS10: Shell | AT10: Jacket | AU10: 2L | AV10: Y | BA10: SS26
A11: TRUE | B11: 608397 | C11: Aska Proof Pant Men | D11: Apparel | G11: OUT | I11: Shell | J11: ABS | K11: Men | M11: TRUE | N11: FALSE | O11: 1700 | P11: 2.1 | Q11: 809.52 | R11: 0.67289258 | S11: Good | U11: Proof | V11: None | X11: Intersport | Y11: =IF(M11=TRUE,"CO",IF(N11=TRUE,"UPDATE","NEW")) -> CO | Z11: =_xlfn.XLOOKUP($B11,[1]F27!$C:$C,[1]F27!$BV:$BV) -> #ERROR! | AD11: =_xlfn.XLOOKUP($B11,[1]F27!$C:$C,[1]F27!$Y:$Y) -> #ERROR! | AE11: =_xlfn.XLOOKUP($B11,[1]F27!$C:$C,[1]F27!$Z:$Z) -> #ERROR! | AF11: =_xlfn.XLOOKUP($B11,[2]PRICING!$B:$B,[2]PRICING!$B:$B,"MISSING") -> #ERROR! | AG11: =COUNTIFS([2]ACTIVE_SCO!$B:$B,$B11,[2]ACTIVE_SCO!$P:$P,"Y") -> #ERROR! | AI11: FW28+ | AJ11: PLC: LS?? US-?? LSO-?? | AK11: SS26 | AM11: Essentials | AN11: Active Essentials | AO11: Essentials | AS11: Shell | AT11: Pant | AU11: 2L | AV11: Y | BA11: SS26
A12: TRUE | B12: 608398 | C12: Aska Proof Pant Women | D12: Apparel | G12: OUT | I12: Shell | J12: ABS | K12: Women | M12: TRUE | N12: FALSE | O12: 1700 | P12: 2.1 | Q12: 809.52 | R12: 0.68005732 | S12: Good | U12: Proof | V12: None | X12: Intersport | Y12: =IF(M12=TRUE,"CO",IF(N12=TRUE,"UPDATE","NEW")) -> CO | Z12: =_xlfn.XLOOKUP($B12,[1]F27!$C:$C,[1]F27!$BV:$BV) -> #ERROR! | AD12: =_xlfn.XLOOKUP($B12,[1]F27!$C:$C,[1]F27!$Y:$Y) -> #ERROR! | AE12: =_xlfn.XLOOKUP($B12,[1]F27!$C:$C,[1]F27!$Z:$Z) -> #ERROR! | AF12: =_xlfn.XLOOKUP($B12,[2]PRICING!$B:$B,[2]PRICING!$B:$B,"MISSING") -> #ERROR! | AG12: =COUNTIFS([2]ACTIVE_SCO!$B:$B,$B12,[2]ACTIVE_SCO!$P:$P,"Y") -> #ERROR! | AI12: FW28+ | AJ12: PLC: LS?? US-?? LSO-?? | AK12: SS26 | AM12: Essentials | AN12: Active Essentials | AO12: Essentials | AS12: Shell | AT12: Pant | AU12: 2L | AV12: Y | BA12: SS26
A13: FALSE | B13: 608250 | C13: Apex II Hood Men | D13: Apparel | G13: OUT | I13: Softshell | J13: Inline | K13: Men | M13: TRUE | N13: FALSE | O13: 2200 | P13: 2.1 | Q13: 1047.62 | R13: 0.67951165 | S13: Better | U13: None | V13: None | X13: XXL | Y13: =IF(M13=TRUE,"CO",IF(N13=TRUE,"UPDATE","NEW")) -> CO | Z13: =_xlfn.XLOOKUP($B13,[1]F27!$C:$C,[1]F27!$BV:$BV) -> #ERROR! | AD13: =_xlfn.XLOOKUP($B13,[1]F27!$C:$C,[1]F27!$Y:$Y) -> #ERROR! | AE13: =_xlfn.XLOOKUP($B13,[1]F27!$C:$C,[1]F27!$Z:$Z) -> #ERROR! | AF13: =_xlfn.XLOOKUP($B13,[2]PRICING!$B:$B,[2]PRICING!$B:$B,"MISSING") -> #ERROR! | AG13: =COUNTIFS([2]ACTIVE_SCO!$B:$B,$B13,[2]ACTIVE_SCO!$P:$P,"Y") -> #ERROR! | AI13: REVIEW
A14: FALSE | B14: 608249 | C14: Apex II Hood Women | D14: Apparel | G14: OUT | I14: Softshell | J14: Inline | K14: Women | M14: TRUE | N14: FALSE | O14: 2200 | P14: 2.1 | Q14: 1047.62 | R14: 0.70093164 | S14: Better | U14: None | V14: None | X14: XXL | Y14: =IF(M14=TRUE,"CO",IF(N14=TRUE,"UPDATE","NEW")) -> CO | Z14: =_xlfn.XLOOKUP($B14,[1]F27!$C:$C,[1]F27!$BV:$BV) -> #ERROR! | AD14: =_xlfn.XLOOKUP($B14,[1]F27!$C:$C,[1]F27!$Y:$Y) -> #ERROR! | AE14: =_xlfn.XLOOKUP($B14,[1]F27!$C:$C,[1]F27!$Z:$Z) -> #ERROR! | AF14: =_xlfn.XLOOKUP($B14,[2]PRICING!$B:$B,[2]PRICING!$B:$B,"MISSING") -> #ERROR! | AG14: =COUNTIFS([2]ACTIVE_SCO!$B:$B,$B14,[2]ACTIVE_SCO!$P:$P,"Y") -> #ERROR! | AI14: REVIEW
A15: TRUE | B15: 608451 | C15: Base Mimic II Hood Men | D15: Apparel | G15: OUT | I15: Insulation | J15: ABS | K15: Men | M15: TRUE | N15: FALSE | O15: 2200 | P15: 2.1 | Q15: 1047.62 | R15: 0.72570207 | S15: Good | U15: Mimic | V15: None | X15: XXL | Y15: =IF(M15=TRUE,"CO",IF(N15=TRUE,"UPDATE","NEW")) -> CO | Z15: =_xlfn.XLOOKUP($B15,[1]F27!$C:$C,[1]F27!$BV:$BV) -> #ERROR! | AD15: =_xlfn.XLOOKUP($B15,[1]F27!$C:$C,[1]F27!$Y:$Y) -> #ERROR! | AE15: =_xlfn.XLOOKUP($B15,[1]F27!$C:$C,[1]F27!$Z:$Z) -> #ERROR! | AF15: =_xlfn.XLOOKUP($B15,[2]PRICING!$B:$B,[2]PRICING!$B:$B,"MISSING") -> #ERROR! | AG15: =COUNTIFS([2]ACTIVE_SCO!$B:$B,$B15,[2]ACTIVE_SCO!$P:$P,"Y") -> #ERROR! | AI15: FW28+ | AJ15: PLC: LS?? US-?? LSO-?? | AK15: Pre S23 | AL15: FW25 | AM15: Essentials | AN15: Active Essentials | AO15: Essentials | AS15: Insulation | AT15: Hooded Jacket | AU15: Midweight Synthetic | AV15: N | BA15: Pre S23 | BB15: FW25
A16: TRUE | B16: 608452 | C16: Base Mimic II Hood Women | D16: Apparel | G16: OUT | I16: Insulation | J16: ABS | K16: Women | M16: TRUE | N16: FALSE | O16: 2200 | P16: 2.1 | Q16: 1047.62 | R16: 0.73729024 | S16: Good | U16: Mimic | V16: None | X16: XXL | Y16: =IF(M16=TRUE,"CO",IF(N16=TRUE,"UPDATE","NEW")) -> CO | Z16: =_xlfn.XLOOKUP($B16,[1]F27!$C:$C,[1]F27!$BV:$BV) -> #ERROR! | AD16: =_xlfn.XLOOKUP($B16,[1]F27!$C:$C,[1]F27!$Y:$Y) -> #ERROR! | AE16: =_xlfn.XLOOKUP($B16,[1]F27!$C:$C,[1]F27!$Z:$Z) -> #ERROR! | AF16: =_xlfn.XLOOKUP($B16,[2]PRICING!$B:$B,[2]PRICING!$B:$B,"MISSING") -> #ERROR! | AG16: =COUNTIFS([2]ACTIVE_SCO!$B:$B,$B16,[2]ACTIVE_SCO!$P:$P,"Y") -> #ERROR! | AI16: FW28+ | AJ16: PLC: LS?? US-?? LSO-?? | AK16: Pre S23 | AL16: FW25 | AM16: Essentials | AN16: Active Essentials | AO16: Essentials | AS16: Insulation | AT16: Hooded Jacket | AU16: Midweight Synthetic | AV16: N | BA16: Pre S23 | BB16: FW25
A17: TRUE | B17: 608454 | C17: Base Mimic II Jacket Men | D17: Apparel | G17: OUT | I17: Insulation | J17: ABS | K17: Men | M17: TRUE | N17: FALSE | O17: 2000 | P17: 2.1 | Q17: 952.38 | R17: 0.72113022 | S17: Good | U17: Mimic | V17: None | X17: XXL | Y17: =IF(M17=TRUE,"CO",IF(N17=TRUE,"UPDATE","NEW")) -> CO | Z17: =_xlfn.XLOOKUP($B17,[1]F27!$C:$C,[1]F27!$BV:$BV) -> #ERROR! | AD17: =_xlfn.XLOOKUP($B17,[1]F27!$C:$C,[1]F27!$Y:$Y) -> #ERROR! | AE17: =_xlfn.XLOOKUP($B17,[1]F27!$C:$C,[1]F27!$Z:$Z) -> #ERROR! | AF17: =_xlfn.XLOOKUP($B17,[2]PRICING!$B:$B,[2]PRICING!$B:$B,"MISSING") -> #ERROR! | AG17: =COUNTIFS([2]ACTIVE_SCO!$B:$B,$B17,[2]ACTIVE_SCO!$P:$P,"Y") -> #ERROR! | AI17: FW28+ | AJ17: PLC: LS?? US-?? LSO-?? | AK17: Pre S23 | AL17: FW25 | AM17: Essentials | AN17: Active Essentials | AO17: Essentials | AS17: Insulation | AT17: Jacket | AU17: Midweight Synthetic | AV17: N | BA17: Pre S23 | BB17: FW25
A18: TRUE | B18: 608453 | C18: Base Mimic II Jacket Women | D18: Apparel | G18: OUT | I18: Insulation | J18: ABS | K18: Women | M18: TRUE | N18: FALSE | O18: 2000 | P18: 2.1 | Q18: 952.38 | R18: 0.72759823 | S18: Good | U18: Mimic | V18: None | X18: XXL | Y18: =IF(M18=TRUE,"CO",IF(N18=TRUE,"UPDATE","NEW")) -> CO | Z18: =_xlfn.XLOOKUP($B18,[1]F27!$C:$C,[1]F27!$BV:$BV) -> #ERROR! | AD18: =_xlfn.XLOOKUP($B18,[1]F27!$C:$C,[1]F27!$Y:$Y) -> #ERROR! | AE18: =_xlfn.XLOOKUP($B18,[1]F27!$C:$C,[1]F27!$Z:$Z) -> #ERROR! | AF18: =_xlfn.XLOOKUP($B18,[2]PRICING!$B:$B,[2]PRICING!$B:$B,"MISSING") -> #ERROR! | AG18: =COUNTIFS([2]ACTIVE_SCO!$B:$B,$B18,[2]ACTIVE_SCO!$P:$P,"Y") -> #ERROR! | AI18: FW28+ | AJ18: PLC: LS?? US-?? LSO-?? | AK18: Pre S23 | AL18: FW25 | AM18: Essentials | AN18: Active Essentials | AO18: Essentials | AS18: Insulation | AT18: Jacket | AU18: Midweight Synthetic | AV18: N | BA18: Pre S23 | BB18: FW25
A19: TRUE | B19: 608421 | C19: Chaos GTX II Jacket Men | D19: Apparel | G19: OUT | I19: Shell | J19: ABS | K19: Men | M19: TRUE | N19: FALSE | O19: 3500 | P19: 2.1 | Q19: 1666.67 | R19: 0.67878464 | S19: Good | U19: Gore-Tex | V19: None | X19: Intersport | Y19: =IF(M19=TRUE,"CO",IF(N19=TRUE,"UPDATE","NEW")) -> CO | Z19: =_xlfn.XLOOKUP($B19,[1]F27!$C:$C,[1]F27!$BV:$BV) -> #ERROR! | AD19: =_xlfn.XLOOKUP($B19,[1]F27!$C:$C,[1]F27!$Y:$Y) -> #ERROR! | AE19: =_xlfn.XLOOKUP($B19,[1]F27!$C:$C,[1]F27!$Z:$Z) -> #ERROR! | AF19: =_xlfn.XLOOKUP($B19,[2]PRICING!$B:$B,[2]PRICING!$B:$B,"MISSING") -> #ERROR! | AG19: =COUNTIFS([2]ACTIVE_SCO!$B:$B,$B19,[2]ACTIVE_SCO!$P:$P,"Y") -> #ERROR! | AI19: FW28+ | AJ19: PLC: LS?? US-?? LSO-?? | AK19: Pre S23 | AL19: SS25 | AM19: Outdoor | AN19: Active Essentials | AO19: Essentials | AS19: Shell | AT19: Jacket | AU19: 2L | AV19: Y | BA19: Pre S23 | BB19: SS25
A20: TRUE | B20: 608422 | C20: Chaos GTX II Jacket Women | D20: Apparel | G20: OUT | I20: Shell | J20: ABS | K20: Women | M20: TRUE | N20: FALSE | O20: 3500 | P20: 2.1 | Q20: 1666.67 | R20: 0.69681461 | S20: Good | U20: Gore-Tex | V20: None | X20: Intersport | Y20: =IF(M20=TRUE,"CO",IF(N20=TRUE,"UPDATE","NEW")) -> CO | Z20: =_xlfn.XLOOKUP($B20,[1]F27!$C:$C,[1]F27!$BV:$BV) -> #ERROR! | AD20: =_xlfn.XLOOKUP($B20,[1]F27!$C:$C,[1]F27!$Y:$Y) -> #ERROR! | AE20: =_xlfn.XLOOKUP($B20,[1]F27!$C:$C,[1]F27!$Z:$Z) -> #ERROR! | AF20: =_xlfn.XLOOKUP($B20,[2]PRICING!$B:$B,[2]PRICING!$B:$B,"MISSING") -> #ERROR! | AG20: =COUNTIFS([2]ACTIVE_SCO!$B:$B,$B20,[2]ACTIVE_SCO!$P:$P,"Y") -> #ERROR! | AI20: FW28+ | AJ20: PLC: LS?? US-?? LSO-?? | AK20: Pre S23 | AL20: SS25 | AM20: Outdoor | AN20: Active Essentials | AO20: Essentials | AS20: Shell | AT20: Jacket | AU20: 2L | AV20: Y | BA20: Pre S23 | BB20: SS25
A21: TRUE | B21: 605630 | C21: Chill Down Hood Men | D21: Apparel | G21: OUT | I21: Insulation | J21: ABS | K21: Men | M21: TRUE | N21: FALSE | O21: 3400 | P21: 2.1 | Q21: 1619.05 | R21: 0.59544177 | S21: Better | U21: Down | V21: None | X21: Intersport | Y21: =IF(M21=TRUE,"CO",IF(N21=TRUE,"UPDATE","NEW")) -> CO | Z21: =_xlfn.XLOOKUP($B21,[1]F27!$C:$C,[1]F27!$BV:$BV) -> #ERROR! | AD21: =_xlfn.XLOOKUP($B21,[1]F27!$C:$C,[1]F27!$Y:$Y) -> #ERROR! | AE21: =_xlfn.XLOOKUP($B21,[1]F27!$C:$C,[1]F27!$Z:$Z) -> #ERROR! | AF21: =_xlfn.XLOOKUP($B21,[2]PRICING!$B:$B,[2]PRICING!$B:$B,"MISSING") -> #ERROR! | AG21: =COUNTIFS([2]ACTIVE_SCO!$B:$B,$B21,[2]ACTIVE_SCO!$P:$P,"Y") -> #ERROR! | AI21: FW28+ | AJ21: PLC: LS?? US-?? LSO-?? | AK21: Pre S23 | AM21: Essentials | AN21: Active Essentials | AO21: Essentials | AS21: Insulation | AT21: Hooded Jacket | AU21: Midweight Down | AV21: N | BA21: Pre S23
A22: TRUE | B22: 608450 | C22: Fiction Down II Hood Men | D22: Apparel | G22: OUT | I22: Insulation | J22: ABS | K22: Men | M22: TRUE | N22: FALSE | O22: 2800 | P22: 2.1 | Q22: 1333.33 | R22: 0.65078413 | S22: Better | U22: Down | V22: None | X22: Intersport | Y22: =IF(M22=TRUE,"CO",IF(N22=TRUE,"UPDATE","NEW")) -> CO | Z22: =_xlfn.XLOOKUP($B22,[1]F27!$C:$C,[1]F27!$BV:$BV) -> #ERROR! | AD22: =_xlfn.XLOOKUP($B22,[1]F27!$C:$C,[1]F27!$Y:$Y) -> #ERROR! | AE22: =_xlfn.XLOOKUP($B22,[1]F27!$C:$C,[1]F27!$Z:$Z) -> #ERROR! | AF22: =_xlfn.XLOOKUP($B22,[2]PRICING!$B:$B,[2]PRICING!$B:$B,"MISSING") -> #ERROR! | AG22: =COUNTIFS([2]ACTIVE_SCO!$B:$B,$B22,[2]ACTIVE_SCO!$P:$P,"Y") -> #ERROR! | AI22: FW28+ | AJ22: PLC: LS?? US-?? LSO-?? | AK22: Pre S23 | AL22: FW25 | AM22: Essentials | AN22: Active Essentials | AO22: Essentials | AS22: Insulation | AT22: Hooded Jacket | AU22: Midweight Down | AV22: N | BA22: Pre S23 | BB22: FW25
A23: TRUE | B23: 608657 | C23: Aska Softshell Pant Men | D23: Apparel | G23: OUT | I23: Softshell | J23: ABS | K23: Men | M23: TRUE | N23: FALSE | O23: 1400 | P23: 2.1 | Q23: 666.67 | R23: 0.70483148 | S23: Good | U23: None | V23: None | X23: Intersport | Y23: =IF(M23=TRUE,"CO",IF(N23=TRUE,"UPDATE","NEW")) -> CO | Z23: =_xlfn.XLOOKUP($B23,[1]F27!$C:$C,[1]F27!$BV:$BV) -> #ERROR! | AD23: =_xlfn.XLOOKUP($B23,[1]F27!$C:$C,[1]F27!$Y:$Y) -> #ERROR! | AE23: =_xlfn.XLOOKUP($B23,[1]F27!$C:$C,[1]F27!$Z:$Z) -> #ERROR! | AF23: =_xlfn.XLOOKUP($B23,[2]PRICING!$B:$B,[2]PRICING!$B:$B,"MISSING") -> #ERROR! | AG23: =COUNTIFS([2]ACTIVE_SCO!$B:$B,$B23,[2]ACTIVE_SCO!$P:$P,"Y") -> #ERROR! | AI23: FW28+ | AJ23: PLC: LS?? US-?? LSO-?? | AK23: SS27 | AM23: Outdoor | AN23: Day Hiking | AO23: Outdoor | AP23: Hiking | AS23: Softshell | AT23: Pant | AU23: Classic Softshell | AV23: N | AY23: Trekking? | BA23: SS27
A24: TRUE | B24: 608659 | C24: Aska Softshell Pant Women | D24: Apparel | G24: OUT | I24: Softshell | J24: ABS | K24: Women | M24: TRUE | N24: FALSE | O24: 1400 | P24: 2.1 | Q24: 666.67 | R24: 0.71021645 | S24: Good | U24: None | V24: None | X24: Intersport | Y24: =IF(M24=TRUE,"CO",IF(N24=TRUE,"UPDATE","NEW")) -> CO | Z24: =_xlfn.XLOOKUP($B24,[1]F27!$C:$C,[1]F27!$BV:$BV) -> #ERROR! | AD24: =_xlfn.XLOOKUP($B24,[1]F27!$C:$C,[1]F27!$Y:$Y) -> #ERROR! | AE24: =_xlfn.XLOOKUP($B24,[1]F27!$C:$C,[1]F27!$Z:$Z) -> #ERROR! | AF24: =_xlfn.XLOOKUP($B24,[2]PRICING!$B:$B,[2]PRICING!$B:$B,"MISSING") -> #ERROR! | AG24: =COUNTIFS([2]ACTIVE_SCO!$B:$B,$B24,[2]ACTIVE_SCO!$P:$P,"Y") -> #ERROR! | AI24: FW28+ | AJ24: PLC: LS?? US-?? LSO-?? | AK24: SS27 | AM24: Outdoor | AN24: Day Hiking | AO24: Outdoor | AP24: Hiking | AS24: Softshell | AT24: Pant | AU24: Classic Softshell | AV24: N | AY24: Trekking? | BA24: SS27
A25: TRUE | B25: 608527 | C25: Pollux 1/2 zip II Jacket Men | D25: Apparel | G25: OUT | I25: Midlayer | J25: ABS | K25: Men | M25: TRUE | N25: FALSE | O25: 800 | P25: 2.1 | Q25: 380.95 | R25: 0.59574747 | S25: Good | U25: Polartec | V25: None | X25: XXL | Y25: =IF(M25=TRUE,"CO",IF(N25=TRUE,"UPDATE","NEW")) -> CO | Z25: =_xlfn.XLOOKUP($B25,[1]F27!$C:$C,[1]F27!$BV:$BV) -> #ERROR! | AD25: =_xlfn.XLOOKUP($B25,[1]F27!$C:$C,[1]F27!$Y:$Y) -> #ERROR! | AE25: =_xlfn.XLOOKUP($B25,[1]F27!$C:$C,[1]F27!$Z:$Z) -> #ERROR! | AF25: =_xlfn.XLOOKUP($B25,[2]PRICING!$B:$B,[2]PRICING!$B:$B,"MISSING") -> #ERROR! | AG25: =COUNTIFS([2]ACTIVE_SCO!$B:$B,$B25,[2]ACTIVE_SCO!$P:$P,"Y") -> #ERROR! | AI25: FW27 or SS28 | AJ25: Replaced with Buteo 1/2 zip Inline | AK25: Pre S23 | AL25: FW26 | AM25: Essentials | AN25: Active Essentials | AO25: Essentials | AS25: Fleece/Midlayer | AT25: 1/2 Zip | AU25: Lightweight | AV25: N | BA25: Pre S23 | BB25: FW26
A26: TRUE | B26: 608528 | C26: Pollux 1/2 zip II Jacket Women | D26: Apparel | G26: OUT | I26: Midlayer | J26: ABS | K26: Women | M26: TRUE | N26: FALSE | O26: 800 | P26: 2.1 | Q26: 380.95 | R26: 0.62955768 | S26: Good | U26: Polartec | V26: None | X26: XXL | Y26: =IF(M26=TRUE,"CO",IF(N26=TRUE,"UPDATE","NEW")) -> CO | Z26: =_xlfn.XLOOKUP($B26,[1]F27!$C:$C,[1]F27!$BV:$BV) -> #ERROR! | AD26: =_xlfn.XLOOKUP($B26,[1]F27!$C:$C,[1]F27!$Y:$Y) -> #ERROR! | AE26: =_xlfn.XLOOKUP($B26,[1]F27!$C:$C,[1]F27!$Z:$Z) -> #ERROR! | AF26: =_xlfn.XLOOKUP($B26,[2]PRICING!$B:$B,[2]PRICING!$B:$B,"MISSING") -> #ERROR! | AG26: =COUNTIFS([2]ACTIVE_SCO!$B:$B,$B26,[2]ACTIVE_SCO!$P:$P,"Y") -> #ERROR! | AI26: FW28+ | AJ26: Replaced with Buteo 1/2 zip Inline | AK26: Pre S23 | AL26: FW26 | AM26: Essentials | AN26: Active Essentials | AO26: Essentials | AS26: Fleece/Midlayer | AT26: 1/2 Zip | AU26: Lightweight | AV26: N | BA26: Pre S23 | BB26: FW26
A27: TRUE | B27: 608864 | C27: Skuta Proof Jacket Men | D27: Apparel | G27: OUT | I27: Shell | J27: ABS | K27: Men | M27: FALSE | N27: FALSE | O27: 2500 | P27: 2.1 | Q27: 1190.48 | R27: 0.70470734 | S27: Good | U27: Proof | V27: None | Y27: =IF(M27=TRUE,"CO",IF(N27=TRUE,"UPDATE","NEW")) -> NEW | Z27: =_xlfn.XLOOKUP($B27,[1]F27!$C:$C,[1]F27!$BV:$BV) -> #ERROR! | AD27: =_xlfn.XLOOKUP($B27,[1]F27!$C:$C,[1]F27!$Y:$Y) -> #ERROR! | AE27: =_xlfn.XLOOKUP($B27,[1]F27!$C:$C,[1]F27!$Z:$Z) -> #ERROR! | AF27: =_xlfn.XLOOKUP($B27,[2]PRICING!$B:$B,[2]PRICING!$B:$B,"MISSING") -> #ERROR! | AG27: =COUNTIFS([2]ACTIVE_SCO!$B:$B,$B27,[2]ACTIVE_SCO!$P:$P,"Y") -> #ERROR! | AI27: FW28+ | AJ27: PLC: LS?? US-?? LSO-?? | AK27: SS27 | AM27: Essentials | AN27: Active Essentials | AO27: Essentials | AS27: Shell | AT27: Jacket | AU27: 2L | AV27: Y | BA27: SS27
A28: TRUE | B28: 608863 | C28: Skuta Proof Jacket Women | D28: Apparel | G28: OUT | I28: Shell | J28: ABS | K28: Women | M28: FALSE | N28: FALSE | O28: 2500 | P28: 2.1 | Q28: 1190.48 | R28: 0.72132249 | S28: Good | U28: Proof | V28: None | Y28: =IF(M28=TRUE,"CO",IF(N28=TRUE,"UPDATE","NEW")) -> NEW | Z28: =_xlfn.XLOOKUP($B28,[1]F27!$C:$C,[1]F27!$BV:$BV) -> #ERROR! | AD28: =_xlfn.XLOOKUP($B28,[1]F27!$C:$C,[1]F27!$Y:$Y) -> #ERROR! | AE28: =_xlfn.XLOOKUP($B28,[1]F27!$C:$C,[1]F27!$Z:$Z) -> #ERROR! | AF28: =_xlfn.XLOOKUP($B28,[2]PRICING!$B:$B,[2]PRICING!$B:$B,"MISSING") -> #ERROR! | AG28: =COUNTIFS([2]ACTIVE_SCO!$B:$B,$B28,[2]ACTIVE_SCO!$P:$P,"Y") -> #ERROR! | AI28: FW28+ | AJ28: PLC: LS?? US-?? LSO-?? | AK28: SS27 | AM28: Essentials | AN28: Active Essentials | AO28: Essentials | AS28: Shell | AT28: Jacket | AU28: 2L | AV28: Y | BA28: SS27
A29: TRUE | B29: 607855 | C29: Trekk Tech LS Tee Men | D29: Apparel | G29: OUT | I29: Tops | J29: ABS | K29: Men | M29: TRUE | N29: FALSE | O29: 700 | P29: 2.1 | Q29: 333.33 | R29: 0.74373744 | S29: Good | U29: None | V29: None | Y29: =IF(M29=TRUE,"CO",IF(N29=TRUE,"UPDATE","NEW")) -> CO | Z29: =_xlfn.XLOOKUP($B29,[1]F27!$C:$C,[1]F27!$BV:$BV) -> #ERROR! | AD29: =_xlfn.XLOOKUP($B29,[1]F27!$C:$C,[1]F27!$Y:$Y) -> #ERROR! | AE29: =_xlfn.XLOOKUP($B29,[1]F27!$C:$C,[1]F27!$Z:$Z) -> #ERROR! | AF29: =_xlfn.XLOOKUP($B29,[2]PRICING!$B:$B,[2]PRICING!$B:$B,"MISSING") -> #ERROR! | AG29: =COUNTIFS([2]ACTIVE_SCO!$B:$B,$B29,[2]ACTIVE_SCO!$P:$P,"Y") -> #ERROR! | AI29: FW27 | AJ29: PLC: LS?? US LSO-FW27 | AK29: Pre S23 | AL29: SS25 | AM29: Essentials | AN29: Active Essentials | AO29: Essentials | AQ29: Essentials | AS29: Tops | AT29: Tee | AU29: Tech Tee | AV29: N | BA29: Pre S23 | BB29: SS25
A30: TRUE | B30: 607858 | C30: Trekk Tech LS Tee Women | D30: Apparel | G30: OUT | I30: Tops | J30: ABS | K30: Women | M30: TRUE | N30: FALSE | O30: 700 | P30: 2.1 | Q30: 333.33 | R30: 0.76824768 | S30: Good | U30: None | V30: None | Y30: =IF(M30=TRUE,"CO",IF(N30=TRUE,"UPDATE","NEW")) -> CO | Z30: =_xlfn.XLOOKUP($B30,[1]F27!$C:$C,[1]F27!$BV:$BV) -> #ERROR! | AD30: =_xlfn.XLOOKUP($B30,[1]F27!$C:$C,[1]F27!$Y:$Y) -> #ERROR! | AE30: =_xlfn.XLOOKUP($B30,[1]F27!$C:$C,[1]F27!$Z:$Z) -> #ERROR! | AF30: =_xlfn.XLOOKUP($B30,[2]PRICING!$B:$B,[2]PRICING!$B:$B,"MISSING") -> #ERROR! | AG30: =COUNTIFS([2]ACTIVE_SCO!$B:$B,$B30,[2]ACTIVE_SCO!$P:$P,"Y") -> #ERROR! | AI30: FW27 | AJ30: PLC: LS?? US LSO-FW27 | AK30: Pre S23 | AL30: SS25 | AM30: Essentials | AN30: Active Essentials | AO30: Essentials | AQ30: Essentials | AS30: Tops | AT30: Tee | AU30: Tech Tee | AV30: N | BA30: Pre S23 | BB30: SS25
A31: TRUE | B31: 607856 | C31: Trekk Tech Tee Men | D31: Apparel | G31: OUT | I31: Tops | J31: ABS | K31: Men | M31: TRUE | N31: FALSE | O31: 500 | P31: 2.1 | Q31: 238.1 | R31: 0.69252415 | S31: Good | U31: None | V31: None | Y31: =IF(M31=TRUE,"CO",IF(N31=TRUE,"UPDATE","NEW")) -> CO | Z31: =_xlfn.XLOOKUP($B31,[1]F27!$C:$C,[1]F27!$BV:$BV) -> #ERROR! | AD31: =_xlfn.XLOOKUP($B31,[1]F27!$C:$C,[1]F27!$Y:$Y) -> #ERROR! | AE31: =_xlfn.XLOOKUP($B31,[1]F27!$C:$C,[1]F27!$Z:$Z) -> #ERROR! | AF31: =_xlfn.XLOOKUP($B31,[2]PRICING!$B:$B,[2]PRICING!$B:$B,"MISSING") -> #ERROR! | AG31: =COUNTIFS([2]ACTIVE_SCO!$B:$B,$B31,[2]ACTIVE_SCO!$P:$P,"Y") -> #ERROR! | AI31: FW27 | AJ31: PLC: LS?? US LSO-FW27 | AK31: Pre S23 | AL31: SS25 | AM31: Essentials | AN31: Active Essentials | AO31: Essentials | AQ31: Essentials | AS31: Tops | AT31: Tee | AU31: Tech Tee | AV31: N | BA31: Pre S23 | BB31: SS25
A32: TRUE | B32: 607857 | C32: Trekk Tech Tee Women | D32: Apparel | G32: OUT | I32: Tops | J32: ABS | K32: Women | M32: TRUE | N32: FALSE | O32: 500 | P32: 2.1 | Q32: 238.1 | R32: 0.70949181 | S32: Good | U32: None | V32: None | Y32: =IF(M32=TRUE,"CO",IF(N32=TRUE,"UPDATE","NEW")) -> CO | Z32: =_xlfn.XLOOKUP($B32,[1]F27!$C:$C,[1]F27!$BV:$BV) -> #ERROR! | AD32: =_xlfn.XLOOKUP($B32,[1]F27!$C:$C,[1]F27!$Y:$Y) -> #ERROR! | AE32: =_xlfn.XLOOKUP($B32,[1]F27!$C:$C,[1]F27!$Z:$Z) -> #ERROR! | AF32: =_xlfn.XLOOKUP($B32,[2]PRICING!$B:$B,[2]PRICING!$B:$B,"MISSING") -> #ERROR! | AG32: =COUNTIFS([2]ACTIVE_SCO!$B:$B,$B32,[2]ACTIVE_SCO!$P:$P,"Y") -> #ERROR! | AI32: FW27 | AJ32: PLC: LS?? US LSO-FW27 | AK32: Pre S23 | AL32: SS25 | AM32: Essentials | AN32: Active Essentials | AO32: Essentials | AQ32: Essentials | AS32: Tops | AT32: Tee | AU32: Tech Tee | AV32: N | BA32: Pre S23 | BB32: SS25
A33: TRUE | B33: 608874 | C33: Steep GTX Jacket Men | D33: Apparel | G33: OUT | I33: Shell | J33: ABS | K33: Men | M33: FALSE | N33: FALSE | O33: 4000 | P33: 2.1 | Q33: 1904.76 | R33: 0.56852307 | S33: Better | U33: Gore-Tex | V33: None | Y33: =IF(M33=TRUE,"CO",IF(N33=TRUE,"UPDATE","NEW")) -> NEW | Z33: =_xlfn.XLOOKUP($B33,[1]F27!$C:$C,[1]F27!$BV:$BV) -> #ERROR! | AD33: =_xlfn.XLOOKUP($B33,[1]F27!$C:$C,[1]F27!$Y:$Y) -> #ERROR! | AE33: =_xlfn.XLOOKUP($B33,[1]F27!$C:$C,[1]F27!$Z:$Z) -> #ERROR! | AF33: =_xlfn.XLOOKUP($B33,[2]PRICING!$B:$B,[2]PRICING!$B:$B,"MISSING") -> #ERROR! | AG33: =COUNTIFS([2]ACTIVE_SCO!$B:$B,$B33,[2]ACTIVE_SCO!$P:$P,"Y") -> #ERROR! | AI33: FW28+ | AJ33: PLC: LS?? US-?? LSO-?? | AK33: SS27 | AM33: Essentials | AN33: Active Essentials | AO33: Essentials | AS33: Shell | AT33: Jacket | AU33: 2L | AV33: Y | BA33: SS27
A34: TRUE | B34: 608873 | C34: Steep GTX Jacket Women | D34: Apparel | G34: OUT | I34: Shell | J34: ABS | K34: Women | M34: FALSE | N34: FALSE | O34: 4000 | P34: 2.1 | Q34: 1904.76 | R34: 0.59499359 | S34: Better | U34: Gore-Tex | V34: None | Y34: =IF(M34=TRUE,"CO",IF(N34=TRUE,"UPDATE","NEW")) -> NEW | Z34: =_xlfn.XLOOKUP($B34,[1]F27!$C:$C,[1]F27!$BV:$BV) -> #ERROR! | AD34: =_xlfn.XLOOKUP($B34,[1]F27!$C:$C,[1]F27!$Y:$Y) -> #ERROR! | AE34: =_xlfn.XLOOKUP($B34,[1]F27!$C:$C,[1]F27!$Z:$Z) -> #ERROR! | AF34: =_xlfn.XLOOKUP($B34,[2]PRICING!$B:$B,[2]PRICING!$B:$B,"MISSING") -> #ERROR! | AG34: =COUNTIFS([2]ACTIVE_SCO!$B:$B,$B34,[2]ACTIVE_SCO!$P:$P,"Y") -> #ERROR! | AI34: FW28+ | AJ34: PLC: LS?? US-?? LSO-?? | AK34: SS27 | AM34: Essentials | AN34: Active Essentials | AO34: Essentials | AS34: Shell | AT34: Jacket | AU34: 2L | AV34: Y | BA34: SS27
A35: FALSE | B35: 608256 | C35: Bield Down II Hood Men | D35: Apparel | G35: OUT | I35: Insulation | J35: ABS | K35: Men | M35: TRUE | N35: FALSE | O35: 2700 | P35: 2.1 | Q35: 1285.71 | R35: 0.64038547 | S35: Better | U35: Down | V35: None | X35: XXL | Y35: =IF(M35=TRUE,"CO",IF(N35=TRUE,"UPDATE","NEW")) -> CO | Z35: =_xlfn.XLOOKUP($B35,[1]F27!$C:$C,[1]F27!$BV:$BV) -> #ERROR! | AD35: =_xlfn.XLOOKUP($B35,[1]F27!$C:$C,[1]F27!$Y:$Y) -> #ERROR! | AE35: =_xlfn.XLOOKUP($B35,[1]F27!$C:$C,[1]F27!$Z:$Z) -> #ERROR! | AF35: =_xlfn.XLOOKUP($B35,[2]PRICING!$B:$B,[2]PRICING!$B:$B,"MISSING") -> #ERROR! | AG35: =COUNTIFS([2]ACTIVE_SCO!$B:$B,$B35,[2]ACTIVE_SCO!$P:$P,"Y") -> #ERROR! | AI35: REVIEW
A36: FALSE | B36: 608257 | C36: Bield Down II Hood Women | D36: Apparel | G36: OUT | I36: Insulation | J36: ABS | K36: Women | M36: TRUE | N36: FALSE | O36: 2700 | P36: 2.1 | Q36: 1285.71 | R36: 0.6798656 | S36: Better | U36: Down | V36: None | X36: XXL | Y36: =IF(M36=TRUE,"CO",IF(N36=TRUE,"UPDATE","NEW")) -> CO | Z36: =_xlfn.XLOOKUP($B36,[1]F27!$C:$C,[1]F27!$BV:$BV) -> #ERROR! | AD36: =_xlfn.XLOOKUP($B36,[1]F27!$C:$C,[1]F27!$Y:$Y) -> #ERROR! | AE36: =_xlfn.XLOOKUP($B36,[1]F27!$C:$C,[1]F27!$Z:$Z) -> #ERROR! | AF36: =_xlfn.XLOOKUP($B36,[2]PRICING!$B:$B,[2]PRICING!$B:$B,"MISSING") -> #ERROR! | AG36: =COUNTIFS([2]ACTIVE_SCO!$B:$B,$B36,[2]ACTIVE_SCO!$P:$P,"Y") -> #ERROR! | AI36: REVIEW
A37: TRUE | B37: 608872 | C37: Zircon Flex Pant Men | D37: Apparel | G37: OUT | I37: Legwear | J37: ABS | K37: Men | M37: FALSE | N37: FALSE | O37: 2000 | P37: 2.1 | Q37: 952.38 | R37: 0.6956992 | S37: Better | U37: None | V37: None | Y37: =IF(M37=TRUE,"CO",IF(N37=TRUE,"UPDATE","NEW")) -> NEW | Z37: =_xlfn.XLOOKUP($B37,[1]F27!$C:$C,[1]F27!$BV:$BV) -> #ERROR! | AD37: =_xlfn.XLOOKUP($B37,[1]F27!$C:$C,[1]F27!$Y:$Y) -> #ERROR! | AE37: =_xlfn.XLOOKUP($B37,[1]F27!$C:$C,[1]F27!$Z:$Z) -> #ERROR! | AF37: =_xlfn.XLOOKUP($B37,[2]PRICING!$B:$B,[2]PRICING!$B:$B,"MISSING") -> #ERROR! | AG37: =COUNTIFS([2]ACTIVE_SCO!$B:$B,$B37,[2]ACTIVE_SCO!$P:$P,"Y") -> #ERROR! | AI37: FW28+ | AJ37: PLC: LS?? US-?? LSO-?? | AK37: SS27 | AM37: Outdoor | AN37: Day Hiking | AO37: Outdoor | AP37: Hiking | AS37: Legwear | AT37: Pant | AU37: Classic Softshell | AV37: N | BA37: SS27
A38: TRUE | B38: 608871 | C38: Zircon Flex Pant Women | D38: Apparel | G38: OUT | I38: Legwear | J38: ABS | K38: Women | M38: FALSE | N38: FALSE | O38: 2000 | P38: 2.1 | Q38: 952.38 | R38: 0.6973792 | S38: Better | U38: None | V38: None | Y38: =IF(M38=TRUE,"CO",IF(N38=TRUE,"UPDATE","NEW")) -> NEW | Z38: =_xlfn.XLOOKUP($B38,[1]F27!$C:$C,[1]F27!$BV:$BV) -> #ERROR! | AD38: =_xlfn.XLOOKUP($B38,[1]F27!$C:$C,[1]F27!$Y:$Y) -> #ERROR! | AE38: =_xlfn.XLOOKUP($B38,[1]F27!$C:$C,[1]F27!$Z:$Z) -> #ERROR! | AF38: =_xlfn.XLOOKUP($B38,[2]PRICING!$B:$B,[2]PRICING!$B:$B,"MISSING") -> #ERROR! | AG38: =COUNTIFS([2]ACTIVE_SCO!$B:$B,$B38,[2]ACTIVE_SCO!$P:$P,"Y") -> #ERROR! | AI38: FW28+ | AJ38: PLC: LS?? US-?? LSO-?? | AK38: SS27 | AM38: Outdoor | AN38: Day Hiking | AO38: Outdoor | AP38: Hiking | AS38: Legwear | AT38: Pant | AU38: Classic Softshell | AV38: N | BA38: SS27
A39: TRUE | B39: 608639 | C39: Zodiac Mid II Jacket Men | D39: Apparel | G39: OUT | I39: Midlayer | J39: ABS | K39: Men | M39: TRUE | N39: FALSE | O39: 1300 | P39: 2.1 | Q39: 619.05 | R39: 0.62762297 | S39: Good | U39: None | V39: None | X39: XXL | Y39: =IF(M39=TRUE,"CO",IF(N39=TRUE,"UPDATE","NEW")) -> CO | Z39: =_xlfn.XLOOKUP($B39,[1]F27!$C:$C,[1]F27!$BV:$BV) -> #ERROR! | AD39: =_xlfn.XLOOKUP($B39,[1]F27!$C:$C,[1]F27!$Y:$Y) -> #ERROR! | AE39: =_xlfn.XLOOKUP($B39,[1]F27!$C:$C,[1]F27!$Z:$Z) -> #ERROR! | AF39: =_xlfn.XLOOKUP($B39,[2]PRICING!$B:$B,[2]PRICING!$B:$B,"MISSING") -> #ERROR! | AG39: =COUNTIFS([2]ACTIVE_SCO!$B:$B,$B39,[2]ACTIVE_SCO!$P:$P,"Y") -> #ERROR! | AI39: FW28+ | AJ39: STILL OFFERING THIS ABS PAST FW27? | AK39: SS25 | AL39: SS27 | AM39: Essentials | AN39: Active Essentials | AO39: Essentials | AS39: Fleece/Midlayer | AT39: Jacket | AU39: Midweight | AV39: N | BA39: SS25 | BB39: SS27
A40: TRUE | B40: 608640 | C40: Zodiac Mid II Jacket Women | D40: Apparel | G40: OUT | I40: Midlayer | J40: ABS | K40: Women | M40: TRUE | N40: FALSE | O40: 1300 | P40: 2.1 | Q40: 619.05 | R40: 0.65182134 | S40: Good | U40: None | V40: None | X40: XXL | Y40: =IF(M40=TRUE,"CO",IF(N40=TRUE,"UPDATE","NEW")) -> CO | Z40: =_xlfn.XLOOKUP($B40,[1]F27!$C:$C,[1]F27!$BV:$BV) -> #ERROR! | AD40: =_xlfn.XLOOKUP($B40,[1]F27!$C:$C,[1]F27!$Y:$Y) -> #ERROR! | AE40: =_xlfn.XLOOKUP($B40,[1]F27!$C:$C,[1]F27!$Z:$Z) -> #ERROR! | AF40: =_xlfn.XLOOKUP($B40,[2]PRICING!$B:$B,[2]PRICING!$B:$B,"MISSING") -> #ERROR! | AG40: =COUNTIFS([2]ACTIVE_SCO!$B:$B,$B40,[2]ACTIVE_SCO!$P:$P,"Y") -> #ERROR! | AI40: FW28+ | AJ40: STILL OFFERING THIS ABS PAST FW27? | AK40: SS25 | AL40: SS27 | AM40: Essentials | AN40: Active Essentials | AO40: Essentials | AS40: Fleece/Midlayer | AT40: Jacket | AU40: Midweight | AV40: N | BA40: SS25 | BB40: SS27
A41: TRUE | B41: 608774 | C41: Polka Aresk Beanie | D41: Apparel | G41: OUT | I41: Accessories | J41: ABS Exclusive | K41: Unisex | M41: FALSE | N41: FALSE | O41: 500 | P41: 2.1 | Q41: 238.1 | R41: 0.69655607 | S41: Good | U41: None | V41: None | X41: DTC | Y41: =IF(M41=TRUE,"CO",IF(N41=TRUE,"UPDATE","NEW")) -> NEW | Z41: =_xlfn.XLOOKUP($B41,[1]F27!$C:$C,[1]F27!$BV:$BV) -> #ERROR! | AD41: =_xlfn.XLOOKUP($B41,[1]F27!$C:$C,[1]F27!$Y:$Y) -> #ERROR! | AE41: =_xlfn.XLOOKUP($B41,[1]F27!$C:$C,[1]F27!$Z:$Z) -> #ERROR! | AF41: =_xlfn.XLOOKUP($B41,[2]PRICING!$B:$B,[2]PRICING!$B:$B,"MISSING") -> #ERROR! | AG41: =COUNTIFS([2]ACTIVE_SCO!$B:$B,$B41,[2]ACTIVE_SCO!$P:$P,"Y") -> #ERROR! | AI41: FW27 | AM41: Essentials | AN41: Active Essentials | AO41: Essentials | AQ41: Essentials | AS41: Accessories | AT41: Headwear | AU41: Beanie | AV41: N
A42: TRUE | B42: 608820 | C42: Sunpack Prototype Hoodie Men | D42: Apparel | G42: L.I.M | I42: Tops | J42: ABS Exclusive | K42: Men | M42: FALSE | N42: FALSE | O42: 0 | P42: 2.1 | Q42: 0 | R42: #DIV/0! | U42: None | X42: KA YO Collab | Y42: =IF(M42=TRUE,"CO",IF(N42=TRUE,"UPDATE","NEW")) -> NEW | Z42: =_xlfn.XLOOKUP($B42,[1]F27!$C:$C,[1]F27!$BV:$BV) -> #ERROR! | AD42: =_xlfn.XLOOKUP($B42,[1]F27!$C:$C,[1]F27!$Y:$Y) -> #ERROR! | AE42: =_xlfn.XLOOKUP($B42,[1]F27!$C:$C,[1]F27!$Z:$Z) -> #ERROR! | AF42: =_xlfn.XLOOKUP($B42,[2]PRICING!$B:$B,[2]PRICING!$B:$B,"MISSING") -> #ERROR! | AG42: =COUNTIFS([2]ACTIVE_SCO!$B:$B,$B42,[2]ACTIVE_SCO!$P:$P,"Y") -> #ERROR! | AI42: FW27 | AM42: Essentials | AN42: Active Essentials | AO42: Essentials | AS42: Tops | AT42: Hooded Jacket | AU42: Cotton/Graphic Tee | AV42: N
A43: TRUE | B43: 608858 | C43: Team SWE Mitten | D43: Apparel | G43: OUT | I43: Accessories | J43: ABS Exclusive | K43: Unisex | M43: FALSE | N43: TRUE | O43: 800 | P43: 2.1 | Q43: 380.95 | R43: 0.53938837 | U43: Primaloft | V43: Pertex | X43: DTC | Y43: =IF(M43=TRUE,"CO",IF(N43=TRUE,"UPDATE","NEW")) -> UPDATE | Z43: =_xlfn.XLOOKUP($B43,[1]F27!$C:$C,[1]F27!$BV:$BV) -> #ERROR! | AD43: =_xlfn.XLOOKUP($B43,[1]F27!$C:$C,[1]F27!$Y:$Y) -> #ERROR! | AE43: =_xlfn.XLOOKUP($B43,[1]F27!$C:$C,[1]F27!$Z:$Z) -> #ERROR! | AF43: =_xlfn.XLOOKUP($B43,[2]PRICING!$B:$B,[2]PRICING!$B:$B,"MISSING") -> #ERROR! | AG43: =COUNTIFS([2]ACTIVE_SCO!$B:$B,$B43,[2]ACTIVE_SCO!$P:$P,"Y") -> #ERROR! | AI43: FW28+ | AJ43: PLC: LS?? US-?? LSO-?? | AM43: Essentials | AN43: Active Essentials | AO43: Skiing/Snowboarding | AP43: All Mountain | AR43: FW27: Haglöfs Mimic Mitten | AS43: Accessories | AT43: Handwear | AV43: N
A44: TRUE | B44: 608690 | C44: Aresk Beanie | D44: Apparel | G44: OUT | I44: Accessories | J44: Inline | K44: Unisex | M44: FALSE | N44: FALSE | O44: 450 | P44: 2.1 | Q44: 214.29 | R44: 0.68607961 | S44: Good | U44: None | V44: None | Y44: =IF(M44=TRUE,"CO",IF(N44=TRUE,"UPDATE","NEW")) -> NEW | Z44: =_xlfn.XLOOKUP($B44,[1]F27!$C:$C,[1]F27!$BV:$BV) -> #ERROR! | AD44: =_xlfn.XLOOKUP($B44,[1]F27!$C:$C,[1]F27!$Y:$Y) -> #ERROR! | AE44: =_xlfn.XLOOKUP($B44,[1]F27!$C:$C,[1]F27!$Z:$Z) -> #ERROR! | AF44: =_xlfn.XLOOKUP($B44,[2]PRICING!$B:$B,[2]PRICING!$B:$B,"MISSING") -> #ERROR! | AG44: =COUNTIFS([2]ACTIVE_SCO!$B:$B,$B44,[2]ACTIVE_SCO!$P:$P,"Y") -> #ERROR! | AI44: FW28+ | AJ44: PLC: LS?? US-?? LSO-?? | AM44: Essentials | AN44: Active Essentials | AO44: Essentials | AQ44: Essentials | AS44: Accessories | AT44: Headwear | AU44: Beanie | AV44: N
A45: TRUE | B45: 608875 | C45: Zircon Proof Jacket Men | D45: Apparel | G45: OUT | I45: Shell | J45: ABS | K45: Men | M45: FALSE | N45: FALSE | O45: 2500 | P45: 2.1 | Q45: 1190.48 | R45: 0.6235384 | S45: Good | U45: Proof | V45: None | Y45: =IF(M45=TRUE,"CO",IF(N45=TRUE,"UPDATE","NEW")) -> NEW | Z45: =_xlfn.XLOOKUP($B45,[1]F27!$C:$C,[1]F27!$BV:$BV) -> #ERROR! | AD45: =_xlfn.XLOOKUP($B45,[1]F27!$C:$C,[1]F27!$Y:$Y) -> #ERROR! | AE45: =_xlfn.XLOOKUP($B45,[1]F27!$C:$C,[1]F27!$Z:$Z) -> #ERROR! | AF45: =_xlfn.XLOOKUP($B45,[2]PRICING!$B:$B,[2]PRICING!$B:$B,"MISSING") -> #ERROR! | AG45: =COUNTIFS([2]ACTIVE_SCO!$B:$B,$B45,[2]ACTIVE_SCO!$P:$P,"Y") -> #ERROR! | AI45: FW28+ | AJ45: PLC: LS?? US-?? LSO-?? | AK45: SS27 | AM45: Essentials | AN45: Active Essentials | AO45: Essentials | AS45: Shell | AT45: Jacket | AU45: 2.5L | AV45: Y | BA45: SS27
A46: TRUE | B46: 608869 | C46: Zircon Proof Jacket Women | D46: Apparel | G46: OUT | I46: Shell | J46: ABS | K46: Women | M46: FALSE | N46: FALSE | O46: 2500 | P46: 2.1 | Q46: 1190.48 | R46: 0.64868792 | S46: Good | U46: Proof | V46: None | Y46: =IF(M46=TRUE,"CO",IF(N46=TRUE,"UPDATE","NEW")) -> NEW | Z46: =_xlfn.XLOOKUP($B46,[1]F27!$C:$C,[1]F27!$BV:$BV) -> #ERROR! | AD46: =_xlfn.XLOOKUP($B46,[1]F27!$C:$C,[1]F27!$Y:$Y) -> #ERROR! | AE46: =_xlfn.XLOOKUP($B46,[1]F27!$C:$C,[1]F27!$Z:$Z) -> #ERROR! | AF46: =_xlfn.XLOOKUP($B46,[2]PRICING!$B:$B,[2]PRICING!$B:$B,"MISSING") -> #ERROR! | AG46: =COUNTIFS([2]ACTIVE_SCO!$B:$B,$B46,[2]ACTIVE_SCO!$P:$P,"Y") -> #ERROR! | AI46: FW28+ | AJ46: PLC: LS?? US-?? LSO-?? | AK46: SS27 | AM46: Essentials | AN46: Active Essentials | AO46: Essentials | AS46: Shell | AT46: Jacket | AU46: 2.5L | AV46: Y | BA46: SS27
A47: TRUE | B47: 608822 | C47: Airak GTX Prototype Jacket Men | D47: Apparel | G47: L.I.M | I47: Shell | J47: ABS Exclusive | K47: Men | M47: FALSE | N47: FALSE | O47: 0 | P47: 2.1 | Q47: 0 | R47: #DIV/0! | U47: Gore-Tex | X47: KA YO Collab | Y47: =IF(M47=TRUE,"CO",IF(N47=TRUE,"UPDATE","NEW")) -> NEW | Z47: =_xlfn.XLOOKUP($B47,[1]F27!$C:$C,[1]F27!$BV:$BV) -> #ERROR! | AA47: =TEXT(IF(_xlfn.XLOOKUP($B47,[2]STYLE_LINK!L:L,[2]STYLE_LINK!J:J,"")=$B47,"",_xlfn.XLOOKUP($B47,[2]STYLE_LINK!L:L,[2]STYLE_LINK!J:J,"")),0) -> #ERROR! | AB47: =_xlfn.XLOOKUP(AA47,[2]STYLE_LINK!J:J,[2]STYLE_LINK!K:K,"") -> #ERROR! | AD47: =_xlfn.XLOOKUP($B47,[1]F27!$C:$C,[1]F27!$Y:$Y) -> #ERROR! | AE47: =_xlfn.XLOOKUP($B47,[1]F27!$C:$C,[1]F27!$Z:$Z) -> #ERROR! | AF47: =_xlfn.XLOOKUP($B47,[2]PRICING!$B:$B,[2]PRICING!$B:$B,"MISSING") -> #ERROR! | AG47: =COUNTIFS([2]ACTIVE_SCO!$B:$B,$B47,[2]ACTIVE_SCO!$P:$P,"Y") -> #ERROR! | AI47: FW27 | AK47: FW27 | AM47: Essentials | AN47: Active Essentials | AO47: Essentials | AS47: Shell | AT47: Jacket | AU47: 3L | AV47: Y | BA47: FW27
A48: TRUE | B48: 608596 | C48: Alert GTX Jacket Men AF | D48: Apparel | G48: OUT | I48: Shell | J48: ABS Exclusive | K48: Men | M48: TRUE | N48: FALSE | O48: 3800 | P48: 2.1 | Q48: 1809.52 | R48: 0.62236947 | S48: Good | U48: Gore-Tex | V48: None | X48: ASIA | Y48: =IF(M48=TRUE,"CO",IF(N48=TRUE,"UPDATE","NEW")) -> CO | Z48: =_xlfn.XLOOKUP($B48,[1]F27!$C:$C,[1]F27!$BV:$BV) -> #ERROR! | AD48: =_xlfn.XLOOKUP($B48,[1]F27!$C:$C,[1]F27!$Y:$Y) -> #ERROR! | AE48: =_xlfn.XLOOKUP($B48,[1]F27!$C:$C,[1]F27!$Z:$Z) -> #ERROR! | AF48: =_xlfn.XLOOKUP($B48,[2]PRICING!$B:$B,[2]PRICING!$B:$B,"MISSING") -> #ERROR! | AG48: =COUNTIFS([2]ACTIVE_SCO!$B:$B,$B48,[2]ACTIVE_SCO!$P:$P,"Y") -> #ERROR! | AI48: FW28+ | AJ48: PLC: LS?? US-?? LSO-?? | AK48: SS26 | AM48: Outdoor | AN48: Day Hiking | AO48: Outdoor | AP48: Hiking | AQ48: Essentials | AS48: Shell | AT48: Jacket | AU48: 2L | AV48: Y | BA48: SS26
A49: TRUE | B49: 608819 | C49: Hede Down Prototype Hood Men | D49: Apparel | G49: DAY | I49: Insulation | J49: ABS Exclusive | K49: Men | M49: FALSE | N49: FALSE | O49: 0 | P49: 2.1 | Q49: 0 | R49: #DIV/0! | U49: Down | X49: KA YO Collab | Y49: =IF(M49=TRUE,"CO",IF(N49=TRUE,"UPDATE","NEW")) -> NEW | Z49: =_xlfn.XLOOKUP($B49,[1]F27!$C:$C,[1]F27!$BV:$BV) -> #ERROR! | AD49: =_xlfn.XLOOKUP($B49,[1]F27!$C:$C,[1]F27!$Y:$Y) -> #ERROR! | AE49: =_xlfn.XLOOKUP($B49,[1]F27!$C:$C,[1]F27!$Z:$Z) -> #ERROR! | AF49: =_xlfn.XLOOKUP($B49,[2]PRICING!$B:$B,[2]PRICING!$B:$B,"MISSING") -> #ERROR! | AG49: =COUNTIFS([2]ACTIVE_SCO!$B:$B,$B49,[2]ACTIVE_SCO!$P:$P,"Y") -> #ERROR! | AI49: FW27 | AK49: FW27 | AM49: Essentials | AN49: Active Essentials | AO49: Everyday | AP49: Lifestyle | AS49: Insulation | AT49: Hooded Jacket | AU49: Lightweight Down | AV49: N | BA49: FW27
A50: TRUE | B50: 608600 | C50: Korp Lite Pant Men AF | D50: Apparel | G50: OUT | I50: Legwear | J50: ABS Exclusive | K50: Men | M50: TRUE | N50: FALSE | O50: 1300 | P50: 2.1 | Q50: 619.05 | R50: 0.6708505 | S50: Good | U50: None | V50: None | X50: ASIA | Y50: =IF(M50=TRUE,"CO",IF(N50=TRUE,"UPDATE","NEW")) -> CO | Z50: =_xlfn.XLOOKUP($B50,[1]F27!$C:$C,[1]F27!$BV:$BV) -> #ERROR! | AD50: =_xlfn.XLOOKUP($B50,[1]F27!$C:$C,[1]F27!$Y:$Y) -> #ERROR! | AE50: =_xlfn.XLOOKUP($B50,[1]F27!$C:$C,[1]F27!$Z:$Z) -> #ERROR! | AF50: =_xlfn.XLOOKUP($B50,[2]PRICING!$B:$B,[2]PRICING!$B:$B,"MISSING") -> #ERROR! | AG50: =COUNTIFS([2]ACTIVE_SCO!$B:$B,$B50,[2]ACTIVE_SCO!$P:$P,"Y") -> #ERROR! | AI50: FW28+ | AJ50: PLC: LS?? US-?? LSO-?? | AK50: SS26 | AM50: Outdoor | AN50: Day Hiking | AO50: Outdoor | AP50: Hiking | AS50: Softshell | AT50: Pant | AU50: Classic Softshell | AV50: N | BA50: SS26
A51: TRUE | B51: 608823 | C51: Magma Rugged Prototype Pant Men | D51: Apparel | G51: OUT | I51: Legwear | J51: ABS Exclusive | K51: Men | M51: FALSE | N51: FALSE | O51: 0 | P51: 2.1 | Q51: 0 | R51: #DIV/0! | X51: KA YO Collab | Y51: =IF(M51=TRUE,"CO",IF(N51=TRUE,"UPDATE","NEW")) -> NEW | Z51: =_xlfn.XLOOKUP($B51,[1]F27!$C:$C,[1]F27!$BV:$BV) -> #ERROR! | AD51: =_xlfn.XLOOKUP($B51,[1]F27!$C:$C,[1]F27!$Y:$Y) -> #ERROR! | AE51: =_xlfn.XLOOKUP($B51,[1]F27!$C:$C,[1]F27!$Z:$Z) -> #ERROR! | AF51: =_xlfn.XLOOKUP($B51,[2]PRICING!$B:$B,[2]PRICING!$B:$B,"MISSING") -> #ERROR! | AG51: =COUNTIFS([2]ACTIVE_SCO!$B:$B,$B51,[2]ACTIVE_SCO!$P:$P,"Y") -> #ERROR! | AI51: SS28 | AK51: FW27 | AM51: Outdoor | AN51: Trekking | AO51: Outdoor | AP51: Hiking | AS51: Softshell | AT51: Pant | AU51: Classic Softshell | AV51: N | BA51: FW27
A52: TRUE | B52: 608601 | C52: Ozka Proof Jacket Men AF | D52: Apparel | G52: OUT | I52: Shell | J52: ABS Exclusive | K52: Men | M52: TRUE | N52: FALSE | O52: 3000 | P52: 2.1 | Q52: 1428.57 | R52: 0.64102564 | S52: Better | U52: Proof | V52: None | X52: ASIA | Y52: =IF(M52=TRUE,"CO",IF(N52=TRUE,"UPDATE","NEW")) -> CO | Z52: =_xlfn.XLOOKUP($B52,[1]F27!$C:$C,[1]F27!$BV:$BV) -> #ERROR! | AD52: =_xlfn.XLOOKUP($B52,[1]F27!$C:$C,[1]F27!$Y:$Y) -> #ERROR! | AE52: =_xlfn.XLOOKUP($B52,[1]F27!$C:$C,[1]F27!$Z:$Z) -> #ERROR! | AF52: =_xlfn.XLOOKUP($B52,[2]PRICING!$B:$B,[2]PRICING!$B:$B,"MISSING") -> #ERROR! | AG52: =COUNTIFS([2]ACTIVE_SCO!$B:$B,$B52,[2]ACTIVE_SCO!$P:$P,"Y") -> #ERROR! | AI52: FW28+ | AJ52: PLC: LS?? US-?? LSO-?? | AK52: SS26 | AM52: Outdoor | AN52: Hiking | AO52: Outdoor | AP52: Hiking | AS52: Shell | AT52: Jacket | AU52: 2L | AV52: Y | BA52: SS26
A53: TRUE | B53: 608688 | C53: Aze II Beanie | D53: Apparel | G53: OUT | I53: Accessories | J53: Inline | K53: Unisex | M53: FALSE | N53: TRUE | O53: 300 | P53: 2.1 | Q53: 142.86 | R53: 0.56397872 | S53: Good | U53: None | V53: None | Y53: =IF(M53=TRUE,"CO",IF(N53=TRUE,"UPDATE","NEW")) -> UPDATE | Z53: =_xlfn.XLOOKUP($B53,[1]F27!$C:$C,[1]F27!$BV:$BV) -> #ERROR! | AD53: =_xlfn.XLOOKUP($B53,[1]F27!$C:$C,[1]F27!$Y:$Y) -> #ERROR! | AE53: =_xlfn.XLOOKUP($B53,[1]F27!$C:$C,[1]F27!$Z:$Z) -> #ERROR! | AF53: =_xlfn.XLOOKUP($B53,[2]PRICING!$B:$B,[2]PRICING!$B:$B,"MISSING") -> #ERROR! | AG53: =COUNTIFS([2]ACTIVE_SCO!$B:$B,$B53,[2]ACTIVE_SCO!$P:$P,"Y") -> #ERROR! | AI53: FW28+ | AJ53: CORE: PLC: LS-FW27 US-FW30 LSO-?? | AK53: FW27 | AM53: Essentials | AN53: Active Essentials | AO53: Essentials | AQ53: Essentials | AS53: Accessories | AT53: Headwear | AU53: Beanie | AV53: N | BA53: FW27
A54: TRUE | B54: 608773 | C54: Polka Outsiders Graphic Tee Men | D54: Apparel | G54: OUT | I54: Tops | J54: ABS Exclusive | K54: Men | M54: FALSE | N54: FALSE | O54: 450 | P54: 2.1 | Q54: 214.29 | R54: 0.62224089 | S54: Better | U54: None | V54: None | X54: DTC | Y54: =IF(M54=TRUE,"CO",IF(N54=TRUE,"UPDATE","NEW")) -> NEW | Z54: =_xlfn.XLOOKUP($B54,[1]F27!$C:$C,[1]F27!$BV:$BV) -> #ERROR! | AD54: =_xlfn.XLOOKUP($B54,[1]F27!$C:$C,[1]F27!$Y:$Y) -> #ERROR! | AE54: =_xlfn.XLOOKUP($B54,[1]F27!$C:$C,[1]F27!$Z:$Z) -> #ERROR! | AF54: =_xlfn.XLOOKUP($B54,[2]PRICING!$B:$B,[2]PRICING!$B:$B,"MISSING") -> #ERROR! | AG54: =COUNTIFS([2]ACTIVE_SCO!$B:$B,$B54,[2]ACTIVE_SCO!$P:$P,"Y") -> #ERROR! | AI54: FW27 | AK54: FW27 | AM54: Essentials | AN54: Daily Essentials | AO54: Everyday | AP54: Lifestyle | AS54: Tops | AT54: Tee | AU54: Cotton/Graphic Tee | AV54: N | BA54: FW27
A55: TRUE | B55: 608772 | C55: Polka Outsiders Graphic Tee Women | D55: Apparel | G55: OUT | I55: Tops | J55: ABS Exclusive | K55: Women | M55: FALSE | N55: FALSE | O55: 450 | P55: 2.1 | Q55: 214.29 | R55: 0.64216716 | S55: Better | U55: None | V55: None | X55: DTC | Y55: =IF(M55=TRUE,"CO",IF(N55=TRUE,"UPDATE","NEW")) -> NEW | Z55: =_xlfn.XLOOKUP($B55,[1]F27!$C:$C,[1]F27!$BV:$BV) -> #ERROR! | AD55: =_xlfn.XLOOKUP($B55,[1]F27!$C:$C,[1]F27!$Y:$Y) -> #ERROR! | AE55: =_xlfn.XLOOKUP($B55,[1]F27!$C:$C,[1]F27!$Z:$Z) -> #ERROR! | AF55: =_xlfn.XLOOKUP($B55,[2]PRICING!$B:$B,[2]PRICING!$B:$B,"MISSING") -> #ERROR! | AG55: =COUNTIFS([2]ACTIVE_SCO!$B:$B,$B55,[2]ACTIVE_SCO!$P:$P,"Y") -> #ERROR! | AI55: FW27 | AK55: FW27 | AM55: Essentials | AN55: Daily Essentials | AO55: Everyday | AP55: Lifestyle | AS55: Tops | AT55: Tee | AU55: Cotton/Graphic Tee | AV55: N | BA55: FW27
A56: TRUE | B56: 608767 | C56: Polka Saulo Proof Jacket Men | D56: Apparel | G56: SNW | I56: Shell | J56: ABS Exclusive | K56: Men | M56: FALSE | N56: FALSE | O56: 3500 | P56: 2.1 | Q56: 1666.67 | R56: 0.68977062 | S56: Good | U56: Proof | V56: None | X56: DTC | Y56: =IF(M56=TRUE,"CO",IF(N56=TRUE,"UPDATE","NEW")) -> NEW | Z56: =_xlfn.XLOOKUP($B56,[1]F27!$C:$C,[1]F27!$BV:$BV) -> #ERROR! | AD56: =_xlfn.XLOOKUP($B56,[1]F27!$C:$C,[1]F27!$Y:$Y) -> #ERROR! | AE56: =_xlfn.XLOOKUP($B56,[1]F27!$C:$C,[1]F27!$Z:$Z) -> #ERROR! | AF56: =_xlfn.XLOOKUP($B56,[2]PRICING!$B:$B,[2]PRICING!$B:$B,"MISSING") -> #ERROR! | AG56: =COUNTIFS([2]ACTIVE_SCO!$B:$B,$B56,[2]ACTIVE_SCO!$P:$P,"Y") -> #ERROR! | AI56: FW27 | AK56: FW27 | AM56: Skiing/Snowboarding | AN56: All Mountain | AO56: Skiing/Snowboarding | AP56: All Mountain | AS56: Shell | AT56: Jacket | AU56: 3L | AV56: Y | BA56: FW27
A57: TRUE | B57: 608770 | C57: Polka Saulo Proof Jacket Women | D57: Apparel | G57: SNW | I57: Shell | J57: ABS Exclusive | K57: Women | M57: FALSE | N57: FALSE | O57: 3500 | P57: 2.1 | Q57: 1666.67 | R57: 0.70954058 | S57: Good | U57: Proof | V57: None | X57: DTC | Y57: =IF(M57=TRUE,"CO",IF(N57=TRUE,"UPDATE","NEW")) -> NEW | Z57: =_xlfn.XLOOKUP($B57,[1]F27!$C:$C,[1]F27!$BV:$BV) -> #ERROR! | AD57: =_xlfn.XLOOKUP($B57,[1]F27!$C:$C,[1]F27!$Y:$Y) -> #ERROR! | AE57: =_xlfn.XLOOKUP($B57,[1]F27!$C:$C,[1]F27!$Z:$Z) -> #ERROR! | AF57: =_xlfn.XLOOKUP($B57,[2]PRICING!$B:$B,[2]PRICING!$B:$B,"MISSING") -> #ERROR! | AG57: =COUNTIFS([2]ACTIVE_SCO!$B:$B,$B57,[2]ACTIVE_SCO!$P:$P,"Y") -> #ERROR! | AI57: FW27 | AK57: FW27 | AM57: Skiing/Snowboarding | AN57: All Mountain | AO57: Skiing/Snowboarding | AP57: All Mountain | AS57: Shell | AT57: Jacket | AU57: 3L | AV57: Y | BA57: FW27
A58: FALSE | B58: 608652 | C58: Gabbro II Pant Men | D58: Apparel | G58: OUT | I58: Softshell | J58: ABS | K58: Men | M58: TRUE | N58: FALSE | O58: 2200 | P58: 2.1 | Q58: 1047.62 | R58: 0.69682709 | S58: Better | U58: None | V58: None | X58: XXL | Y58: =IF(M58=TRUE,"CO",IF(N58=TRUE,"UPDATE","NEW")) -> CO | Z58: =_xlfn.XLOOKUP($B58,[1]F27!$C:$C,[1]F27!$BV:$BV) -> #ERROR! | AD58: =_xlfn.XLOOKUP($B58,[1]F27!$C:$C,[1]F27!$Y:$Y) -> #ERROR! | AE58: =_xlfn.XLOOKUP($B58,[1]F27!$C:$C,[1]F27!$Z:$Z) -> #ERROR! | AF58: =_xlfn.XLOOKUP($B58,[2]PRICING!$B:$B,[2]PRICING!$B:$B,"MISSING") -> #ERROR! | AG58: =COUNTIFS([2]ACTIVE_SCO!$B:$B,$B58,[2]ACTIVE_SCO!$P:$P,"Y") -> #ERROR! | AI58: REVIEW
A59: FALSE | B59: 608653 | C59: Gabbro II Pant Women | D59: Apparel | G59: OUT | I59: Softshell | J59: ABS | K59: Women | M59: TRUE | N59: FALSE | O59: 2200 | P59: 2.1 | Q59: 1047.62 | R59: 0.71743571 | S59: Better | U59: None | V59: None | X59: XXL | Y59: =IF(M59=TRUE,"CO",IF(N59=TRUE,"UPDATE","NEW")) -> CO | Z59: =_xlfn.XLOOKUP($B59,[1]F27!$C:$C,[1]F27!$BV:$BV) -> #ERROR! | AD59: =_xlfn.XLOOKUP($B59,[1]F27!$C:$C,[1]F27!$Y:$Y) -> #ERROR! | AE59: =_xlfn.XLOOKUP($B59,[1]F27!$C:$C,[1]F27!$Z:$Z) -> #ERROR! | AF59: =_xlfn.XLOOKUP($B59,[2]PRICING!$B:$B,[2]PRICING!$B:$B,"MISSING") -> #ERROR! | AG59: =COUNTIFS([2]ACTIVE_SCO!$B:$B,$B59,[2]ACTIVE_SCO!$P:$P,"Y") -> #ERROR! | AI59: REVIEW
A60: TRUE | B60: 608768 | C60: Polka Saulo Proof Pant Men | D60: Apparel | G60: SNW | I60: Shell | J60: ABS Exclusive | K60: Men | M60: FALSE | N60: FALSE | O60: 3100 | P60: 2.1 | Q60: 1476.19 | R60: 0.74318347 | S60: Good | U60: Proof | V60: None | X60: DTC | Y60: =IF(M60=TRUE,"CO",IF(N60=TRUE,"UPDATE","NEW")) -> NEW | Z60: =_xlfn.XLOOKUP($B60,[1]F27!$C:$C,[1]F27!$BV:$BV) -> #ERROR! | AD60: =_xlfn.XLOOKUP($B60,[1]F27!$C:$C,[1]F27!$Y:$Y) -> #ERROR! | AE60: =_xlfn.XLOOKUP($B60,[1]F27!$C:$C,[1]F27!$Z:$Z) -> #ERROR! | AF60: =_xlfn.XLOOKUP($B60,[2]PRICING!$B:$B,[2]PRICING!$B:$B,"MISSING") -> #ERROR! | AG60: =COUNTIFS([2]ACTIVE_SCO!$B:$B,$B60,[2]ACTIVE_SCO!$P:$P,"Y") -> #ERROR! | AI60: FW27 | AK60: FW27 | AM60: Skiing/Snowboarding | AN60: All Mountain | AO60: Skiing/Snowboarding | AP60: All Mountain | AS60: Shell | AT60: Pant | AU60: 3L | AV60: Y | BA60: FW27
A61: TRUE | B61: 608771 | C61: Polka Saulo Proof Pant Women | D61: Apparel | G61: SNW | I61: Shell | J61: ABS Exclusive | K61: Women | M61: FALSE | N61: FALSE | O61: 3100 | P61: 2.1 | Q61: 1476.19 | R61: 0.75567508 | S61: Good | U61: Proof | V61: None | X61: DTC | Y61: =IF(M61=TRUE,"CO",IF(N61=TRUE,"UPDATE","NEW")) -> NEW | Z61: =_xlfn.XLOOKUP($B61,[1]F27!$C:$C,[1]F27!$BV:$BV) -> #ERROR! | AD61: =_xlfn.XLOOKUP($B61,[1]F27!$C:$C,[1]F27!$Y:$Y) -> #ERROR! | AE61: =_xlfn.XLOOKUP($B61,[1]F27!$C:$C,[1]F27!$Z:$Z) -> #ERROR! | AF61: =_xlfn.XLOOKUP($B61,[2]PRICING!$B:$B,[2]PRICING!$B:$B,"MISSING") -> #ERROR! | AG61: =COUNTIFS([2]ACTIVE_SCO!$B:$B,$B61,[2]ACTIVE_SCO!$P:$P,"Y") -> #ERROR! | AI61: FW27 | AK61: FW27 | AM61: Skiing/Snowboarding | AN61: All Mountain | AO61: Skiing/Snowboarding | AP61: All Mountain | AS61: Shell | AT61: Pant | AU61: 3L | AV61: Y | BA61: FW27
A62: TRUE | B62: 608620 | C62: Mid Slim II Pant Men | D62: Apparel | G62: OUT | I62: Legwear | J62: ABS Exclusive | K62: Men | M62: TRUE | N62: FALSE | O62: 1300 | P62: 2.1 | Q62: 619.05 | R62: 0.55905016 | S62: Better | U62: None | V62: None | X62: ASIA | Y62: =IF(M62=TRUE,"CO",IF(N62=TRUE,"UPDATE","NEW")) -> CO | Z62: =_xlfn.XLOOKUP($B62,[1]F27!$C:$C,[1]F27!$BV:$BV) -> #ERROR! | AD62: =_xlfn.XLOOKUP($B62,[1]F27!$C:$C,[1]F27!$Y:$Y) -> #ERROR! | AE62: =_xlfn.XLOOKUP($B62,[1]F27!$C:$C,[1]F27!$Z:$Z) -> #ERROR! | AF62: =_xlfn.XLOOKUP($B62,[2]PRICING!$B:$B,[2]PRICING!$B:$B,"MISSING") -> #ERROR! | AG62: =COUNTIFS([2]ACTIVE_SCO!$B:$B,$B62,[2]ACTIVE_SCO!$P:$P,"Y") -> #ERROR! | AI62: FW28+ | AJ62: PLC: LS?? US-?? LSO-?? | AK62: Pre S23 | AL62: FW26 | AM62: Outdoor | AN62: Day Hiking | AO62: Outdoor | AP62: Hiking | AS62: Softshell | AT62: Pant | AU62: Classic Softshell | AV62: N | BA62: Pre S23 | BB62: FW26
A63: TRUE | B63: 608619 | C63: Mid Slim II Pant Women | D63: Apparel | G63: OUT | I63: Legwear | J63: ABS Exclusive | K63: Women | M63: TRUE | N63: FALSE | O63: 1300 | P63: 2.1 | Q63: 619.05 | R63: 0.56316937 | S63: Better | U63: Climatic | V63: None | X63: ASIA | Y63: =IF(M63=TRUE,"CO",IF(N63=TRUE,"UPDATE","NEW")) -> CO | Z63: =_xlfn.XLOOKUP($B63,[1]F27!$C:$C,[1]F27!$BV:$BV) -> #ERROR! | AD63: =_xlfn.XLOOKUP($B63,[1]F27!$C:$C,[1]F27!$Y:$Y) -> #ERROR! | AE63: =_xlfn.XLOOKUP($B63,[1]F27!$C:$C,[1]F27!$Z:$Z) -> #ERROR! | AF63: =_xlfn.XLOOKUP($B63,[2]PRICING!$B:$B,[2]PRICING!$B:$B,"MISSING") -> #ERROR! | AG63: =COUNTIFS([2]ACTIVE_SCO!$B:$B,$B63,[2]ACTIVE_SCO!$P:$P,"Y") -> #ERROR! | AI63: FW28+ | AJ63: PLC: LS?? US-?? LSO-?? | AK63: Pre S23 | AL63: FW26 | AM63: Outdoor | AN63: Day Hiking | AO63: Outdoor | AP63: Hiking | AS63: Softshell | AT63: Pant | AU63: Classic Softshell | AV63: N | BA63: Pre S23 | BB63: FW26
A64: TRUE | B64: 608616 | C64: Rugged Slim II Pant Men | D64: Apparel | G64: OUT | I64: Legwear | J64: ABS Exclusive | K64: Men | M64: TRUE | N64: FALSE | O64: 2200 | P64: 2.1 | Q64: 1047.62 | R64: 0.69263664 | S64: Best | U64: Climatic | V64: None | X64: ASIA | Y64: =IF(M64=TRUE,"CO",IF(N64=TRUE,"UPDATE","NEW")) -> CO | Z64: =_xlfn.XLOOKUP($B64,[1]F27!$C:$C,[1]F27!$BV:$BV) -> #ERROR! | AD64: =_xlfn.XLOOKUP($B64,[1]F27!$C:$C,[1]F27!$Y:$Y) -> #ERROR! | AE64: =_xlfn.XLOOKUP($B64,[1]F27!$C:$C,[1]F27!$Z:$Z) -> #ERROR! | AF64: =_xlfn.XLOOKUP($B64,[2]PRICING!$B:$B,[2]PRICING!$B:$B,"MISSING") -> #ERROR! | AG64: =COUNTIFS([2]ACTIVE_SCO!$B:$B,$B64,[2]ACTIVE_SCO!$P:$P,"Y") -> #ERROR! | AI64: FW28+ | AJ64: PLC: LS?? US-?? LSO-?? | AK64: Pre S23 | AL64: FW26 | AM64: Outdoor | AN64: Trekking | AO64: Outdoor | AP64: Hiking | AS64: Softshell | AT64: Pant | AU64: Classic Softshell | AV64: N | AY64: TR & FH? | BA64: Pre S23 | BB64: FW26 | BD64: Updated in S23
A65: TRUE | B65: 608617 | C65: Rugged Slim II Pant Women | D65: Apparel | G65: OUT | I65: Legwear | J65: ABS Exclusive | K65: Women | M65: TRUE | N65: FALSE | O65: 2200 | P65: 2.1 | Q65: 1047.62 | R65: 0.61129035 | S65: Best | U65: None | V65: None | X65: ASIA | Y65: =IF(M65=TRUE,"CO",IF(N65=TRUE,"UPDATE","NEW")) -> CO | Z65: =_xlfn.XLOOKUP($B65,[1]F27!$C:$C,[1]F27!$BV:$BV) -> #ERROR! | AD65: =_xlfn.XLOOKUP($B65,[1]F27!$C:$C,[1]F27!$Y:$Y) -> #ERROR! | AE65: =_xlfn.XLOOKUP($B65,[1]F27!$C:$C,[1]F27!$Z:$Z) -> #ERROR! | AF65: =_xlfn.XLOOKUP($B65,[2]PRICING!$B:$B,[2]PRICING!$B:$B,"MISSING") -> #ERROR! | AG65: =COUNTIFS([2]ACTIVE_SCO!$B:$B,$B65,[2]ACTIVE_SCO!$P:$P,"Y") -> #ERROR! | AI65: FW28+ | AJ65: PLC: LS?? US-?? LSO-?? | AK65: Pre S23 | AL65: FW26 | AM65: Outdoor | AN65: Trekking | AO65: Outdoor | AP65: Hiking | AS65: Softshell | AT65: Pant | AU65: Classic Softshell | AV65: N | AY65: TR & FH? | BA65: Pre S23 | BB65: FW26 | BD65: Updated in S23
A66: TRUE | B66: 608587 | C66: Brand Five Panel Cap | D66: Apparel | G66: DAY | I66: Accessories | J66: Inline | K66: Unisex | M66: TRUE | N66: FALSE | O66: 450 | P66: 2.1 | Q66: 214.29 | R66: 0.68971954 | S66: Better | U66: None | V66: None | Y66: =IF(M66=TRUE,"CO",IF(N66=TRUE,"UPDATE","NEW")) -> CO | Z66: =_xlfn.XLOOKUP($B66,[1]F27!$C:$C,[1]F27!$BV:$BV) -> #ERROR! | AD66: =_xlfn.XLOOKUP($B66,[1]F27!$C:$C,[1]F27!$Y:$Y) -> #ERROR! | AE66: =_xlfn.XLOOKUP($B66,[1]F27!$C:$C,[1]F27!$Z:$Z) -> #ERROR! | AF66: =_xlfn.XLOOKUP($B66,[2]PRICING!$B:$B,[2]PRICING!$B:$B,"MISSING") -> #ERROR! | AG66: =COUNTIFS([2]ACTIVE_SCO!$B:$B,$B66,[2]ACTIVE_SCO!$P:$P,"Y") -> #ERROR! | AI66: FW28+ | AJ66: CORE: PLC: LS?? US-?? LSO-?? | AK66: FW27 | AM66: Essentials | AN66: Active Essentials | AO66: Everyday | AP66: Lifestyle | AS66: Accessories | AT66: Headwear | AU66: Cap | AV66: N | BA66: FW27
A67: TRUE | B67: 607538 | C67: Latnja Wool 3/4 Pant Men | D67: Apparel | G67: SNW | I67: Baselayer | J67: Inline | K67: Men | M67: TRUE | N67: FALSE | O67: 900 | P67: 2.1 | Q67: 428.57 | R67: 0.59724199 | S67: Better | U67: None | V67: None | Y67: =IF(M67=TRUE,"CO",IF(N67=TRUE,"UPDATE","NEW")) -> CO | Z67: =_xlfn.XLOOKUP($B67,[1]F27!$C:$C,[1]F27!$BV:$BV) -> #ERROR! | AD67: =_xlfn.XLOOKUP($B67,[1]F27!$C:$C,[1]F27!$Y:$Y) -> #ERROR! | AE67: =_xlfn.XLOOKUP($B67,[1]F27!$C:$C,[1]F27!$Z:$Z) -> #ERROR! | AF67: =_xlfn.XLOOKUP($B67,[2]PRICING!$B:$B,[2]PRICING!$B:$B,"MISSING") -> #ERROR! | AG67: =COUNTIFS([2]ACTIVE_SCO!$B:$B,$B67,[2]ACTIVE_SCO!$P:$P,"Y") -> #ERROR! | AI67: FW27 | AJ67: Replaced with new basic baselayers FW28 | AK67: SS26 | AL67: FW27 | AM67: Essentials | AN67: Active Essentials | AO67: Essentials | AQ67: Essentials | AS67: Baselayer | AT67: Pant | AU67: Merino Wool | AV67: N | BA67: SS26 | BB67: FW27
A68: TRUE | B68: 608821 | C68: Vara Alpha Prototype Sweater Men | D68: Apparel | G68: DAY | I68: Tops | J68: ABS Exclusive | K68: Men | M68: FALSE | N68: FALSE | O68: 0 | P68: 2.1 | Q68: 0 | R68: #DIV/0! | U68: Polartec | X68: KA YO Collab | Y68: =IF(M68=TRUE,"CO",IF(N68=TRUE,"UPDATE","NEW")) -> NEW | Z68: =_xlfn.XLOOKUP($B68,[1]F27!$C:$C,[1]F27!$BV:$BV) -> #ERROR! | AD68: =_xlfn.XLOOKUP($B68,[1]F27!$C:$C,[1]F27!$Y:$Y) -> #ERROR! | AE68: =_xlfn.XLOOKUP($B68,[1]F27!$C:$C,[1]F27!$Z:$Z) -> #ERROR! | AF68: =_xlfn.XLOOKUP($B68,[2]PRICING!$B:$B,[2]PRICING!$B:$B,"MISSING") -> #ERROR! | AG68: =COUNTIFS([2]ACTIVE_SCO!$B:$B,$B68,[2]ACTIVE_SCO!$P:$P,"Y") -> #ERROR! | AI68: FW27 | AK68: FW27 | AM68: Essentials | AN68: Daily Essentials | AS68: Tops | AT68: Pullover | AU68: Cotton/Graphic Tee | AV68: N | BA68: FW27
A69: TRUE | B69: 607539 | C69: Latnja Wool 3/4 Pant Women | D69: Apparel | G69: SNW | I69: Baselayer | J69: Inline | K69: Women | M69: TRUE | N69: FALSE | O69: 900 | P69: 2.1 | Q69: 428.57 | R69: 0.60503535 | S69: Better | U69: None | V69: None | Y69: =IF(M69=TRUE,"CO",IF(N69=TRUE,"UPDATE","NEW")) -> CO | Z69: =_xlfn.XLOOKUP($B69,[1]F27!$C:$C,[1]F27!$BV:$BV) -> #ERROR! | AD69: =_xlfn.XLOOKUP($B69,[1]F27!$C:$C,[1]F27!$Y:$Y) -> #ERROR! | AE69: =_xlfn.XLOOKUP($B69,[1]F27!$C:$C,[1]F27!$Z:$Z) -> #ERROR! | AF69: =_xlfn.XLOOKUP($B69,[2]PRICING!$B:$B,[2]PRICING!$B:$B,"MISSING") -> #ERROR! | AG69: =COUNTIFS([2]ACTIVE_SCO!$B:$B,$B69,[2]ACTIVE_SCO!$P:$P,"Y") -> #ERROR! | AI69: FW27 | AJ69: Replaced with new basic baselayers FW28 | AK69: FW27 | AM69: Essentials | AN69: Active Essentials | AO69: Essentials | AQ69: Essentials | AS69: Baselayer | AT69: Pant | AU69: Merino Wool | AV69: N | BA69: FW27
A70: TRUE | B70: 608172 | C70: Alert GTX Jacket Men | D70: Apparel | G70: OUT | I70: Shell | J70: Inline | K70: Men | M70: TRUE | N70: FALSE | O70: 3800 | P70: 2.1 | Q70: 1809.52 | R70: 0.61263208 | S70: Good | U70: Gore-Tex | V70: None | Y70: =IF(M70=TRUE,"CO",IF(N70=TRUE,"UPDATE","NEW")) -> CO | Z70: =_xlfn.XLOOKUP($B70,[1]F27!$C:$C,[1]F27!$BV:$BV) -> #ERROR! | AD70: =_xlfn.XLOOKUP($B70,[1]F27!$C:$C,[1]F27!$Y:$Y) -> #ERROR! | AE70: =_xlfn.XLOOKUP($B70,[1]F27!$C:$C,[1]F27!$Z:$Z) -> #ERROR! | AF70: =_xlfn.XLOOKUP($B70,[2]PRICING!$B:$B,[2]PRICING!$B:$B,"MISSING") -> #ERROR! | AG70: =COUNTIFS([2]ACTIVE_SCO!$B:$B,$B70,[2]ACTIVE_SCO!$P:$P,"Y") -> #ERROR! | AI70: FW28+ | AJ70: PLC: LS?? US-?? LSO-?? | AL70: SS26 | AM70: Outdoor | AN70: Day Hiking | AO70: Outdoor | AP70: Hiking | AS70: Shell | AT70: Jacket | AU70: 2L | AV70: Y | BB70: SS26
A71: TRUE | B71: 608192 | C71: Alert GTX Jacket Women | D71: Apparel | G71: OUT | I71: Shell | J71: Inline | K71: Women | M71: TRUE | N71: FALSE | O71: 3800 | P71: 2.1 | Q71: 1809.52 | R71: 0.65826296 | S71: Good | U71: Gore-Tex | V71: None | Y71: =IF(M71=TRUE,"CO",IF(N71=TRUE,"UPDATE","NEW")) -> CO | Z71: =_xlfn.XLOOKUP($B71,[1]F27!$C:$C,[1]F27!$BV:$BV) -> #ERROR! | AD71: =_xlfn.XLOOKUP($B71,[1]F27!$C:$C,[1]F27!$Y:$Y) -> #ERROR! | AE71: =_xlfn.XLOOKUP($B71,[1]F27!$C:$C,[1]F27!$Z:$Z) -> #ERROR! | AF71: =_xlfn.XLOOKUP($B71,[2]PRICING!$B:$B,[2]PRICING!$B:$B,"MISSING") -> #ERROR! | AG71: =COUNTIFS([2]ACTIVE_SCO!$B:$B,$B71,[2]ACTIVE_SCO!$P:$P,"Y") -> #ERROR! | AI71: FW28+ | AJ71: PLC: LS?? US-?? LSO-?? | AL71: SS26 | AM71: Outdoor | AN71: Day Hiking | AO71: Outdoor | AP71: Hiking | AS71: Shell | AT71: Jacket | AU71: 2L | AV71: Y | BB71: SS26
A72: TRUE | B72: 607936 | C72: Alper Proof Jacket Men | D72: Apparel | G72: SNW | I72: Shell | J72: Inline | K72: Men | M72: TRUE | N72: FALSE | O72: 4000 | P72: 2.1 | Q72: 1904.76 | R72: 0.55883681 | S72: Better | U72: Proof | V72: None | Y72: =IF(M72=TRUE,"CO",IF(N72=TRUE,"UPDATE","NEW")) -> CO | Z72: =_xlfn.XLOOKUP($B72,[1]F27!$C:$C,[1]F27!$BV:$BV) -> #ERROR! | AD72: =_xlfn.XLOOKUP($B72,[1]F27!$C:$C,[1]F27!$Y:$Y) -> #ERROR! | AE72: =_xlfn.XLOOKUP($B72,[1]F27!$C:$C,[1]F27!$Z:$Z) -> #ERROR! | AF72: =_xlfn.XLOOKUP($B72,[2]PRICING!$B:$B,[2]PRICING!$B:$B,"MISSING") -> #ERROR! | AG72: =COUNTIFS([2]ACTIVE_SCO!$B:$B,$B72,[2]ACTIVE_SCO!$P:$P,"Y") -> #ERROR! | AI72: FW28+ | AJ72: CORE - PLC: LS-FW25 US-FW29 | AK72: FW25 | AM72: Skiing/Snowboarding | AN72: All Mountain | AO72: Skiing/Snowboarding | AP72: All Mountain | AS72: Shell | AT72: Jacket | AU72: 3L | AV72: Y | BA72: FW25
A73: TRUE | B73: 607937 | C73: Alper Proof Jacket Women | D73: Apparel | G73: SNW | I73: Shell | J73: Inline | K73: Women | M73: TRUE | N73: FALSE | O73: 4000 | P73: 2.1 | Q73: 1904.76 | R73: 0.58221508 | S73: Better | U73: Proof | V73: None | Y73: =IF(M73=TRUE,"CO",IF(N73=TRUE,"UPDATE","NEW")) -> CO | Z73: =_xlfn.XLOOKUP($B73,[1]F27!$C:$C,[1]F27!$BV:$BV) -> #ERROR! | AD73: =_xlfn.XLOOKUP($B73,[1]F27!$C:$C,[1]F27!$Y:$Y) -> #ERROR! | AE73: =_xlfn.XLOOKUP($B73,[1]F27!$C:$C,[1]F27!$Z:$Z) -> #ERROR! | AF73: =_xlfn.XLOOKUP($B73,[2]PRICING!$B:$B,[2]PRICING!$B:$B,"MISSING") -> #ERROR! | AG73: =COUNTIFS([2]ACTIVE_SCO!$B:$B,$B73,[2]ACTIVE_SCO!$P:$P,"Y") -> #ERROR! | AI73: FW28+ | AJ73: CORE - PLC: LS-FW25 US-FW29 | AK73: FW25 | AM73: Skiing/Snowboarding | AN73: All Mountain | AO73: Skiing/Snowboarding | AP73: All Mountain | AS73: Shell | AT73: Jacket | AU73: 3L | AV73: Y | BA73: FW25
A74: FALSE | B74: 608487 | C74: Kaja Proof II Jacket Men | D74: Apparel | G74: OUT | I74: Shell | J74: Inline | K74: Men | M74: TRUE | N74: FALSE | O74: 2500 | P74: 2.1 | Q74: 1190.48 | R74: 0.6254788 | S74: Good | U74: Proof | V74: None | X74: XXL | Y74: =IF(M74=TRUE,"CO",IF(N74=TRUE,"UPDATE","NEW")) -> CO | Z74: =_xlfn.XLOOKUP($B74,[1]F27!$C:$C,[1]F27!$BV:$BV) -> #ERROR! | AD74: =_xlfn.XLOOKUP($B74,[1]F27!$C:$C,[1]F27!$Y:$Y) -> #ERROR! | AE74: =_xlfn.XLOOKUP($B74,[1]F27!$C:$C,[1]F27!$Z:$Z) -> #ERROR! | AF74: =_xlfn.XLOOKUP($B74,[2]PRICING!$B:$B,[2]PRICING!$B:$B,"MISSING") -> #ERROR! | AG74: =COUNTIFS([2]ACTIVE_SCO!$B:$B,$B74,[2]ACTIVE_SCO!$P:$P,"Y") -> #ERROR! | AI74: REVIEW
A75: FALSE | B75: 608486 | C75: Kaja Proof II Jacket Women | D75: Apparel | G75: OUT | I75: Shell | J75: Inline | K75: Women | M75: TRUE | N75: FALSE | O75: 2500 | P75: 2.1 | Q75: 1190.48 | R75: 0.65062832 | S75: Good | U75: Proof | V75: None | X75: XXL | Y75: =IF(M75=TRUE,"CO",IF(N75=TRUE,"UPDATE","NEW")) -> CO | Z75: =_xlfn.XLOOKUP($B75,[1]F27!$C:$C,[1]F27!$BV:$BV) -> #ERROR! | AD75: =_xlfn.XLOOKUP($B75,[1]F27!$C:$C,[1]F27!$Y:$Y) -> #ERROR! | AE75: =_xlfn.XLOOKUP($B75,[1]F27!$C:$C,[1]F27!$Z:$Z) -> #ERROR! | AF75: =_xlfn.XLOOKUP($B75,[2]PRICING!$B:$B,[2]PRICING!$B:$B,"MISSING") -> #ERROR! | AG75: =COUNTIFS([2]ACTIVE_SCO!$B:$B,$B75,[2]ACTIVE_SCO!$P:$P,"Y") -> #ERROR! | AI75: REVIEW
A76: TRUE | B76: 607939 | C76: Alper Proof Pant Men | D76: Apparel | G76: SNW | I76: Shell | J76: Inline | K76: Men | M76: TRUE | N76: FALSE | O76: 3200 | P76: 2.1 | Q76: 1523.81 | R76: 0.56797764 | S76: Better | U76: Proof | V76: None | Y76: =IF(M76=TRUE,"CO",IF(N76=TRUE,"UPDATE","NEW")) -> CO | Z76: =_xlfn.XLOOKUP($B76,[1]F27!$C:$C,[1]F27!$BV:$BV) -> #ERROR! | AD76: =_xlfn.XLOOKUP($B76,[1]F27!$C:$C,[1]F27!$Y:$Y) -> #ERROR! | AE76: =_xlfn.XLOOKUP($B76,[1]F27!$C:$C,[1]F27!$Z:$Z) -> #ERROR! | AF76: =_xlfn.XLOOKUP($B76,[2]PRICING!$B:$B,[2]PRICING!$B:$B,"MISSING") -> #ERROR! | AG76: =COUNTIFS([2]ACTIVE_SCO!$B:$B,$B76,[2]ACTIVE_SCO!$P:$P,"Y") -> #ERROR! | AI76: FW28+ | AJ76: CORE - PLC: LS-FW25 US-FW29 | AK76: FW25 | AM76: Skiing/Snowboarding | AN76: All Mountain | AO76: Skiing/Snowboarding | AP76: All Mountain | AS76: Shell | AT76: Pant | AU76: 3L | AV76: Y | BA76: FW25
A77: TRUE | B77: 607938 | C77: Alper Proof Pant Women | D77: Apparel | G77: SNW | I77: Shell | J77: Inline | K77: Women | M77: TRUE | N77: FALSE | O77: 3200 | P77: 2.1 | Q77: 1523.81 | R77: 0.57668607 | S77: Better | U77: Proof | V77: None | Y77: =IF(M77=TRUE,"CO",IF(N77=TRUE,"UPDATE","NEW")) -> CO | Z77: =_xlfn.XLOOKUP($B77,[1]F27!$C:$C,[1]F27!$BV:$BV) -> #ERROR! | AD77: =_xlfn.XLOOKUP($B77,[1]F27!$C:$C,[1]F27!$Y:$Y) -> #ERROR! | AE77: =_xlfn.XLOOKUP($B77,[1]F27!$C:$C,[1]F27!$Z:$Z) -> #ERROR! | AF77: =_xlfn.XLOOKUP($B77,[2]PRICING!$B:$B,[2]PRICING!$B:$B,"MISSING") -> #ERROR! | AG77: =COUNTIFS([2]ACTIVE_SCO!$B:$B,$B77,[2]ACTIVE_SCO!$P:$P,"Y") -> #ERROR! | AI77: FW28+ | AJ77: CORE - PLC: LS-FW25 US-FW29 | AK77: FW25 | AM77: Skiing/Snowboarding | AN77: All Mountain | AO77: Skiing/Snowboarding | AP77: All Mountain | AS77: Shell | AT77: Pant | AU77: 3L | AV77: Y | BA77: FW25
A78: FALSE | B78: 608654 | C78: Klyva GTX Pant Men | D78: Apparel | G78: OUT | I78: Shell | J78: ABS | K78: Men | M78: TRUE | N78: FALSE | O78: 2800 | P78: 2.1 | Q78: 1333.33 | R78: 0.57790644 | S78: Better | U78: Gore-Tex | V78: None | X78: XXL | Y78: =IF(M78=TRUE,"CO",IF(N78=TRUE,"UPDATE","NEW")) -> CO | Z78: =_xlfn.XLOOKUP($B78,[1]F27!$C:$C,[1]F27!$BV:$BV) -> #ERROR! | AD78: =_xlfn.XLOOKUP($B78,[1]F27!$C:$C,[1]F27!$Y:$Y) -> #ERROR! | AE78: =_xlfn.XLOOKUP($B78,[1]F27!$C:$C,[1]F27!$Z:$Z) -> #ERROR! | AF78: =_xlfn.XLOOKUP($B78,[2]PRICING!$B:$B,[2]PRICING!$B:$B,"MISSING") -> #ERROR! | AG78: =COUNTIFS([2]ACTIVE_SCO!$B:$B,$B78,[2]ACTIVE_SCO!$P:$P,"Y") -> #ERROR! | AI78: REVIEW
A79: FALSE | B79: 608655 | C79: Klyva GTX Pant Women | D79: Apparel | G79: OUT | I79: Shell | J79: ABS | K79: Women | M79: TRUE | N79: FALSE | O79: 2800 | P79: 2.1 | Q79: 1333.33 | R79: 0.60218401 | S79: Better | U79: Gore-Tex | V79: None | X79: XXL | Y79: =IF(M79=TRUE,"CO",IF(N79=TRUE,"UPDATE","NEW")) -> CO | Z79: =_xlfn.XLOOKUP($B79,[1]F27!$C:$C,[1]F27!$BV:$BV) -> #ERROR! | AD79: =_xlfn.XLOOKUP($B79,[1]F27!$C:$C,[1]F27!$Y:$Y) -> #ERROR! | AE79: =_xlfn.XLOOKUP($B79,[1]F27!$C:$C,[1]F27!$Z:$Z) -> #ERROR! | AF79: =_xlfn.XLOOKUP($B79,[2]PRICING!$B:$B,[2]PRICING!$B:$B,"MISSING") -> #ERROR! | AG79: =COUNTIFS([2]ACTIVE_SCO!$B:$B,$B79,[2]ACTIVE_SCO!$P:$P,"Y") -> #ERROR! | AI79: REVIEW
A80: TRUE | B80: 607476 | C80: Latnja Wool Crew Neck Men | D80: Apparel | G80: SNW | I80: Baselayer | J80: Inline | K80: Men | M80: TRUE | N80: FALSE | O80: 1300 | P80: 2.1 | Q80: 619.05 | R80: 0.52709797 | S80: Better | U80: None | V80: None | Y80: =IF(M80=TRUE,"CO",IF(N80=TRUE,"UPDATE","NEW")) -> CO | Z80: =_xlfn.XLOOKUP($B80,[1]F27!$C:$C,[1]F27!$BV:$BV) -> #ERROR! | AD80: =_xlfn.XLOOKUP($B80,[1]F27!$C:$C,[1]F27!$Y:$Y) -> #ERROR! | AE80: =_xlfn.XLOOKUP($B80,[1]F27!$C:$C,[1]F27!$Z:$Z) -> #ERROR! | AF80: =_xlfn.XLOOKUP($B80,[2]PRICING!$B:$B,[2]PRICING!$B:$B,"MISSING") -> #ERROR! | AG80: =COUNTIFS([2]ACTIVE_SCO!$B:$B,$B80,[2]ACTIVE_SCO!$P:$P,"Y") -> #ERROR! | AI80: FW27 | AJ80: Replaced with new basic baselayers FW28 | AK80: FW27 | AM80: Essentials | AN80: Active Essentials | AO80: Essentials | AQ80: Essentials | AS80: Baselayer | AT80: Pullover | AU80: Merino Wool | AV80: N | BA80: FW27
A81: TRUE | B81: 608552 | C81: Korp Softshell Hood Men | D81: Apparel | G81: OUT | I81: Softshell | J81: Inline | K81: Men | M81: TRUE | N81: FALSE | O81: 1800 | P81: 2.1 | Q81: 857.14 | R81: 0.72563409 | S81: Good | U81: None | V81: None | Y81: =IF(M81=TRUE,"CO",IF(N81=TRUE,"UPDATE","NEW")) -> CO | Z81: =_xlfn.XLOOKUP($B81,[1]F27!$C:$C,[1]F27!$BV:$BV) -> #ERROR! | AD81: =_xlfn.XLOOKUP($B81,[1]F27!$C:$C,[1]F27!$Y:$Y) -> #ERROR! | AE81: =_xlfn.XLOOKUP($B81,[1]F27!$C:$C,[1]F27!$Z:$Z) -> #ERROR! | AF81: =_xlfn.XLOOKUP($B81,[2]PRICING!$B:$B,[2]PRICING!$B:$B,"MISSING") -> #ERROR! | AG81: =COUNTIFS([2]ACTIVE_SCO!$B:$B,$B81,[2]ACTIVE_SCO!$P:$P,"Y") -> #ERROR! | AI81: FW28+ | AJ81: CORE: PLC: LS?? US-?? LSO-?? | AK81: SS27 | AM81: Outdoor | AN81: Day Hiking | AO81: Outdoor | AP81: Hiking | AS81: Softshell | AT81: Hooded Jacket | AU81: Classic Softshell | AV81: N | BA81: SS27
A82: TRUE | B82: 608553 | C82: Korp Softshell Hood Women | D82: Apparel | G82: OUT | I82: Softshell | J82: Inline | K82: Women | M82: TRUE | N82: FALSE | O82: 1800 | P82: 2.1 | Q82: 857.14 | R82: 0.74220081 | S82: Good | U82: None | V82: None | Y82: =IF(M82=TRUE,"CO",IF(N82=TRUE,"UPDATE","NEW")) -> CO | Z82: =_xlfn.XLOOKUP($B82,[1]F27!$C:$C,[1]F27!$BV:$BV) -> #ERROR! | AD82: =_xlfn.XLOOKUP($B82,[1]F27!$C:$C,[1]F27!$Y:$Y) -> #ERROR! | AE82: =_xlfn.XLOOKUP($B82,[1]F27!$C:$C,[1]F27!$Z:$Z) -> #ERROR! | AF82: =_xlfn.XLOOKUP($B82,[2]PRICING!$B:$B,[2]PRICING!$B:$B,"MISSING") -> #ERROR! | AG82: =COUNTIFS([2]ACTIVE_SCO!$B:$B,$B82,[2]ACTIVE_SCO!$P:$P,"Y") -> #ERROR! | AI82: FW28+ | AJ82: CORE: PLC: LS?? US-?? LSO-?? | AK82: SS27 | AM82: Outdoor | AN82: Day Hiking | AO82: Outdoor | AP82: Hiking | AS82: Softshell | AT82: Hooded Jacket | AU82: Classic Softshell | AV82: N | BA82: SS27
A83: TRUE | B83: 608549 | C83: Norrvind Shield Hood Men | D83: Apparel | G83: OUT | I83: Shell | J83: Inline | K83: Men | M83: TRUE | N83: FALSE | O83: 1300 | P83: 2.1 | Q83: 619.05 | R83: 0.6465229 | S83: Better | U83: None | V83: None | Y83: =IF(M83=TRUE,"CO",IF(N83=TRUE,"UPDATE","NEW")) -> CO | Z83: =_xlfn.XLOOKUP($B83,[1]F27!$C:$C,[1]F27!$BV:$BV) -> #ERROR! | AD83: =_xlfn.XLOOKUP($B83,[1]F27!$C:$C,[1]F27!$Y:$Y) -> #ERROR! | AE83: =_xlfn.XLOOKUP($B83,[1]F27!$C:$C,[1]F27!$Z:$Z) -> #ERROR! | AF83: =_xlfn.XLOOKUP($B83,[2]PRICING!$B:$B,[2]PRICING!$B:$B,"MISSING") -> #ERROR! | AG83: =COUNTIFS([2]ACTIVE_SCO!$B:$B,$B83,[2]ACTIVE_SCO!$P:$P,"Y") -> #ERROR! | AI83: FW28+ | AJ83: PLC: LS?? US-?? LSO-?? | AK83: SS27 | AM83: Outdoor | AN83: Day Hiking | AO83: Outdoor | AP83: Hiking | AS83: Softshell | AT83: Hooded Jacket | AU83: Windbreaker | AV83: N | BA83: SS27
A84: TRUE | B84: 608550 | C84: Norrvind Shield Hood Women | D84: Apparel | G84: OUT | I84: Shell | J84: Inline | K84: Women | M84: TRUE | N84: FALSE | O84: 1300 | P84: 2.1 | Q84: 619.05 | R84: 0.66290283 | S84: Better | U84: None | V84: None | Y84: =IF(M84=TRUE,"CO",IF(N84=TRUE,"UPDATE","NEW")) -> CO | Z84: =_xlfn.XLOOKUP($B84,[1]F27!$C:$C,[1]F27!$BV:$BV) -> #ERROR! | AD84: =_xlfn.XLOOKUP($B84,[1]F27!$C:$C,[1]F27!$Y:$Y) -> #ERROR! | AE84: =_xlfn.XLOOKUP($B84,[1]F27!$C:$C,[1]F27!$Z:$Z) -> #ERROR! | AF84: =_xlfn.XLOOKUP($B84,[2]PRICING!$B:$B,[2]PRICING!$B:$B,"MISSING") -> #ERROR! | AG84: =COUNTIFS([2]ACTIVE_SCO!$B:$B,$B84,[2]ACTIVE_SCO!$P:$P,"Y") -> #ERROR! | AI84: FW28+ | AJ84: PLC: LS?? US-?? LSO-?? | AK84: SS27 | AM84: Outdoor | AN84: Day Hiking | AO84: Outdoor | AP84: Hiking | AS84: Softshell | AT84: Hooded Jacket | AU84: Windbreaker | AV84: N | BA84: SS27
A85: TRUE | B85: 607593 | C85: Astral GTX II Jacket Men | D85: Apparel | G85: OUT | I85: Shell | J85: Inline | K85: Men | M85: TRUE | N85: FALSE | O85: 4500 | P85: 2.1 | Q85: 2142.86 | R85: 0.52764996 | S85: Better | U85: Gore-Tex | V85: None | Y85: =IF(M85=TRUE,"CO",IF(N85=TRUE,"UPDATE","NEW")) -> CO | Z85: =_xlfn.XLOOKUP($B85,[1]F27!$C:$C,[1]F27!$BV:$BV) -> #ERROR! | AD85: =_xlfn.XLOOKUP($B85,[1]F27!$C:$C,[1]F27!$Y:$Y) -> #ERROR! | AE85: =_xlfn.XLOOKUP($B85,[1]F27!$C:$C,[1]F27!$Z:$Z) -> #ERROR! | AF85: =_xlfn.XLOOKUP($B85,[2]PRICING!$B:$B,[2]PRICING!$B:$B,"MISSING") -> #ERROR! | AG85: =COUNTIFS([2]ACTIVE_SCO!$B:$B,$B85,[2]ACTIVE_SCO!$P:$P,"Y") -> #ERROR! | AI85: FW28+ | AJ85: CORE: PLC: LS-FW25 US-SS29 LSO-?? | AK85: SS25 | AM85: Essentials | AN85: Active Essentials | AO85: Essentials | AQ85: Essentials | AS85: Shell | AT85: Jacket | AU85: 2L | AV85: Y | BA85: SS25
A86: TRUE | B86: 607563 | C86: Astral GTX II Jacket Women | D86: Apparel | G86: OUT | I86: Shell | J86: Inline | K86: Women | M86: TRUE | N86: FALSE | O86: 4500 | P86: 2.1 | Q86: 2142.86 | R86: 0.57925389 | S86: Better | U86: Gore-Tex | V86: None | Y86: =IF(M86=TRUE,"CO",IF(N86=TRUE,"UPDATE","NEW")) -> CO | Z86: =_xlfn.XLOOKUP($B86,[1]F27!$C:$C,[1]F27!$BV:$BV) -> #ERROR! | AD86: =_xlfn.XLOOKUP($B86,[1]F27!$C:$C,[1]F27!$Y:$Y) -> #ERROR! | AE86: =_xlfn.XLOOKUP($B86,[1]F27!$C:$C,[1]F27!$Z:$Z) -> #ERROR! | AF86: =_xlfn.XLOOKUP($B86,[2]PRICING!$B:$B,[2]PRICING!$B:$B,"MISSING") -> #ERROR! | AG86: =COUNTIFS([2]ACTIVE_SCO!$B:$B,$B86,[2]ACTIVE_SCO!$P:$P,"Y") -> #ERROR! | AI86: FW28+ | AJ86: CORE: PLC: LS-FW25 US-SS29 LSO-?? | AK86: SS25 | AM86: Essentials | AN86: Active Essentials | AO86: Essentials | AQ86: Essentials | AS86: Shell | AT86: Jacket | AU86: 2L | AV86: Y | BA86: SS25
A87: TRUE | B87: 607477 | C87: Latnja Wool Crew Neck Women | D87: Apparel | G87: SNW | I87: Baselayer | J87: Inline | K87: Women | M87: TRUE | N87: FALSE | O87: 1300 | P87: 2.1 | Q87: 619.05 | R87: 0.56124707 | S87: Better | U87: None | V87: None | Y87: =IF(M87=TRUE,"CO",IF(N87=TRUE,"UPDATE","NEW")) -> CO | Z87: =_xlfn.XLOOKUP($B87,[1]F27!$C:$C,[1]F27!$BV:$BV) -> #ERROR! | AD87: =_xlfn.XLOOKUP($B87,[1]F27!$C:$C,[1]F27!$Y:$Y) -> #ERROR! | AE87: =_xlfn.XLOOKUP($B87,[1]F27!$C:$C,[1]F27!$Z:$Z) -> #ERROR! | AF87: =_xlfn.XLOOKUP($B87,[2]PRICING!$B:$B,[2]PRICING!$B:$B,"MISSING") -> #ERROR! | AG87: =COUNTIFS([2]ACTIVE_SCO!$B:$B,$B87,[2]ACTIVE_SCO!$P:$P,"Y") -> #ERROR! | AI87: FW27 | AJ87: Replaced with new basic baselayers FW28 | AK87: Pre S23 | AL87: FW27 | AM87: Essentials | AN87: Active Essentials | AO87: Essentials | AQ87: Essentials | AS87: Baselayer | AT87: Pullover | AU87: Merino Wool | AV87: N | BA87: Pre S23 | BB87: FW27
A88: TRUE | B88: 607475 | C88: Latnja Wool Long John's Men | D88: Apparel | G88: SNW | I88: Baselayer | J88: Inline | K88: Men | M88: TRUE | N88: FALSE | O88: 1000 | P88: 2.1 | Q88: 476.19 | R88: 0.55458955 | S88: Better | U88: None | V88: None | Y88: =IF(M88=TRUE,"CO",IF(N88=TRUE,"UPDATE","NEW")) -> CO | Z88: =_xlfn.XLOOKUP($B88,[1]F27!$C:$C,[1]F27!$BV:$BV) -> #ERROR! | AD88: =_xlfn.XLOOKUP($B88,[1]F27!$C:$C,[1]F27!$Y:$Y) -> #ERROR! | AE88: =_xlfn.XLOOKUP($B88,[1]F27!$C:$C,[1]F27!$Z:$Z) -> #ERROR! | AF88: =_xlfn.XLOOKUP($B88,[2]PRICING!$B:$B,[2]PRICING!$B:$B,"MISSING") -> #ERROR! | AG88: =COUNTIFS([2]ACTIVE_SCO!$B:$B,$B88,[2]ACTIVE_SCO!$P:$P,"Y") -> #ERROR! | AI88: FW27 | AJ88: Replaced with new basic baselayers FW28 | AK88: SS25 | AL88: SS26 | AM88: Essentials | AN88: Active Essentials | AO88: Essentials | AQ88: Essentials | AS88: Baselayer | AT88: Pant | AU88: Merino Wool | AV88: N | BA88: SS25 | BB88: SS26
A89: TRUE | B89: 607824 | C89: Breeze Mimic Hood Men | D89: Apparel | G89: OUT | I89: Insulation | J89: Inline | K89: Men | M89: TRUE | N89: FALSE | O89: 2600 | P89: 2.1 | Q89: 1238.1 | R89: 0.6900735 | S89: Good | U89: Mimic | V89: None | X89: Intersport | Y89: =IF(M89=TRUE,"CO",IF(N89=TRUE,"UPDATE","NEW")) -> CO | Z89: =_xlfn.XLOOKUP($B89,[1]F27!$C:$C,[1]F27!$BV:$BV) -> #ERROR! | AD89: =_xlfn.XLOOKUP($B89,[1]F27!$C:$C,[1]F27!$Y:$Y) -> #ERROR! | AE89: =_xlfn.XLOOKUP($B89,[1]F27!$C:$C,[1]F27!$Z:$Z) -> #ERROR! | AF89: =_xlfn.XLOOKUP($B89,[2]PRICING!$B:$B,[2]PRICING!$B:$B,"MISSING") -> #ERROR! | AG89: =COUNTIFS([2]ACTIVE_SCO!$B:$B,$B89,[2]ACTIVE_SCO!$P:$P,"Y") -> #ERROR! | AI89: FW28+ | AJ89: PLC: LS?? US-?? LSO-?? | AK89: FW25 | AM89: Essentials | AN89: Active Essentials | AO89: Essentials | AS89: Insulation | AT89: Hooded Jacket | AU89: Midweight Synthetic | AV89: N | BA89: FW25
A90: TRUE | B90: 607825 | C90: Breeze Mimic Hood Women | D90: Apparel | G90: OUT | I90: Insulation | J90: Inline | K90: Women | M90: TRUE | N90: FALSE | O90: 2600 | P90: 2.1 | Q90: 1238.1 | R90: 0.71372264 | S90: Good | U90: Mimic | V90: None | X90: Intersport | Y90: =IF(M90=TRUE,"CO",IF(N90=TRUE,"UPDATE","NEW")) -> CO | Z90: =_xlfn.XLOOKUP($B90,[1]F27!$C:$C,[1]F27!$BV:$BV) -> #ERROR! | AD90: =_xlfn.XLOOKUP($B90,[1]F27!$C:$C,[1]F27!$Y:$Y) -> #ERROR! | AE90: =_xlfn.XLOOKUP($B90,[1]F27!$C:$C,[1]F27!$Z:$Z) -> #ERROR! | AF90: =_xlfn.XLOOKUP($B90,[2]PRICING!$B:$B,[2]PRICING!$B:$B,"MISSING") -> #ERROR! | AG90: =COUNTIFS([2]ACTIVE_SCO!$B:$B,$B90,[2]ACTIVE_SCO!$P:$P,"Y") -> #ERROR! | AI90: FW28+ | AJ90: PLC: LS?? US-?? LSO-?? | AK90: FW25 | AM90: Essentials | AN90: Active Essentials | AO90: Essentials | AS90: Insulation | AT90: Hooded Jacket | AU90: Midweight Synthetic | AV90: N | BA90: FW25
A91: TRUE | B91: 607680 | C91: Breeze Proof Jacket Men | D91: Apparel | G91: OUT | I91: Shell | J91: Inline | K91: Men | M91: TRUE | N91: FALSE | O91: 2000 | P91: 2.1 | Q91: 952.38 | R91: 0.65517966 | S91: Good | U91: Proof | V91: None | Y91: =IF(M91=TRUE,"CO",IF(N91=TRUE,"UPDATE","NEW")) -> CO | Z91: =_xlfn.XLOOKUP($B91,[1]F27!$C:$C,[1]F27!$BV:$BV) -> #ERROR! | AD91: =_xlfn.XLOOKUP($B91,[1]F27!$C:$C,[1]F27!$Y:$Y) -> #ERROR! | AE91: =_xlfn.XLOOKUP($B91,[1]F27!$C:$C,[1]F27!$Z:$Z) -> #ERROR! | AF91: =_xlfn.XLOOKUP($B91,[2]PRICING!$B:$B,[2]PRICING!$B:$B,"MISSING") -> #ERROR! | AG91: =COUNTIFS([2]ACTIVE_SCO!$B:$B,$B91,[2]ACTIVE_SCO!$P:$P,"Y") -> #ERROR! | AI91: FW28+ | AJ91: PLC: LS?? US-?? LSO-?? | AK91: SS25 | AM91: Essentials | AN91: Daily Essentials | AO91: Essentials | AS91: Shell | AT91: Jacket | AU91: 2L | AV91: Y | BA91: SS25
A92: TRUE | B92: 607681 | C92: Breeze Proof Jacket Women | D92: Apparel | G92: OUT | I92: Shell | J92: Inline | K92: Women | M92: TRUE | N92: FALSE | O92: 2000 | P92: 2.1 | Q92: 952.38 | R92: 0.67552868 | S92: Good | U92: Proof | V92: None | Y92: =IF(M92=TRUE,"CO",IF(N92=TRUE,"UPDATE","NEW")) -> CO | Z92: =_xlfn.XLOOKUP($B92,[1]F27!$C:$C,[1]F27!$BV:$BV) -> #ERROR! | AD92: =_xlfn.XLOOKUP($B92,[1]F27!$C:$C,[1]F27!$Y:$Y) -> #ERROR! | AE92: =_xlfn.XLOOKUP($B92,[1]F27!$C:$C,[1]F27!$Z:$Z) -> #ERROR! | AF92: =_xlfn.XLOOKUP($B92,[2]PRICING!$B:$B,[2]PRICING!$B:$B,"MISSING") -> #ERROR! | AG92: =COUNTIFS([2]ACTIVE_SCO!$B:$B,$B92,[2]ACTIVE_SCO!$P:$P,"Y") -> #ERROR! | AI92: FW28+ | AJ92: PLC: LS?? US-?? LSO-?? | AK92: SS25 | AM92: Essentials | AN92: Daily Essentials | AO92: Essentials | AS92: Shell | AT92: Jacket | AU92: 2L | AV92: Y | BA92: SS25
A93: TRUE | B93: 608683 | C93: Brisen Tech Mid Hood Men | D93: Apparel | G93: ROC | I93: Midlayer | J93: Inline | K93: Men | M93: FALSE | N93: FALSE | O93: 2200 | P93: 2.1 | Q93: 1047.62 | R93: 0.59305855 | S93: Best | U93: None | V93: None | Y93: =IF(M93=TRUE,"CO",IF(N93=TRUE,"UPDATE","NEW")) -> NEW | Z93: =_xlfn.XLOOKUP($B93,[1]F27!$C:$C,[1]F27!$BV:$BV) -> #ERROR! | AD93: =_xlfn.XLOOKUP($B93,[1]F27!$C:$C,[1]F27!$Y:$Y) -> #ERROR! | AE93: =_xlfn.XLOOKUP($B93,[1]F27!$C:$C,[1]F27!$Z:$Z) -> #ERROR! | AF93: =_xlfn.XLOOKUP($B93,[2]PRICING!$B:$B,[2]PRICING!$B:$B,"MISSING") -> #ERROR! | AG93: =COUNTIFS([2]ACTIVE_SCO!$B:$B,$B93,[2]ACTIVE_SCO!$P:$P,"Y") -> #ERROR! | AI93: FW28+ | AJ93: PLC: LS-FW?? US-FW?? | AK93: FW27 | AM93: Essentials | AN93: Active Essentials | AO93: Essentials | AS93: Fleece/Midlayer | AT93: Hooded Jacket | AU93: Lightweight | AV93: N | BA93: FW27
A94: TRUE | B94: 608684 | C94: Brisen Tech Mid Hood Women | D94: Apparel | G94: ROC | I94: Midlayer | J94: Inline | K94: Women | M94: FALSE | N94: FALSE | O94: 2200 | P94: 2.1 | Q94: 1047.62 | R94: 0.63432351 | S94: Best | U94: None | V94: None | Y94: =IF(M94=TRUE,"CO",IF(N94=TRUE,"UPDATE","NEW")) -> NEW | Z94: =_xlfn.XLOOKUP($B94,[1]F27!$C:$C,[1]F27!$BV:$BV) -> #ERROR! | AD94: =_xlfn.XLOOKUP($B94,[1]F27!$C:$C,[1]F27!$Y:$Y) -> #ERROR! | AE94: =_xlfn.XLOOKUP($B94,[1]F27!$C:$C,[1]F27!$Z:$Z) -> #ERROR! | AF94: =_xlfn.XLOOKUP($B94,[2]PRICING!$B:$B,[2]PRICING!$B:$B,"MISSING") -> #ERROR! | AG94: =COUNTIFS([2]ACTIVE_SCO!$B:$B,$B94,[2]ACTIVE_SCO!$P:$P,"Y") -> #ERROR! | AI94: FW28+ | AJ94: PLC: LS-FW?? US-FW?? | AK94: FW27 | AM94: Essentials | AN94: Active Essentials | AO94: Essentials | AS94: Fleece/Midlayer | AT94: Hooded Jacket | AU94: Lightweight | AV94: N | BA94: FW27
A95: FALSE | B95: 608273 | C95: Kyligt Softshell Pant Men | D95: Apparel | G95: OUT | I95: Softshell | J95: ABS | K95: Men | M95: TRUE | N95: FALSE | O95: 2500 | P95: 2.1 | Q95: 1190.48 | R95: 0.66530307 | S95: Better | U95: None | V95: None | X95: XXL | Y95: =IF(M95=TRUE,"CO",IF(N95=TRUE,"UPDATE","NEW")) -> CO | Z95: =_xlfn.XLOOKUP($B95,[1]F27!$C:$C,[1]F27!$BV:$BV) -> #ERROR! | AD95: =_xlfn.XLOOKUP($B95,[1]F27!$C:$C,[1]F27!$Y:$Y) -> #ERROR! | AE95: =_xlfn.XLOOKUP($B95,[1]F27!$C:$C,[1]F27!$Z:$Z) -> #ERROR! | AF95: =_xlfn.XLOOKUP($B95,[2]PRICING!$B:$B,[2]PRICING!$B:$B,"MISSING") -> #ERROR! | AG95: =COUNTIFS([2]ACTIVE_SCO!$B:$B,$B95,[2]ACTIVE_SCO!$P:$P,"Y") -> #ERROR! | AI95: REVIEW
A96: FALSE | B96: 608274 | C96: Kyligt Softshell Pant Women | D96: Apparel | G96: OUT | I96: Softshell | J96: ABS | K96: Women | M96: TRUE | N96: FALSE | O96: 2500 | P96: 2.1 | Q96: 1190.48 | R96: 0.67644144 | S96: Better | U96: None | V96: None | X96: XXL | Y96: =IF(M96=TRUE,"CO",IF(N96=TRUE,"UPDATE","NEW")) -> CO | Z96: =_xlfn.XLOOKUP($B96,[1]F27!$C:$C,[1]F27!$BV:$BV) -> #ERROR! | AD96: =_xlfn.XLOOKUP($B96,[1]F27!$C:$C,[1]F27!$Y:$Y) -> #ERROR! | AE96: =_xlfn.XLOOKUP($B96,[1]F27!$C:$C,[1]F27!$Z:$Z) -> #ERROR! | AF96: =_xlfn.XLOOKUP($B96,[2]PRICING!$B:$B,[2]PRICING!$B:$B,"MISSING") -> #ERROR! | AG96: =COUNTIFS([2]ACTIVE_SCO!$B:$B,$B96,[2]ACTIVE_SCO!$P:$P,"Y") -> #ERROR! | AI96: REVIEW
A97: TRUE | B97: 608351 | C97: Buteo Mid II Jacket Men | D97: Apparel | G97: OUT | I97: Midlayer | J97: Inline | K97: Men | M97: TRUE | N97: FALSE | O97: 900 | P97: 2.1 | Q97: 428.57 | R97: 0.66609889 | S97: Good | U97: Polartec | V97: None | Y97: =IF(M97=TRUE,"CO",IF(N97=TRUE,"UPDATE","NEW")) -> CO | Z97: =_xlfn.XLOOKUP($B97,[1]F27!$C:$C,[1]F27!$BV:$BV) -> #ERROR! | AD97: =_xlfn.XLOOKUP($B97,[1]F27!$C:$C,[1]F27!$Y:$Y) -> #ERROR! | AE97: =_xlfn.XLOOKUP($B97,[1]F27!$C:$C,[1]F27!$Z:$Z) -> #ERROR! | AF97: =_xlfn.XLOOKUP($B97,[2]PRICING!$B:$B,[2]PRICING!$B:$B,"MISSING") -> #ERROR! | AG97: =COUNTIFS([2]ACTIVE_SCO!$B:$B,$B97,[2]ACTIVE_SCO!$P:$P,"Y") -> #ERROR! | AI97: FW28+ | AJ97: CORE: PLC: LS-FW26 US-FW29 LSO-?? | AK97: FW26 | AM97: Essentials | AN97: Active Essentials | AO97: Essentials | AQ97: Essentials | AS97: Fleece/Midlayer | AT97: Jacket | AU97: Midweight | AV97: N | BA97: FW26
A98: TRUE | B98: 608352 | C98: Buteo Mid II Jacket Women | D98: Apparel | G98: OUT | I98: Midlayer | J98: Inline | K98: Women | M98: TRUE | N98: FALSE | O98: 900 | P98: 2.1 | Q98: 428.57 | R98: 0.68408895 | S98: Good | U98: Polartec | V98: None | Y98: =IF(M98=TRUE,"CO",IF(N98=TRUE,"UPDATE","NEW")) -> CO | Z98: =_xlfn.XLOOKUP($B98,[1]F27!$C:$C,[1]F27!$BV:$BV) -> #ERROR! | AD98: =_xlfn.XLOOKUP($B98,[1]F27!$C:$C,[1]F27!$Y:$Y) -> #ERROR! | AE98: =_xlfn.XLOOKUP($B98,[1]F27!$C:$C,[1]F27!$Z:$Z) -> #ERROR! | AF98: =_xlfn.XLOOKUP($B98,[2]PRICING!$B:$B,[2]PRICING!$B:$B,"MISSING") -> #ERROR! | AG98: =COUNTIFS([2]ACTIVE_SCO!$B:$B,$B98,[2]ACTIVE_SCO!$P:$P,"Y") -> #ERROR! | AI98: FW28+ | AJ98: CORE: PLC: LS-FW26 US-FW29 LSO-?? | AK98: FW26 | AM98: Essentials | AN98: Active Essentials | AO98: Essentials | AQ98: Essentials | AS98: Fleece/Midlayer | AT98: Jacket | AU98: Midweight | AV98: N | BA98: FW26
A99: TRUE | B99: 608481 | C99: Fram Mimic Jacket Men | D99: Apparel | G99: DAY | I99: Insulation | J99: Inline | K99: Men | M99: TRUE | N99: FALSE | O99: 2500 | P99: 2.1 | Q99: 1190.48 | R99: 0.59847288 | S99: Better | U99: Pertex | V99: Mimic | Y99: =IF(M99=TRUE,"CO",IF(N99=TRUE,"UPDATE","NEW")) -> CO | Z99: =_xlfn.XLOOKUP($B99,[1]F27!$C:$C,[1]F27!$BV:$BV) -> #ERROR! | AD99: =_xlfn.XLOOKUP($B99,[1]F27!$C:$C,[1]F27!$Y:$Y) -> #ERROR! | AE99: =_xlfn.XLOOKUP($B99,[1]F27!$C:$C,[1]F27!$Z:$Z) -> #ERROR! | AF99: =_xlfn.XLOOKUP($B99,[2]PRICING!$B:$B,[2]PRICING!$B:$B,"MISSING") -> #ERROR! | AG99: =COUNTIFS([2]ACTIVE_SCO!$B:$B,$B99,[2]ACTIVE_SCO!$P:$P,"Y") -> #ERROR! | AI99: FW28+ | AJ99: PLC: LS?? US-?? LSO-?? | AK99: FW26 | AM99: Essentials | AN99: Daily Essentials | AO99: Everyday | AP99: Lifestyle | AS99: Insulation | AT99: Jacket | AU99: Midweight Synthetic | AV99: N | BA99: FW26
A100: TRUE | B100: 608482 | C100: Fram Mimic Jacket Women | D100: Apparel | G100: DAY | I100: Insulation | J100: Inline | K100: Women | M100: TRUE | N100: FALSE | O100: 2500 | P100: 2.1 | Q100: 1190.48 | R100: 0.62195921 | S100: Better | U100: Pertex | V100: Mimic | Y100: =IF(M100=TRUE,"CO",IF(N100=TRUE,"UPDATE","NEW")) -> CO | Z100: =_xlfn.XLOOKUP($B100,[1]F27!$C:$C,[1]F27!$BV:$BV) -> #ERROR! | AD100: =_xlfn.XLOOKUP($B100,[1]F27!$C:$C,[1]F27!$Y:$Y) -> #ERROR! | AE100: =_xlfn.XLOOKUP($B100,[1]F27!$C:$C,[1]F27!$Z:$Z) -> #ERROR! | AF100: =_xlfn.XLOOKUP($B100,[2]PRICING!$B:$B,[2]PRICING!$B:$B,"MISSING") -> #ERROR! | AG100: =COUNTIFS([2]ACTIVE_SCO!$B:$B,$B100,[2]ACTIVE_SCO!$P:$P,"Y") -> #ERROR! | AI100: FW28+ | AJ100: PLC: LS?? US-?? LSO-?? | AK100: FW26 | AM100: Essentials | AN100: Daily Essentials | AO100: Everyday | AP100: Lifestyle | AS100: Insulation | AT100: Jacket | AU100: Midweight Synthetic | AV100: N | BA100: FW26
...

Sheet SS28
A2: Season | B2: Style Seasonality | C2: Active | D2: Code | E2: Style | F2: xx | G2: Business Area | H2: CO Seson | I2: Status | J2: Tobias Comment | K2: Merch Comment | L2: Other | M2: Product Concept | N2: Category/Layer | O2: Collection Type | P2: Gender | Q2: Product Type | R2: Type | S2: xxx | T2: xxxx | U2: RRP Comment | V2: Target RRP | W2: Mark-up | X2: WP | Y2: DISCOUNT | Z2: NET PRICE | AA2: GM0% | AB2: Product Hierarchy | AC2: Target GM0% | AD2: Actual LC SEK | AE2: Main technology platform | AF2: Secondary technology platform | AG2: Target No. of SCO | AH2: Actual No. Of SCO | AI2: Style Comment | AJ2: ABS Customer | AK2: FORECAST 0 | AL2: S27 | AM2: S26 | AN2: F27 | AO2: F26 | AP2: FORECAST 0 | AQ2: S27 | AR2: F26 | AS2: S28 | AT2: F26 | AU2: FORECAST 0 | AV2: S27 | AW2: S26 | AX2: F27 | AY2: F26 | AZ2: Info & Comments | BA2: Collection | BB2: NEW MAPPING: Activity | BC2: PPT Collection / Activity (deck) | BD2: Category/Layer(V2) | BE2: Silhouette | BF2: Category/Layer Subtype | BG2: Waterproof | BH2: Attribution Review | BI2: Franchise/Family | BJ2: Note
A3: SS28 | C3: FALSE | D3: 608822 | E3: Airak GTX Prototype Jacket Men | G3: Apparel | H3: F27 | I3: CANCELED | J3: Seasonal Brand Builder | M3: L.I.M | N3: Shell | O3: ABS Exclusive | P3: Men | Q3: Jacket | R3: Top | V3: 0 | W3: 2.1 | X3: 0 | Y3: 0 | Z3: 0 | AA3: 0 | AE3: Gore-Tex | AH3: 1 | AJ3: KA YO Collab | AL3: 0 | AM3: 0 | AN3: 0 | AO3: 0 | AP3: 0 | AQ3: 0 | AR3: 0 | AS3: 0 | AT3: 0 | AU3: 0 | AV3: 0 | AW3: 0 | AX3: 0 | AY3: 0 | AZ3: NOT Active in Centric | BA3: Essentials | BB3: Active Essentials | BD3: Shell | BE3: Jacket | BF3: 3L | BG3: Y
A4: SS28 | B4: All year | C4: TRUE | D4: 608172 | E4: Alert GTX Jacket Men | G4: Apparel | H4: F27 | I4: CO | M4: OUT | N4: Shell | O4: Inline | P4: Men | Q4: Jacket | R4: Top | V4: 3800 | W4: 2.1 | X4: 1810 | Y4: 0.2 | Z4: 1448 | AA4: 1 | AB4: Good | AC4: 0.58 | AE4: Gore-Tex | AF4: None | AG4: 4 | AH4: 4 | AI4: potentially add 1 new. Charlotte: 4SCO. 1 NEW. | AK4: 1700 | AL4: 1653 | AM4: 1630 | AN4: 1330 | AO4: 861 | AP4: 3077000 | AQ4: 2991136.6 | AR4: 1558410 | AS4: 0 | AT4: 1558410 | AU4: 2461600 | AV4: 2537969 | AW4: 2396467.4 | AX4: 1980693.6 | AY4: 1353722.4 | BA4: Outdoor | BB4: Day Hiking | BC4: Outdoor / Hiking [MATCH] | BD4: Shell | BE4: Jacket | BF4: 2L | BG4: Y
A5: SS28 | B5: All year | C5: TRUE | D5: 608596 | E5: Alert GTX Jacket Men AF | G5: Apparel | H5: F27 | I5: CO | J5: Asia Fit | M5: OUT | N5: Shell | O5: ABS Exclusive | P5: Men | Q5: Jacket | R5: Top | V5: 3800 | W5: 2.1 | X5: 1810 | Y5: 0.2 | Z5: 1448 | AA5: 1 | AB5: Good | AE5: Gore-Tex | AF5: None | AH5: 0 | AI5: follow inline. Charlotte: 4SCO. 1 New. | AJ5: ASIA | AK5: 1000 | AL5: 1000 | AM5: 1000 | AN5: 300 | AO5: 0 | AP5: 1810000 | AQ5: 1809520 | AR5: 0 | AS5: 0 | AT5: 0 | AU5: 1448000 | AV5: 633410 | AW5: 669600 | AX5: 190023 | AY5: 0 | AZ5: NOT Active in Centric | BA5: Outdoor | BB5: Day Hiking | BC5: Outdoor / Hiking [MATCH] | BD5: Shell | BE5: Jacket | BF5: 2L | BG5: Y
A6: SS28 | B6: All year | C6: TRUE | D6: 608192 | E6: Alert GTX Jacket Women | G6: Apparel | H6: F27 | I6: CO | M6: OUT | N6: Shell | O6: Inline | P6: Women | Q6: Jacket | R6: Top | V6: 3800 | W6: 2.1 | X6: 1810 | Y6: 0.2 | Z6: 1448 | AA6: 1 | AB6: Good | AC6: 0.6 | AE6: Gore-Tex | AF6: None | AG6: 4 | AH6: 4 | AI6: potentially add 1 new if LT Haze Blue does not work in a FW. Charlotte: 4SCO. 1 New. | AK6: 2000 | AL6: 1989 | AM6: 1878 | AN6: 1239 | AO6: 521 | AP6: 3620000 | AQ6: 3599135.3 | AR6: 943010 | AS6: 0 | AT6: 943010 | AU6: 2896000 | AV6: 2645230.1 | AW6: 2194639.4 | AX6: 1663577.9 | AY6: 831871.75 | BA6: Outdoor | BB6: Day Hiking | BC6: Outdoor / Hiking [MATCH] | BD6: Shell | BE6: Jacket | BF6: 2L | BG6: Y
A7: SS28 | B7: All year | C7: TRUE | D7: 607645 | E7: Alert Mid Pant Men | G7: Apparel | H7: F27 | I7: CO | M7: OUT | N7: Legwear | O7: Inline | P7: Men | Q7: Pants | R7: Bottom | V7: 1700 | W7: 2.1 | X7: 810 | Y7: 0.2 | Z7: 648 | AA7: 1 | AB7: Better | AC7: 0.62 | AE7: None | AF7: None | AG7: 4 | AH7: 4 | AI7: 4SCO. No new. Update FW28? | AK7: 6000 | AL7: 7095 | AM7: 4652 | AN7: 5683 | AO7: 4400 | AP7: 4860000 | AQ7: 5743544.4 | AR7: 3564000 | AS7: 0 | AT7: 3564000 | AU7: 3888000 | AV7: 4637409.9 | AW7: 2901739.1 | AX7: 3512969.7 | AY7: 2723876.7 | BA7: Outdoor | BB7: Trekking | BC7: Outdoor / Mountaineering [CHECK - activity] | BD7: Softshell | BE7: Pant | BF7: Classic Softshell | BG7: N
A8: SS28 | B8: All year | C8: TRUE | D8: 607649 | E8: Alert Mid Pant Women | G8: Apparel | H8: F27 | I8: CO | M8: OUT | N8: Legwear | O8: Inline | P8: Women | Q8: Pants | R8: Bottom | V8: 1700 | W8: 2.1 | X8: 810 | Y8: 0.2 | Z8: 648 | AA8: 1 | AB8: Better | AC8: 0.63 | AE8: None | AF8: None | AG8: 4 | AH8: 4 | AI8: 4SCO. No new. Update FW28? | AK8: 4000 | AL8: 5087 | AM8: 2986 | AN8: 3897 | AO8: 2958 | AP8: 3240000 | AQ8: 4118028.2 | AR8: 2395980 | AS8: 0 | AT8: 2395980 | AU8: 2592000 | AV8: 3346565.2 | AW8: 1938128 | AX8: 2436492.6 | AY8: 1855962.9 | BA8: Outdoor | BB8: Trekking | BC8: Outdoor / Mountaineering [CHECK - activity] | BD8: Softshell | BE8: Pant | BF8: Classic Softshell | BG8: N
A9: SS28 | B9: Spring/Summer | C9: TRUE | D9: 608158 | E9: Alert Mid Shorts Men | G9: Apparel | H9: S27 | I9: CO | M9: OUT | N9: Legwear | O9: Inline | P9: Men | Q9: Shorts | R9: Bottom | V9: 1200 | W9: 2.1 | X9: 571 | Y9: 0.2 | Z9: 456.8 | AA9: 1 | AB9: Better | AC9: 0.63 | AE9: None | AF9: None | AG9: 5 | AH9: 5 | AK9: 5100 | AL9: 5066 | AM9: 5091 | AN9: 0 | AO9: 0 | AP9: 2912100 | AQ9: 2894864.4 | AR9: 0 | AS9: 0 | AT9: 0 | AU9: 2329680 | AV9: 2473686.7 | AW9: 2256708.7 | AX9: 0 | AY9: 0 | BA9: Essentials | BB9: Trekking | BD9: Softshell | BE9: Shorts | BF9: Classic Softshell | BG9: N
A10: SS28 | B10: Spring/Summer | C10: TRUE | D10: 608178 | E10: Alert Mid Shorts Women | G10: Apparel | H10: S27 | I10: CO | M10: OUT | N10: Legwear | O10: Inline | P10: Women | Q10: Shorts | R10: Bottom | V10: 1200 | W10: 2.1 | X10: 571 | Y10: 0.2 | Z10: 456.8 | AA10: 1 | AB10: Better | AC10: 0.64 | AE10: None | AF10: None | AG10: 4 | AH10: 4 | AK10: 3400 | AL10: 3383 | AM10: 2688 | AN10: 0 | AO10: 0 | AP10: 1941400 | AQ10: 1933147.7 | AR10: 0 | AS10: 0 | AT10: 0 | AU10: 1553120 | AV10: 1630457.6 | AW10: 1311618.2 | AX10: 0 | AY10: 0 | BA10: Essentials | BB10: Trekking | BD10: Softshell | BE10: Shorts | BF10: Classic Softshell | BG10: N
A11: SS28 | B11: Fall/Winter | C11: FALSE | D11: 607936 | E11: Alper Proof Jacket Men | G11: Apparel | H11: F27 | I11: SEASONAL DROP | J11: FW-Style | M11: SNW | N11: Shell | O11: Inline | P11: Men | Q11: Jacket | R11: Top | V11: 4000 | W11: 2.1 | X11: 1905 | Y11: 0 | Z11: 1905 | AA11: 1 | AB11: Better | AE11: Proof | AF11: None | AH11: 4 | AI11: 4SCOS. 1NEW. Keep Northern Blue. | AL11: 0 | AM11: 0 | AN11: 2497 | AO11: 1964 | AP11: 0 | AQ11: 0 | AR11: 3741420 | AS11: 0 | AT11: 3741420 | AU11: 0 | AV11: 0 | AW11: 0 | AX11: 3782774.6 | AY11: 3026581 | AZ11: NOT Active in Centric | BA11: Skiing/Snowboarding | BB11: All Mountain | BC11: Skiing/Snowboarding / Freeride [CHECK - activity] | BD11: Shell | BE11: Jacket | BF11: 3L | BG11: Y
A12: SS28 | B12: Fall/Winter | C12: FALSE | D12: 607937 | E12: Alper Proof Jacket Women | G12: Apparel | H12: F27 | I12: SEASONAL DROP | J12: FW-Style | M12: SNW | N12: Shell | O12: Inline | P12: Women | Q12: Jacket | R12: Top | V12: 4000 | W12: 2.1 | X12: 1905 | Y12: 0 | Z12: 1905 | AA12: 1 | AB12: Better | AE12: Proof | AF12: None | AH12: 3 | AI12: 4SCOS. 1NEW. 20/11: 3 Colours. | AL12: 0 | AM12: 0 | AN12: 1605 | AO12: 1265 | AP12: 0 | AQ12: 0 | AR12: 2409825 | AS12: 0 | AT12: 2409825 | AU12: 0 | AV12: 0 | AW12: 0 | AX12: 2520159.8 | AY12: 2020862.7 | AZ12: NOT Active in Centric | BA12: Skiing/Snowboarding | BB12: All Mountain | BC12: Skiing/Snowboarding / Freeride [CHECK - activity] | BD12: Shell | BE12: Jacket | BF12: 3L | BG12: Y
A13: SS28 | B13: Fall/Winter | C13: FALSE | D13: 607939 | E13: Alper Proof Pant Men | G13: Apparel | H13: F27 | I13: SEASONAL DROP | J13: FW-Style | M13: SNW | N13: Shell | O13: Inline | P13: Men | Q13: Pants | R13: Bottom | V13: 3200 | W13: 2.1 | X13: 1524 | Y13: 0 | Z13: 1524 | AA13: 1 | AB13: Better | AE13: Proof | AF13: None | AH13: 3 | AI13: 1NEW to match Jacket. | AL13: 0 | AM13: 0 | AN13: 1816 | AO13: 1464 | AP13: 0 | AQ13: 0 | AR13: 2231136 | AS13: 0 | AT13: 2231136 | AU13: 0 | AV13: 0 | AW13: 0 | AX13: 2203624.3 | AY13: 1809783.8 | AZ13: NOT Active in Centric | BA13: Skiing/Snowboarding | BB13: All Mountain | BC13: Skiing/Snowboarding / Freeride [CHECK - activity] | BD13: Shell | BE13: Pant | BF13: 3L | BG13: Y
A14: SS28 | B14: Fall/Winter | C14: FALSE | D14: 607938 | E14: Alper Proof Pant Women | G14: Apparel | H14: F27 | I14: SEASONAL DROP | J14: FW-Style | M14: SNW | N14: Shell | O14: Inline | P14: Women | Q14: Pants | R14: Bottom | V14: 3200 | W14: 2.1 | X14: 1524 | Y14: 0 | Z14: 1524 | AA14: 1 | AB14: Better | AE14: Proof | AF14: None | AH14: 3 | AL14: 0 | AM14: 0 | AN14: 1003 | AO14: 1122 | AP14: 0 | AQ14: 0 | AR14: 1709928 | AS14: 0 | AT14: 1709928 | AU14: 0 | AV14: 0 | AW14: 0 | AX14: 1290394.6 | AY14: 1456702.5 | AZ14: NOT Active in Centric | BA14: Skiing/Snowboarding | BB14: All Mountain | BC14: Skiing/Snowboarding / Freeride [CHECK - activity] | BD14: Shell | BE14: Pant | BF14: 3L | BG14: Y
A15: SS28 | B15: All year | C15: FALSE | D15: 608250 | E15: Apex II Hood Men | G15: Apparel | H15: S27 | I15: CANCELED | J15: Dropped | L15: XXL | M15: OUT | N15: Softshell | O15: Inline | P15: Men | Q15: Jacket | R15: Top | V15: 2200 | W15: 2.1 | X15: 1048 | Y15: 0 | Z15: 1048 | AA15: 1 | AB15: Better | AE15: None | AF15: None | AH15: 1 | AJ15: XXL | AL15: 0 | AM15: 3032 | AN15: 0 | AO15: 0 | AP15: 0 | AQ15: 0 | AR15: 0 | AS15: 0 | AT15: 0 | AU15: 0 | AV15: 0 | AW15: 1744987.2 | AX15: 0 | AY15: 0 | AZ15: NOT Active in Centric | BA15: Essentials | BB15: Active Essentials | BD15: Softshell | BE15: Hooded Jacket | BF15: Classic Softshell | BG15: N | BH15: In FW27 but not attributed there — proposed from FW27 rules; confirm
A16: SS28 | B16: All year | C16: FALSE | D16: 608249 | E16: Apex II Hood Women | G16: Apparel | H16: S27 | I16: CANCELED | J16: Dropped | L16: XXL | M16: OUT | N16: Softshell | O16: Inline | P16: Women | Q16: Hood | R16: Top | V16: 2200 | W16: 2.1 | X16: 1048 | Y16: 0 | Z16: 1048 | AA16: 1 | AB16: Better | AE16: None | AF16: None | AH16: 1 | AJ16: XXL | AL16: 0 | AM16: 1475 | AN16: 0 | AO16: 0 | AP16: 0 | AQ16: 0 | AR16: 0 | AS16: 0 | AT16: 0 | AU16: 0 | AV16: 0 | AW16: 848685.75 | AX16: 0 | AY16: 0 | AZ16: NOT Active in Centric | BA16: Essentials | BB16: Active Essentials | BD16: Softshell | BE16: Hooded Jacket | BF16: Classic Softshell | BG16: N | BH16: In FW27 but not attributed there — proposed from FW27 rules; confirm
A17: SS28 | B17: Fall/Winter | C17: FALSE | D17: 608690 | E17: Aresk Beanie | G17: Apparel | H17: F27 | I17: SEASONAL DROP | J17: FW-Style | M17: OUT | N17: Accessories | O17: Inline | P17: Unisex | Q17: Beanie | R17: Other | V17: 450 | W17: 2.1 | X17: 214 | Y17: 0 | Z17: 214 | AA17: 1 | AB17: Good | AE17: None | AF17: None | AH17: 5 | AI17: 5SCO. 5 NEW. No of SCOs aligned with other Beanies. | AL17: 0 | AM17: 0 | AN17: 3055 | AO17: 0 | AP17: 0 | AQ17: 0 | AR17: 0 | AS17: 0 | AT17: 0 | AU17: 0 | AV17: 0 | AW17: 0 | AX17: 447391.93 | AY17: 0 | AZ17: NOT Active in Centric | BA17: Essentials | BB17: Active Essentials | BD17: Accessories | BE17: Headwear | BF17: Beanie | BG17: N
A18: SS28 | B18: All year | C18: FALSE | D18: 607766 | E18: Aria Proof Parka Women | G18: Apparel | H18: S27 | I18: CANCELED | J18: Dropped for FW27 | M18: OUT | N18: Shell | O18: Inline | P18: Women | Q18: Parka | R18: Top | V18: 2500 | W18: 2.1 | X18: 1190 | Y18: 0.2 | Z18: 952 | AA18: 1 | AB18: Better | AE18: Proof | AF18: None | AH18: 3 | AJ18: XXL | AL18: 1191 | AM18: 708 | AN18: 0 | AO18: 1163 | AP18: 0 | AQ18: 1417861.7 | AR18: 1383970 | AS18: 0 | AT18: 1383970 | AU18: 0 | AV18: 1120741.9 | AW18: 718346.38 | AX18: 0 | AY18: 1199096.3 | AZ18: NOT Active in Centric | BA18: Essentials | BB18: Daily Essentials | BD18: Shell | BE18: Parka | BF18: 2L | BG18: Y | BH18: Carryover from SS27 — aligned Activity→Daily Essentials
A19: SS28 | B19: Fall/Winter | C19: FALSE | D19: 608363 | E19: Aska Insulated Jacket Men | G19: Apparel | H19: F27 | I19: SEASONAL DROP | J19: FW-Style | L19: Intersport | M19: OUT | N19: Shell | O19: ABS | P19: Men | Q19: Jacket | R19: Top | V19: 2500 | W19: 2.1 | X19: 1190 | Y19: 0 | Z19: 1190 | AA19: 1 | AB19: Good | AE19: Proof | AF19: Mimic | AH19: 3 | AI19: Check col request with Tom F in Finland. 25/11 Tom: Add Stone Brick. | AJ19: Intersport | AL19: 0 | AM19: 0 | AN19: 1500 | AO19: 1011 | AP19: 0 | AQ19: 0 | AR19: 1203090 | AS19: 0 | AT19: 1203090 | AU19: 0 | AV19: 0 | AW19: 0 | AX19: 1471851.4 | AY19: 891142.2 | AZ19: NOT Active in Centric | BA19: Essentials | BB19: Active Essentials | BD19: Shell | BE19: Jacket | BF19: Insulated | BG19: Y
A20: SS28 | B20: Fall/Winter | C20: FALSE | D20: 608365 | E20: Aska Insulated Jacket Women | G20: Apparel | H20: F27 | I20: SEASONAL DROP | J20: FW-Style | L20: Intersport | M20: OUT | N20: Shell | O20: ABS | P20: Women | Q20: Jacket | R20: Top | V20: 2500 | W20: 2.1 | X20: 1190 | Y20: 0 | Z20: 1190 | AA20: 1 | AB20: Good | AE20: Proof | AF20: Mimic | AH20: 3 | AI20: Check col request with Tom F in Finland. 25/11 Tom: Add Tarn Blue. | AJ20: Intersport | AL20: 0 | AM20: 0 | AN20: 1340 | AO20: 735 | AP20: 0 | AQ20: 0 | AR20: 874650 | AS20: 0 | AT20: 874650 | AU20: 0 | AV20: 0 | AW20: 0 | AX20: 1310782.8 | AY20: 612003.32 | AZ20: NOT Active in Centric | BA20: Essentials | BB20: Active Essentials | BD20: Shell | BE20: Jacket | BF20: Insulated | BG20: Y
A21: SS28 | B21: Fall/Winter | C21: FALSE | D21: 608530 | E21: Aska Insulated Pant Men | G21: Apparel | H21: F27 | I21: SEASONAL DROP | J21: FW-Style | L21: Intersport | M21: OUT | N21: Shell | O21: ABS | P21: Men | Q21: Pants | R21: Bottom | V21: 2000 | W21: 2.1 | X21: 952 | Y21: 0 | Z21: 952 | AA21: 1 | AB21: Good | AE21: Proof | AF21: Mimic | AH21: 1 | AI21: only Black | AJ21: Intersport | AL21: 0 | AM21: 0 | AN21: 845 | AO21: 681 | AP21: 0 | AQ21: 0 | AR21: 648312 | AS21: 0 | AT21: 648312 | AU21: 0 | AV21: 0 | AW21: 0 | AX21: 640402.86 | AY21: 468186.2 | AZ21: NOT Active in Centric | BA21: Essentials | BB21: Active Essentials | BC21: Essentials / Essentials/Everyday [MATCH] | BD21: Shell | BE21: Pant | BF21: Insulated | BG21: Y
A22: SS28 | B22: Fall/Winter | C22: FALSE | D22: 608529 | E22: Aska Insulated Pant Women | G22: Apparel | H22: F27 | I22: SEASONAL DROP | J22: FW-Style | L22: Intersport | M22: OUT | N22: Shell | O22: ABS | P22: Women | Q22: Pants | R22: Bottom | V22: 2000 | W22: 2.1 | X22: 952 | Y22: 0 | Z22: 952 | AA22: 1 | AB22: Good | AE22: Proof | AF22: Mimic | AH22: 1 | AI22: only Black | AJ22: Intersport | AL22: 0 | AM22: 0 | AN22: 995 | AO22: 781 | AP22: 0 | AQ22: 0 | AR22: 743512 | AS22: 0 | AT22: 743512 | AU22: 0 | AV22: 0 | AW22: 0 | AX22: 753260 | AY22: 536031.08 | AZ22: NOT Active in Centric | BA22: Essentials | BB22: Active Essentials | BC22: Essentials / Essentials/Everyday [MATCH] | BD22: Shell | BE22: Pant | BF22: Insulated | BG22: Y
A23: SS28 | B23: All year | C23: TRUE | D23: 608395 | E23: Aska Proof Jacket Men | G23: Apparel | H23: F27 | I23: CO | L23: Intersport | M23: OUT | N23: Shell | O23: ABS | P23: Men | Q23: Jacket | R23: Top | V23: 2200 | W23: 2.1 | X23: 1048 | Y23: 0.2 | Z23: 838.4 | AA23: 1 | AB23: Good | AC23: 0.592 | AE23: Proof | AF23: None | AG23: 3 | AH23: 3 | AI23: Check col request with Tom F in Finland. 25/11 Tom: No News. | AJ23: Intersport | AK23: 2300 | AL23: 2300 | AM23: 2838 | AN23: 2125 | AO23: 1259 | AP23: 2410400 | AQ23: 2409526 | AR23: 1319432 | AS23: 0 | AT23: 1319432 | AU23: 1928320 | AV23: 1866064.7 | AW23: 1988996.3 | AX23: 1723444.6 | AY23: 885189.88 | BA23: Essentials | BB23: Active Essentials | BD23: Shell | BE23: Jacket | BF23: 2L | BG23: Y
A24: SS28 | B24: All year | C24: TRUE | D24: 608396 | E24: Aska Proof Jacket Women | G24: Apparel | H24: F27 | I24: CO | L24: Intersport | M24: OUT | N24: Shell | O24: ABS | P24: Women | Q24: Jacket | R24: Top | V24: 2200 | W24: 2.1 | X24: 1048 | Y24: 0.2 | Z24: 838.4 | AA24: 1 | AB24: Good | AC24: 0.575 | AE24: Proof | AF24: None | AG24: 3 | AH24: 3 | AI24: Check col request with Tom F in Finland. 25/11 Tom: No News. | AJ24: Intersport | AK24: 2300 | AL24: 2335 | AM24: 2067 | AN24: 2125 | AO24: 1283 | AP24: 2410400 | AQ24: 2446192.7 | AR24: 1344584 | AS24: 0 | AT24: 1344584 | AU24: 1928320 | AV24: 1892373.1 | AW24: 1464220.9 | AX24: 1720616.1 | AY24: 913682.28 | BA24: Essentials | BB24: Active Essentials | BD24: Shell | BE24: Jacket | BF24: 2L | BG24: Y
A25: SS28 | B25: All year | C25: TRUE | D25: 608397 | E25: Aska Proof Pant Men | G25: Apparel | H25: F27 | I25: CO | L25: Intersport | M25: OUT | N25: Shell | O25: ABS | P25: Men | Q25: Pants | R25: Bottom | V25: 1700 | W25: 2.1 | X25: 810 | Y25: 0.2 | Z25: 648 | AA25: 1 | AB25: Good | AC25: 0.592 | AE25: Proof | AF25: None | AG25: 1 | AH25: 1 | AI25: Only Black | AJ25: Intersport | AK25: 1600 | AL25: 1625 | AM25: 883 | AN25: 1615 | AO25: 442 | AP25: 1296000 | AQ25: 1315470 | AR25: 358020 | AS25: 0 | AT25: 358020 | AU25: 1036800 | AV25: 1036303.8 | AW25: 504389.49 | AX25: 1032164 | AY25: 255197.48 | BA25: Essentials | BB25: Active Essentials | BD25: Shell | BE25: Pant | BF25: 2L | BG25: Y
A26: SS28 | B26: All year | C26: TRUE | D26: 608398 | E26: Aska Proof Pant Women | G26: Apparel | H26: F27 | I26: CO | L26: Intersport | M26: OUT | N26: Shell | O26: ABS | P26: Women | Q26: Pants | R26: Bottom | V26: 1700 | W26: 2.1 | X26: 810 | Y26: 0.2 | Z26: 648 | AA26: 1 | AB26: Good | AC26: 0.575 | AE26: Proof | AF26: None | AG26: 1 | AH26: 1 | AI26: Only Black | AJ26: Intersport | AK26: 1600 | AL26: 1625 | AM26: 729 | AN26: 1665 | AO26: 472 | AP26: 1296000 | AQ26: 1315470 | AR26: 382320 | AS26: 0 | AT26: 382320 | AU26: 1036800 | AV26: 1036303.8 | AW26: 417695.65 | AX26: 1063866.8 | AY26: 272257.03 | BA26: Essentials | BB26: Active Essentials | BD26: Shell | BE26: Pant | BF26: 2L | BG26: Y
A27: SS28 | B27: All year | C27: TRUE | D27: 608656 | E27: Aska Softshell Hood Men | G27: Apparel | H27: F27 | I27: CO | L27: Intersport | M27: OUT | N27: Softshell | O27: ABS | P27: Men | Q27: Jacket | R27: Top | V27: 1800 | W27: 2.1 | X27: 857 | Y27: 0.2 | Z27: 685.6 | AA27: 1 | AB27: Good | AC27: 0.62 | AE27: None | AF27: None | AG27: 3 | AH27: 4 | AI27: Follow Korp Softshell + Check no of col needed with Tom F in Finland. 25/11 Tom: Chalk Beige dropped. | AJ27: Intersport | AK27: 1700 | AL27: 1745 | AM27: 0 | AN27: 0 | AO27: 0 | AP27: 1456900 | AQ27: 1246436.1 | AR27: 0 | AS27: 0 | AT27: 0 | AU27: 1165520 | AV27: 970756.74 | AW27: 0 | AX27: 0 | AY27: 0 | BA27: Outdoor | BB27: Day Hiking | BC27: Outdoor / Hiking [MATCH] | BD27: Softshell | BE27: Hooded Jacket | BF27: Classic Softshell | BG27: N
A28: SS28 | B28: All year | C28: TRUE | D28: 608658 | E28: Aska Softshell Hood Women | G28: Apparel | H28: F27 | I28: CO | L28: Intersport | M28: OUT | N28: Softshell | O28: ABS | P28: Women | Q28: Jacket | R28: Top | V28: 1800 | W28: 2.1 | X28: 857 | Y28: 0.2 | Z28: 685.6 | AA28: 1 | AB28: Good | AC28: 0.64 | AE28: None | AF28: None | AG28: 3 | AH28: 3 | AI28: Follow Korp Softshell + Check no of col needed with Tom F in Finland. 25/11 Tom: Chalk Beige dropped. | AJ28: Intersport | AK28: 1600 | AL28: 1610 | AM28: 0 | AN28: 250 | AO28: 0 | AP28: 1371200 | AQ28: 1150006.9 | AR28: 0 | AS28: 0 | AT28: 0 | AU28: 1096960 | AV28: 894659.5 | AW28: 0 | AX28: 145304.76 | AY28: 0 | BA28: Outdoor | BB28: Day Hiking | BC28: Outdoor / Hiking [MATCH] | BD28: Softshell | BE28: Hooded Jacket | BF28: Classic Softshell | BG28: N
A29: SS28 | B29: All year | C29: TRUE | D29: 608657 | E29: Aska Softshell Pant Men | G29: Apparel | H29: F27 | I29: CO | L29: Intersport | M29: OUT | N29: Softshell | O29: ABS | P29: Men | Q29: Pants | R29: Bottom | V29: 1400 | W29: 2.1 | X29: 667 | Y29: 0.2 | Z29: 533.6 | AA29: 1 | AB29: Good | AC29: 0.65 | AE29: None | AF29: None | AG29: 1 | AH29: 1 | AI29: Only Black | AJ29: Intersport | AK29: 2500 | AL29: 2525 | AM29: 0 | AN29: 1750 | AO29: 0 | AP29: 1667500 | AQ29: 1442860.8 | AR29: 0 | AS29: 0 | AT29: 0 | AU29: 1334000 | AV29: 1112445.5 | AW29: 0 | AX29: 777628.57 | AY29: 0 | BA29: Outdoor | BB29: Day Hiking | BC29: Outdoor / Hiking [MATCH] | BD29: Softshell | BE29: Pant | BF29: Classic Softshell | BG29: N
A30: SS28 | B30: All year | C30: TRUE | D30: 608659 | E30: Aska Softshell Pant Women | G30: Apparel | H30: F27 | I30: CO | L30: Intersport | M30: OUT | N30: Softshell | O30: ABS | P30: Women | Q30: Pants | R30: Bottom | V30: 1400 | W30: 2.1 | X30: 667 | Y30: 0.2 | Z30: 533.6 | AA30: 1 | AB30: Good | AC30: 0.65 | AE30: None | AF30: None | AG30: 1 | AH30: 1 | AI30: Only Black | AJ30: Intersport | AK30: 2500 | AL30: 2525 | AM30: 0 | AN30: 1600 | AO30: 0 | AP30: 1667500 | AQ30: 1442860.8 | AR30: 0 | AS30: 0 | AT30: 0 | AU30: 1334000 | AV30: 1112445.5 | AW30: 0 | AX30: 710260 | AY30: 0 | BA30: Outdoor | BB30: Day Hiking | BC30: Outdoor / Hiking [MATCH] | BD30: Softshell | BE30: Pant | BF30: Classic Softshell | BG30: N
A31: SS28 | B31: All year | C31: TRUE | D31: 607593 | E31: Astral GTX II Jacket Men | G31: Apparel | H31: F27 | I31: CO | M31: OUT | N31: Shell | O31: Inline | P31: Men | Q31: Jacket | R31: Top | V31: 4500 | W31: 2.1 | X31: 2143 | Y31: 0.2 | Z31: 1714.4 | AA31: 1 | AB31: Better | AC31: 0.615 | AE31: Gore-Tex | AF31: None | AG31: 5 | AH31: 5 | AI31: 5SCO. No New. | AK31: 3700 | AL31: 3931 | AM31: 2516 | AN31: 4202 | AO31: 2944 | AP31: 7929100 | AQ31: 8423582.7 | AR31: 6308992 | AS31: 0 | AT31: 6308992 | AU31: 6343280 | AV31: 6941242.7 | AW31: 3977695.2 | AX31: 7335526 | AY31: 5348195.5 | BA31: Essentials | BB31: Active Essentials | BC31: Essentials / Essentials/Everyday [MATCH] | BD31: Shell | BE31: Jacket | BF31: 2L | BG31: Y
A32: SS28 | B32: All year | C32: TRUE | D32: 607563 | E32: Astral GTX II Jacket Women | G32: Apparel | H32: F27 | I32: CO | M32: OUT | N32: Shell | O32: Inline | P32: Women | Q32: Jacket | R32: Top | V32: 4500 | W32: 2.1 | X32: 2143 | Y32: 0.2 | Z32: 1714.4 | AA32: 1 | AB32: Better | AC32: 0.616 | AE32: Gore-Tex | AF32: None | AG32: 5 | AH32: 5 | AI32: 5SCO. No New. | AK32: 3100 | AL32: 3272 | AM32: 2041 | AN32: 2693 | AO32: 1591 | AP32: 6643300 | AQ32: 7011437.9 | AR32: 3409513 | AS32: 0 | AT32: 3409513 | AU32: 5314640 | AV32: 5779169.8 | AW32: 3349112.4 | AX32: 4708139.8 | AY32: 2930006.2 | BA32: Essentials | BB32: Active Essentials | BC32: Essentials / Essentials/Everyday [MATCH] | BD32: Shell | BE32: Jacket | BF32: 2L | BG32: Y
A33: SS28 | B33: Fall/Winter | C33: FALSE | D33: 608688 | E33: Aze II Beanie | G33: Apparel | H33: F27 | I33: SEASONAL DROP | J33: FW-Style | M33: OUT | N33: Accessories | O33: Inline | P33: Unisex | Q33: Beanie | R33: Other | V33: 300 | W33: 2.1 | X33: 143 | Y33: 0 | Z33: 143 | AA33: 1 | AB33: Good | AE33: None | AF33: None | AH33: 5 | AI33: Branding update | AL33: 0 | AM33: 0 | AN33: 5966 | AO33: 0 | AP33: 0 | AQ33: 0 | AR33: 0 | AS33: 0 | AT33: 0 | AU33: 0 | AV33: 0 | AW33: 0 | AX33: 664971.92 | AY33: 0 | AZ33: NOT Active in Centric | BA33: Essentials | BB33: Active Essentials | BD33: Accessories | BE33: Headwear | BF33: Beanie | BG33: N
A34: SS28 | B34: Fall/Winter | C34: FALSE | D34: 608451 | E34: Base Mimic II Hood Men | G34: Apparel | H34: F27 | I34: CANCELED | J34: Dropped | L34: XXL | M34: OUT | N34: Insulation | O34: ABS | P34: Men | Q34: Hood | R34: Top | V34: 2200 | W34: 2.1 | X34: 1048 | Y34: 0 | Z34: 1048 | AA34: 1 | AB34: Good | AE34: Mimic | AF34: None | AH34: 4 | AI34: If needed check col with Pontus. 25/11 Pontus: Activate Seaweed Green. Add 1 New (Northern Blue) | AJ34: XXL | AL34: 0 | AM34: 0 | AN34: 60 | AO34: 0 | AP34: 0 | AQ34: 0 | AR34: 0 | AS34: 0 | AT34: 0 | AU34: 0 | AV34: 0 | AW34: 0 | AX34: 47142 | AY34: 0 | AZ34: NOT Active in Centric | BA34: Essentials | BB34: Active Essentials | BD34: Insulation | BE34: Hooded Jacket | BF34: Midweight Synthetic | BG34: N
A35: SS28 | B35: Fall/Winter | C35: FALSE | D35: 608452 | E35: Base Mimic II Hood Women | G35: Apparel | H35: F27 | I35: CANCELED | J35: Dropped | L35: XXL | M35: OUT | N35: Insulation | O35: ABS | P35: Women | Q35: Hood | R35: Top | V35: 2200 | W35: 2.1 | X35: 1048 | Y35: 0 | Z35: 1048 | AA35: 1 | AB35: Good | AE35: Mimic | AF35: None | AH35: 3 | AI35: If needed check col with Pontus. 25/11 Pontus: 2 New (Dusty Rose and Misty Mauve), Activate Olive Green. | AJ35: XXL | AL35: 0 | AM35: 0 | AN35: 60 | AO35: 0 | AP35: 0 | AQ35: 0 | AR35: 0 | AS35: 0 | AT35: 0 | AU35: 0 | AV35: 0 | AW35: 0 | AX35: 47142 | AY35: 0 | AZ35: NOT Active in Centric | BA35: Essentials | BB35: Active Essentials | BD35: Insulation | BE35: Hooded Jacket | BF35: Midweight Synthetic | BG35: N
A36: SS28 | B36: Fall/Winter | C36: FALSE | D36: 608454 | E36: Base Mimic II Jacket Men | G36: Apparel | H36: F27 | I36: CANCELED | J36: Dropped | L36: XXL | M36: OUT | N36: Insulation | O36: ABS | P36: Men | Q36: Jacket | R36: Top | V36: 2000 | W36: 2.1 | X36: 952 | Y36: 0 | Z36: 952 | AA36: 1 | AB36: Good | AE36: Mimic | AF36: None | AH36: 4 | AI36: If needed check col with Pontus. 25/11 Pontus: Add 1 New (Northern Blue). Activate Seaweed Green. | AJ36: XXL | AL36: 0 | AM36: 0 | AN36: 40 | AO36: 1000 | AP36: 0 | AQ36: 0 | AR36: 952000 | AS36: 0 | AT36: 952000 | AU36: 0 | AV36: 0 | AW36: 0 | AX36: 29100 | AY36: 571000 | AZ36: NOT Active in Centric | BA36: Essentials | BB36: Active Essentials | BD36: Insulation | BE36: Jacket | BF36: Midweight Synthetic | BG36: N
A37: SS28 | B37: Fall/Winter | C37: FALSE | D37: 608453 | E37: Base Mimic II Jacket Women | G37: Apparel | H37: F27 | I37: CANCELED | J37: Dropped | L37: XXL | M37: OUT | N37: Insulation | O37: ABS | P37: Women | Q37: Jacket | R37: Top | V37: 2000 | W37: 2.1 | X37: 952 | Y37: 0 | Z37: 952 | AA37: 1 | AB37: Good | AE37: Mimic | AF37: None | AH37: 4 | AI37: If needed check col with Pontus. 25/11 Pontus: 2 New (Dusty Rose and Misty Mauve). Activate Seaweed Green. | AJ37: XXL | AL37: 0 | AM37: 0 | AN37: 40 | AO37: 1000 | AP37: 0 | AQ37: 0 | AR37: 952000 | AS37: 0 | AT37: 952000 | AU37: 0 | AV37: 0 | AW37: 0 | AX37: 29100 | AY37: 571000 | AZ37: NOT Active in Centric | BA37: Essentials | BB37: Active Essentials | BD37: Insulation | BE37: Jacket | BF37: Midweight Synthetic | BG37: N
A38: SS28 | B38: All year | C38: TRUE | D38: 608587 | E38: Brand Five Panel Cap | G38: Apparel | H38: F27 | I38: CO | M38: DAY | N38: Accessories | O38: Inline | P38: Unisex | Q38: Cap | R38: Other | V38: 450 | W38: 2.1 | X38: 214 | Y38: 0.2 | Z38: 171.2 | AA38: 1 | AB38: Better | AC38: 0.613 | AE38: None | AF38: None | AG38: 6 | AH38: 6 | AI38: Charlotte: 4SCO. No New. | AK38: 4000 | AL38: 4038 | AM38: 2901 | AN38: 688 | AO38: 580 | AP38: 856000 | AQ38: 865303.02 | AR38: 124120 | AS38: 0 | AT38: 124120 | AU38: 684800 | AV38: 701135.71 | AW38: 547336.03 | AX38: 132974.21 | AY38: 113812.42 | BA38: Essentials | BB38: Active Essentials | BD38: Accessories | BE38: Headwear | BF38: Cap | BG38: N
A39: SS28 | B39: Fall/Winter | C39: FALSE | D39: 607824 | E39: Breeze Mimic Hood Men | G39: Apparel | H39: F27 | I39: SEASONAL DROP | J39: FW-Style | M39: OUT | N39: Insulation | O39: Inline | P39: Men | Q39: Hood | R39: Top | V39: 2600 | W39: 2.1 | X39: 1238 | Y39: 0 | Z39: 1238 | AA39: 1 | AB39: Good | AE39: Mimic | AF39: None | AH39: 3 | AI39: 2SCO. No new. | AJ39: Intersport | AL39: 0 | AM39: 0 | AN39: 1375 | AO39: 1083 | AP39: 0 | AQ39: 0 | AR39: 1340754 | AS39: 0 | AT39: 1340754 | AU39: 0 | AV39: 0 | AW39: 0 | AX39: 1473835.5 | AY39: 1142470 | AZ39: NOT Active in Centric | BA39: Essentials | BB39: Active Essentials | BC39: Outdoor / Mountaineering [CHECK - collection + activity] | BD39: Insulation | BE39: Hooded Jacket | BF39: Midweight Synthetic | BG39: N
A40: SS28 | B40: Fall/Winter | C40: FALSE | D40: 607825 | E40: Breeze Mimic Hood Women | G40: Apparel | H40: F27 | I40: SEASONAL DROP | J40: FW-Style | M40: OUT | N40: Insulation | O40: Inline | P40: Women | Q40: Hood | R40: Top | V40: 2600 | W40: 2.1 | X40: 1238 | Y40: 0 | Z40: 1238 | AA40: 1 | AB40: Good | AE40: Mimic | AF40: None | AH40: 3 | AI40: Charlotte: 2SCO. 1 New. Drop Tarn Blue. Replace with Coffee Bean? | AJ40: Intersport | AL40: 0 | AM40: 0 | AN40: 1204 | AO40: 1107 | AP40: 0 | AQ40: 0 | AR40: 1370466 | AS40: 0 | AT40: 1370466 | AU40: 0 | AV40: 0 | AW40: 0 | AX40: 1304800.7 | AY40: 1123400.6 | AZ40: NOT Active in Centric | BA40: Essentials | BB40: Active Essentials | BC40: Outdoor / Mountaineering [CHECK - collection + activity] | BD40: Insulation | BE40: Hooded Jacket | BF40: Midweight Synthetic | BG40: N
A41: SS28 | B41: All year | C41: TRUE | D41: 607680 | E41: Breeze Proof Jacket Men | G41: Apparel | H41: F27 | I41: CO | M41: OUT | N41: Shell | O41: Inline | P41: Men | Q41: Jacket | R41: Top | V41: 2000 | W41: 2.1 | X41: 952 | Y41: 0.2 | Z41: 761.6 | AA41: 1 | AB41: Good | AC41: 0.6 | AE41: Proof | AF41: None | AG41: 5 | AH41: 5 | AI41: Sofia: Potentially drop Haze Blue. Charlotte: 5SCOS. No New. Drop Northern Blue. | AK41: 5500 | AL41: 5969 | AM41: 4019 | AN41: 3746 | AO41: 2710 | AP41: 5236000 | AQ41: 5684756.2 | AR41: 2579920 | AS41: 0 | AT41: 2579920 | AU41: 4188800 | AV41: 4220635.5 | AW41: 2784798.3 | AX41: 2814178.6 | AY41: 2086447.8 | BA41: Essentials | BB41: Daily Essentials | BC41: Outdoor / Hiking [CHECK - collection + activity] | BD41: Shell | BE41: Jacket | BF41: 2L | BG41: Y
A42: SS28 | B42: All year | C42: TRUE | D42: 608838 | E42: Breeze Proof Jacket Men AF | G42: Apparel | H42: S27 | I42: CO | J42: Asia Fit | M42: OUT | N42: Shell | O42: ABS Exclusive | P42: Men | Q42: Jacket | R42: Top | V42: 2000 | W42: 2.1 | X42: 952 | Y42: 0.2 | Z42: 761.6 | AA42: 1 | AB42: Good | AE42: Proof | AF42: None | AH42: 0 | AJ42: Asia | AK42: 0 | AL42: 0 | AM42: 0 | AN42: 0 | AO42: 0 | AP42: 0 | AQ42: 0 | AR42: 0 | AS42: 0 | AT42: 0 | AU42: 0 | AV42: 0 | AW42: 0 | AX42: 0 | AY42: 0 | AZ42: NOT Active in Centric | BA42: Essentials | BB42: Daily Essentials | BC42: Outdoor / Hiking [CHECK - collection + activity] | BD42: Shell | BE42: Jacket | BF42: 2L | BG42: Y
A43: SS28 | B43: All year | C43: TRUE | D43: 607681 | E43: Breeze Proof Jacket Women | G43: Apparel | H43: F27 | I43: CO | M43: OUT | N43: Shell | O43: Inline | P43: Women | Q43: Jacket | R43: Top | V43: 2000 | W43: 2.1 | X43: 952 | Y43: 0.2 | Z43: 761.6 | AA43: 1 | AB43: Good | AC43: 0.61 | AE43: Proof | AF43: None | AG43: 5 | AH43: 5 | AI43: Sofia: Potentially drop Haze Blue. Charlotte: 6SCOS. No New. 20/11: 5 SCO. | AK43: 4300 | AL43: 4615 | AM43: 3226 | AN43: 2959 | AO43: 2000 | AP43: 4093600 | AQ43: 4395233.7 | AR43: 1904000 | AS43: 0 | AT43: 1904000 | AU43: 3274880 | AV43: 3377107.1 | AW43: 2382801.3 | AX43: 2223956.2 | AY43: 1593406.6 | BA43: Essentials | BB43: Daily Essentials | BC43: Outdoor / Hiking [CHECK - collection + activity] | BD43: Shell | BE43: Jacket | BF43: 2L | BG43: Y
A44: SS28 | B44: All year | C44: TRUE | D44: 608839 | E44: Breeze Proof Jacket Women AF | G44: Apparel | H44: S27 | I44: CO | J44: Asia Fit | M44: OUT | N44: Shell | O44: ABS Exclusive | P44: Women | Q44: Jacket | R44: Top | V44: 2000 | W44: 2.1 | X44: 952 | Y44: 0.2 | Z44: 761.6 | AA44: 1 | AB44: Good | AE44: Proof | AF44: None | AH44: 0 | AJ44: Asia | AK44: 0 | AL44: 0 | AM44: 0 | AN44: 0 | AO44: 0 | AP44: 0 | AQ44: 0 | AR44: 0 | AS44: 0 | AT44: 0 | AU44: 0 | AV44: 0 | AW44: 0 | AX44: 0 | AY44: 0 | AZ44: NOT Active in Centric | BA44: Essentials | BB44: Daily Essentials | BC44: Outdoor / Hiking [CHECK - collection + activity] | BD44: Shell | BE44: Jacket | BF44: 2L | BG44: Y
A45: SS28 | B45: All year | C45: TRUE | D45: 608683 | E45: Brisen Tech Mid Hood Men | G45: Apparel | H45: F27 | I45: CO | M45: ROC | N45: Midlayer | O45: Inline | P45: Men | Q45: Mid Hood | R45: Top | V45: 2200 | W45: 2.1 | X45: 1048 | Y45: 0.2 | Z45: 838.4 | AA45: 1 | AB45: Best | AC45: 0.58 | AE45: None | AF45: None | AG45: 4 | AH45: 4 | AI45: Charlotte: 3SCO. 3 NEW. | AK45: 1500 | AL45: 0 | AM45: 0 | AN45: 1987 | AO45: 0 | AP45: 1572000 | AQ45: 0 | AR45: 0 | AS45: 0 | AT45: 0 | AU45: 1257600 | AV45: 0 | AW45: 0 | AX45: 1221855.6 | AY45: 0 | BA45: Essentials | BB45: Active Essentials | BC45: Outdoor / Mountaineering | Skiing/Snowboarding / Touring [CHECK - collection + activity] | BD45: Fleece/Midlayer | BE45: Hooded Jacket | BF45: Lightweight | BG45: N
A46: SS28 | B46: All year | C46: TRUE | D46: 608684 | E46: Brisen Tech Mid Hood Women | G46: Apparel | H46: F27 | I46: CO | M46: ROC | N46: Midlayer | O46: Inline | P46: Women | Q46: Mid Hood | R46: Top | V46: 2200 | W46: 2.1 | X46: 1048 | Y46: 0.2 | Z46: 838.4 | AA46: 1 | AB46: Best | AC46: 0.6 | AE46: None | AF46: None | AG46: 4 | AH46: 4 | AI46: Charlotte: 3SCO. 3 NEW. | AK46: 1200 | AL46: 0 | AM46: 0 | AN46: 1497 | AO46: 0 | AP46: 1257600 | AQ46: 0 | AR46: 0 | AS46: 0 | AT46: 0 | AU46: 1006080 | AV46: 0 | AW46: 0 | AX46: 856425.97 | AY46: 0 | BA46: Essentials | BB46: Active Essentials | BC46: Outdoor / Mountaineering | Skiing/Snowboarding / Touring [CHECK - collection + activity] | BD46: Fleece/Midlayer | BE46: Hooded Jacket | BF46: Lightweight | BG46: N
A47: SS28 | B47: All year | C47: TRUE | D47: 608351 | E47: Buteo Mid II Jacket Men | G47: Apparel | H47: F27 | I47: CO | M47: OUT | N47: Midlayer | O47: Inline | P47: Men | Q47: Mid Jacket | R47: Top | V47: 900 | W47: 2.1 | X47: 429 | Y47: 0.2 | Z47: 343.2 | AA47: 1 | AB47: Good | AC47: 0.65 | AE47: Polartec | AF47: None | AG47: 6 | AH47: 6 | AI47: Solar orange out? Tech Bright yellow out? Charlotte: Drop Solar Orange (might look "cheap" on a non-premium style). 7SCO. 2NEW. 20/11: Drop Chlorophyll. | AK47: 10400 | AL47: 10354 | AM47: 0 | AN47: 19873 | AO47: 15531 | AP47: 4461600 | AQ47: 4437413.8 | AR47: 6662799 | AS47: 0 | AT47: 6662799 | AU47: 3569280 | AV47: 3585295.3 | AW47: 0 | AX47: 6260264.5 | AY47: 4983007.2 | BA47: Essentials | BB47: Active Essentials | BC47: Essentials / Essentials/Everyday [MATCH] | BD47: Fleece/Midlayer | BE47: Jacket | BF47: Midweight | BG47: N
A48: SS28 | B48: All year | C48: TRUE | D48: 608759 | E48: Buteo Mid II Jacket Men AF | G48: Apparel | H48: S27 | I48: CO | J48: Asia Fit | M48: OUT | N48: Midlayer | O48: ABS Exclusive | P48: Men | Q48: Mid Jacket | R48: Top | V48: 900 | W48: 2.1 | X48: 429 | Y48: 0.2 | Z48: 343.2 | AA48: 1 | AB48: Good | AE48: Polartec | AF48: None | AH48: 0 | AJ48: Asia | AK48: 1000 | AL48: 0 | AM48: 0 | AN48: 0 | AO48: 1200 | AP48: 429000 | AQ48: 0 | AR48: 514800 | AS48: 0 | AT48: 514800 | AU48: 343200 | AV48: 0 | AW48: 0 | AX48: 0 | AY48: 153370.8 | AZ48: NOT Active in Centric | BA48: Essentials | BB48: Active Essentials | BC48: Essentials / Essentials/Everyday [MATCH] | BD48: Fleece/Midlayer | BE48: Jacket | BF48: Midweight | BG48: N
A49: SS28 | B49: All year | C49: TRUE | D49: 608352 | E49: Buteo Mid II Jacket Women | G49: Apparel | H49: F27 | I49: CO | M49: OUT | N49: Midlayer | O49: Inline | P49: Women | Q49: Mid Jacket | R49: Top | V49: 900 | W49: 2.1 | X49: 429 | Y49: 0.2 | Z49: 343.2 | AA49: 1 | AB49: Good | AC49: 0.68 | AE49: Polartec | AF49: None | AG49: 6 | AH49: 6 | AI49: Tech bright yellow out? Charlotte: 7SCO. 1 New. | AK49: 8800 | AL49: 6133 | AM49: 0 | AN49: 14103 | AO49: 10333 | AP49: 3775200 | AQ49: 2628419.8 | AR49: 4432857 | AS49: 0 | AT49: 4432857 | AU49: 3020160 | AV49: 2155706 | AW49: 0 | AX49: 4447945.4 | AY49: 3397201 | BA49: Essentials | BB49: Active Essentials | BC49: Essentials / Essentials/Everyday [MATCH] | BD49: Fleece/Midlayer | BE49: Jacket | BF49: Midweight | BG49: N
A50: SS28 | B50: All year | C50: TRUE | D50: 608760 | E50: Buteo Mid II Jacket Women AF | G50: Apparel | H50: S27 | I50: CO | J50: Asia Fit | M50: OUT | N50: Midlayer | O50: ABS Exclusive | P50: Women | Q50: Mid Jacket | R50: Top | V50: 900 | W50: 2.1 | X50: 429 | Y50: 0.2 | Z50: 343.2 | AA50: 1 | AB50: Good | AE50: Polartec | AF50: None | AH50: 0 | AJ50: Asia | AK50: 1000 | AL50: 0 | AM50: 0 | AN50: 0 | AO50: 600 | AP50: 429000 | AQ50: 0 | AR50: 257400 | AS50: 0 | AT50: 257400 | AU50: 343200 | AV50: 0 | AW50: 0 | AX50: 0 | AY50: 72111.6 | AZ50: NOT Active in Centric | BA50: Essentials | BB50: Active Essentials | BC50: Essentials / Essentials/Everyday [MATCH] | BD50: Fleece/Midlayer | BE50: Jacket | BF50: Midweight | BG50: N
A51: SS28 | B51: All year | C51: TRUE | D51: 608421 | E51: Chaos GTX II Jacket Men | G51: Apparel | H51: F27 | I51: CO | J51: Potential Update, New Vietnam GTX | L51: Intersport | M51: OUT | N51: Shell | O51: ABS | P51: Men | Q51: Jacket | R51: Top | V51: 3500 | W51: 2.1 | X51: 1667 | Y51: 0.2 | Z51: 1333.6 | AA51: 1 | AB51: Good | AC51: 0.592 | AE51: Gore-Tex | AF51: None | AG51: 0 | AH51: 3 | AI51: Check col with Tom F in Finland. 25/11 Tom: Drop Haze Blue. 1 New (Seaweed Green). | AJ51: Intersport | AK51: 1100 | AL51: 1105 | AM51: 1034 | AN51: 850 | AO51: 2011 | AP51: 1833700 | AQ51: 1841670.4 | AR51: 3352337 | AS51: 0 | AT51: 3352337 | AU51: 1466960 | AV51: 1451359.2 | AW51: 1148276.9 | AX51: 1100417.1 | AY51: 1524056.2 | BA51: Essentials | BB51: Active Essentials | BC51: Essentials / Essentials/Everyday [MATCH] | BD51: Shell | BE51: Jacket | BF51: 2L | BG51: Y
A52: SS28 | B52: All year | C52: TRUE | D52: 608422 | E52: Chaos GTX II Jacket Women | G52: Apparel | H52: F27 | I52: CO | J52: Potential Update, New Vietnam GTX | L52: Intersport | M52: OUT | N52: Shell | O52: ABS | P52: Women | Q52: Jacket | R52: Top | V52: 3500 | W52: 2.1 | X52: 1667 | Y52: 0.2 | Z52: 1333.6 | AA52: 1 | AB52: Good | AC52: 0.575 | AE52: Gore-Tex | AF52: None | AG52: 0 | AH52: 2 | AI52: Check col with Tom F in Finland. 25/11 Tom: Drop Haze Blue, Raspberry Red. 1 New (Seaweed Green). | AJ52: Intersport | AK52: 800 | AL52: 810 | AM52: 820 | AN52: 750 | AO52: 1343 | AP52: 1333600 | AQ52: 1350002.7 | AR52: 2238781 | AS52: 0 | AT52: 2238781 | AU52: 1066880 | AV52: 1061877.9 | AW52: 926932.97 | AX52: 968750.48 | AY52: 1192610.3 | BA52: Outdoor | BB52: Active Essentials | BC52: Essentials / Essentials/Everyday [CHECK - collection] | BD52: Shell | BE52: Jacket | BF52: 2L | BG52: Y
A53: SS28 | B53: Fall/Winter | C53: FALSE | D53: 605630 | E53: Chill Down Hood Men | G53: Apparel | H53: F27 | I53: SEASONAL DROP | J53: FW-Style | L53: Intersport | M53: OUT | N53: Insulation | O53: ABS | P53: Men | Q53: Hood | R53: Top | V53: 3400 | W53: 2.1 | X53: 1619 | Y53: 0 | Z53: 1619 | AA53: 1 | AB53: Better | AE53: Down | AF53: None | AH53: 2 | AI53: check Col with Tom F in Finland. 25/11 Tom: No New. | AJ53: Intersport | AL53: 0 | AM53: 0 | AN53: 1140 | AO53: 1160 | AP53: 0 | AQ53: 0 | AR53: 1878040 | AS53: 0 | AT53: 1878040 | AU53: 0 | AV53: 0 | AW53: 0 | AX53: 1455017.1 | AY53: 1142296.4 | AZ53: NOT Active in Centric | BA53: Essentials | BB53: Active Essentials | BC53: Outdoor / Trekking [CHECK - collection + activity] | BD53: Insulation | BE53: Hooded Jacket | BF53: Midweight Down | BG53: N
A54: SS28 | B54: Fall/Winter | C54: FALSE | D54: 608450 | E54: Fiction Down II Hood Men | G54: Apparel | H54: F27 | I54: SEASONAL DROP | J54: FW-Style | L54: Intersport | M54: OUT | N54: Insulation | O54: ABS | P54: Men | Q54: Hood | R54: Top | V54: 2800 | W54: 2.1 | X54: 1333 | Y54: 0 | Z54: 1333 | AA54: 1 | AB54: Better | AE54: Down | AF54: None | AH54: 2 | AI54: check Col with Tom F in Finland. 25/11 Tom: Drop Tarn Blue. Add Seaweed Green. | AJ54: Intersport | AL54: 0 | AM54: 0 | AN54: 2000 | AO54: 2201 | AP54: 0 | AQ54: 0 | AR54: 2933933 | AS54: 0 | AT54: 2933933 | AU54: 0 | AV54: 0 | AW54: 0 | AX54: 2119550 | AY54: 1968619.9 | AZ54: NOT Active in Centric | BA54: Essentials | BB54: Active Essentials | BD54: Insulation | BE54: Hooded Jacket | BF54: Midweight Down | BG54: N
A55: SS28 | B55: Fall/Winter | C55: FALSE | D55: 608481 | E55: Fram Mimic Jacket Men | G55: Apparel | H55: F27 | I55: SEASONAL DROP | J55: FW-Style | M55: DAY | N55: Insulation | O55: Inline | P55: Men | Q55: Jacket | R55: Top | V55: 2500 | W55: 2.1 | X55: 1190 | Y55: 0 | Z55: 1190 | AA55: 1 | AB55: Better | AE55: Pertex | AF55: Mimic | AH55: 2 | AI55: Charlotte: 3SCO. 1 New. | AL55: 0 | AM55: 0 | AN55: 1036 | AO55: 884 | AP55: 0 | AQ55: 0 | AR55: 1051960 | AS55: 0 | AT55: 1051960 | AU55: 0 | AV55: 0 | AW55: 0 | AX55: 825532.45 | AY55: 784549.94 | AZ55: NOT Active in Centric | BA55: Essentials | BB55: Daily Essentials | BC55: Essentials / Essentials/Everyday [MATCH] | BD55: Insulation | BE55: Jacket | BF55: Midweight Synthetic | BG55: N
A56: SS28 | B56: Fall/Winter | C56: FALSE | D56: 608482 | E56: Fram Mimic Jacket Women | G56: Apparel | H56: F27 | I56: SEASONAL DROP | J56: FW-Style | M56: DAY | N56: Insulation | O56: Inline | P56: Women | Q56: Jacket | R56: Top | V56: 2500 | W56: 2.1 | X56: 1190 | Y56: 0 | Z56: 1190 | AA56: 1 | AB56: Better | AE56: Pertex | AF56: Mimic | AH56: 3 | AI56: 3SCO. 1 New. | AL56: 0 | AM56: 0 | AN56: 879 | AO56: 792 | AP56: 0 | AQ56: 0 | AR56: 942480 | AS56: 0 | AT56: 942480 | AU56: 0 | AV56: 0 | AW56: 0 | AX56: 690186.93 | AY56: 726468.33 | AZ56: NOT Active in Centric | BA56: Essentials | BB56: Daily Essentials | BC56: Essentials / Essentials/Everyday [MATCH] | BD56: Insulation | BE56: Jacket | BF56: Midweight Synthetic | BG56: N
A57: SS28 | B57: All year | C57: TRUE | D57: 607646 | E57: Front Flex Pant Men | G57: Apparel | H57: F27 | I57: CO | M57: OUT | N57: Legwear | O57: Inline | P57: Men | Q57: Pants | R57: Bottom | V57: 1500 | W57: 2.1 | X57: 714 | Y57: 0.2 | Z57: 571.2 | AA57: 1 | AB57: Better | AC57: 0.62 | AE57: None | AF57: None | AG57: 0 | AH57: 1 | AK57: 500 | AL57: 478 | AM57: 688 | AN57: 1821 | AO57: 902 | AP57: 357000 | AQ57: 341430.62 | AR57: 644028 | AS57: 0 | AT57: 644028 | AU57: 285600 | AV57: 316823.89 | AW57: 421807.37 | AX57: 824876.66 | AY57: 468937.57 | BA57: Outdoor | BB57: Trekking | BC57: Outdoor / Mountaineering [CHECK - activity] | BD57: Softshell | BE57: Pant | BF57: Classic Softshell | BG57: N
A58: SS28 | B58: All year | C58: TRUE | D58: 607650 | E58: Front Flex Pant Women | G58: Apparel | H58: F27 | I58: CO | M58: OUT | N58: Legwear | O58: Inline | P58: Women | Q58: Pants | R58: Bottom | V58: 1500 | W58: 2.1 | X58: 714 | Y58: 0.2 | Z58: 571.2 | AA58: 1 | AB58: Better | AC58: 0.63 | AE58: None | AF58: None | AG58: 0 | AH58: 1 | AK58: 400 | AL58: 374 | AM58: 742 | AN58: 1169 | AO58: 669 | AP58: 285600 | AQ58: 267144.46 | AR58: 477666 | AS58: 0 | AT58: 477666 | AU58: 228480 | AV58: 241758.75 | AW58: 429512.28 | AX58: 609763.53 | AY58: 382968.6 | BA58: Outdoor | BB58: Trekking | BC58: Outdoor / Mountaineering [CHECK - activity] | BD58: Softshell | BE58: Pant | BF58: Classic Softshell | BG58: N
A59: SS28 | B59: All year | C59: TRUE | D59: 607823 | E59: Front Proof II Jacket Men | G59: Apparel | H59: F27 | I59: CO | M59: OUT | N59: Shell | O59: Inline | P59: Men | Q59: Jacket | R59: Top | V59: 3300 | W59: 2.1 | X59: 1571 | Y59: 0.2 | Z59: 1256.8 | AA59: 1 | AB59: Better | AC59: 0.6 | AE59: Proof | AF59: None | AG59: 5 | AH59: 5 | AI59: Charlotte: 5SCO. 1New. New colour added in SS27. (second most selled shell jacket). 26/11: Maroon Trail/ Solar Orange dropped. 2New. | AK59: 4200 | AL59: 4216 | AM59: 3116 | AN59: 4350 | AO59: 2965 | AP59: 6598200 | AQ59: 6625148.9 | AR59: 4658015 | AS59: 0 | AT59: 4658015 | AU59: 5278560 | AV59: 4791926 | AW59: 3378237.5 | AX59: 5237876.7 | AY59: 3718994.9 | BA59: Outdoor | BB59: Trekking | BC59: Outdoor / Trekking [MATCH] | BD59: Shell | BE59: Jacket | BF59: 3L | BG59: Y
A60: SS28 | B60: All year | C60: FALSE | D60: 608836 | E60: Front Proof II Jacket Men AF | G60: Apparel | H60: S27 | I60: CANCELED | J60: Asia Fit | M60: OUT | N60: Shell | O60: ABS Exclusive | P60: Men | Q60: Jacket | R60: Top | V60: 3300 | W60: 2.1 | X60: 1571 | Y60: 0 | Z60: 1571 | AA60: 1 | AB60: Better | AE60: Proof | AF60: None | AH60: 3 | AJ60: Asia | AL60: 0 | AM60: 0 | AN60: 0 | AO60: 0 | AP60: 0 | AQ60: 0 | AR60: 0 | AS60: 0 | AT60: 0 | AU60: 0 | AV60: 0 | AW60: 0 | AX60: 0 | AY60: 0 | AZ60: NOT Active in Centric | BA60: Outdoor | BB60: Trekking | BC60: Outdoor / Trekking [MATCH] | BD60: Shell | BE60: Jacket | BF60: 3L | BG60: Y | BH60: Carried from FW27 fit-variant base: Front Proof II Jacket Men
A61: SS28 | B61: All year | C61: TRUE | D61: 607821 | E61: Front Proof II Jacket Women | G61: Apparel | H61: F27 | I61: CO | M61: OUT | N61: Shell | O61: Inline | P61: Women | Q61: Jacket | R61: Top | V61: 3300 | W61: 2.1 | X61: 1571 | Y61: 0.2 | Z61: 1256.8 | AA61: 1 | AB61: Better | AC61: 0.62 | AE61: Proof | AF61: None | AG61: 5 | AH61: 5 | AI61: Charlotte: 5SCO. 1New. New colour added in SS27. (second most selled shell jacket) | AK61: 3200 | AL61: 3222 | AM61: 2374 | AN61: 3020 | AO61: 2466 | AP61: 5027200 | AQ61: 5063147.5 | AR61: 3874086 | AS61: 0 | AT61: 3874086 | AU61: 4021760 | AV61: 3853233.2 | AW61: 2652802.9 | AX61: 3757290.4 | AY61: 3149470 | BA61: Outdoor | BB61: Trekking | BC61: Outdoor / Trekking [MATCH] | BD61: Shell | BE61: Jacket | BF61: 3L | BG61: Y
A62: SS28 | B62: All year | C62: FALSE | D62: 608837 | E62: Front Proof II Jacket Women AF | G62: Apparel | H62: S27 | I62: CANCELED | J62: Asia Fit | M62: OUT | N62: Shell | O62: ABS Exclusive | P62: Women | Q62: Jacket | R62: Top | V62: 3300 | W62: 2.1 | X62: 1571 | Y62: 0 | Z62: 1571 | AA62: 1 | AB62: Better | AE62: Proof | AF62: None | AH62: 2 | AJ62: Asia | AL62: 0 | AM62: 0 | AN62: 0 | AO62: 0 | AP62: 0 | AQ62: 0 | AR62: 0 | AS62: 0 | AT62: 0 | AU62: 0 | AV62: 0 | AW62: 0 | AX62: 0 | AY62: 0 | AZ62: NOT Active in Centric | BA62: Outdoor | BB62: Trekking | BC62: Outdoor / Trekking [MATCH] | BD62: Shell | BE62: Jacket | BF62: 3L | BG62: Y | BH62: Carried from FW27 fit-variant base: Front Proof II Jacket Women
A63: SS28 | B63: All year | C63: FALSE | D63: 607817 | E63: Funäs Pile Hood Men | G63: Apparel | H63: F27 | I63: SEASONAL DROP | J63: Change Seasonality | M63: DAY | N63: Midlayer | O63: Inline | P63: Men | Q63: Hood | R63: Top | V63: 1800 | W63: 2.1 | X63: 857 | Y63: 0 | Z63: 857 | AA63: 1 | AB63: Better | AE63: None | AF63: None | AH63: 3 | AI63: Bring back Seaweed green + 1 new (chalk). Charlotte: Drop Misty Mauve. 2 New progressive colors. | AL63: 0 | AM63: 0 | AN63: 2893 | AO63: 2603 | AP63: 0 | AQ63: 0 | AR63: 2230771 | AS63: 0 | AT63: 2230771 | AU63: 0 | AV63: 0 | AW63: 0 | AX63: 1977191.9 | AY63: 1772745.2 | AZ63: NOT Active in Centric | BA63: Essentials | BB63: Daily Essentials | BC63: Essentials / Essentials/Everyday [MATCH] | BD63: Fleece/Midlayer | BE63: Hooded Jacket | BF63: Heavyweight | BG63: N
A64: SS28 | B64: All year | C64: FALSE | D64: 607818 | E64: Funäs Pile Hood Women | G64: Apparel | H64: F27 | I64: SEASONAL DROP | J64: Change Seasonality | M64: DAY | N64: Midlayer | O64: Inline | P64: Women | Q64: Hood | R64: Top | V64: 1800 | W64: 2.1 | X64: 857 | Y64: 0 | Z64: 857 | AA64: 1 | AB64: Better | AE64: None | AF64: None | AH64: 3 | AI64: Chalk beige? Charlotte: 4SCO. 1 New. Progressive color. | AL64: 0 | AM64: 0 | AN64: 3214 | AO64: 2954 | AP64: 0 | AQ64: 0 | AR64: 2531578 | AS64: 0 | AT64: 2531578 | AU64: 0 | AV64: 0 | AW64: 0 | AX64: 2175289.7 | AY64: 2023673.6 | AZ64: NOT Active in Centric | BA64: Essentials | BB64: Daily Essentials | BC64: Essentials / Essentials/Everyday [MATCH] | BD64: Fleece/Midlayer | BE64: Hooded Jacket | BF64: Heavyweight | BG64: N
A65: SS28 | B65: All year | C65: FALSE | D65: 608652 | E65: Gabbro II Pant Men | G65: Apparel | H65: S27 | I65: CANCELED | J65: Dropped | L65: XXL | M65: OUT | N65: Softshell | O65: ABS | P65: Men | Q65: Pants | R65: Bottom | V65: 2200 | W65: 2.1 | X65: 1048 | Y65: 0 | Z65: 1048 | AA65: 1 | AB65: Better | AE65: None | AF65: None | AH65: 1 | AJ65: XXL | AL65: 0 | AM65: 0 | AN65: 0 | AO65: 0 | AP65: 0 | AQ65: 0 | AR65: 0 | AS65: 0 | AT65: 0 | AU65: 0 | AV65: 0 | AW65: 0 | AX65: 0 | AY65: 0 | AZ65: NOT Active in Centric | BA65: Essentials | BB65: Active Essentials | BD65: Softshell | BE65: Pant | BF65: Classic Softshell | BG65: N | BH65: In FW27 but not attributed there — proposed from FW27 rules; confirm
A66: SS28 | B66: All year | C66: FALSE | D66: 608653 | E66: Gabbro II Pant Women | G66: Apparel | H66: S27 | I66: CANCELED | J66: Dropped | L66: XXL | M66: OUT | N66: Softshell | O66: ABS | P66: Women | Q66: Pants | R66: Bottom | V66: 2200 | W66: 2.1 | X66: 1048 | Y66: 0 | Z66: 1048 | AA66: 1 | AB66: Better | AE66: None | AF66: None | AH66: 1 | AJ66: XXL | AL66: 0 | AM66: 0 | AN66: 0 | AO66: 0 | AP66: 0 | AQ66: 0 | AR66: 0 | AS66: 0 | AT66: 0 | AU66: 0 | AV66: 0 | AW66: 0 | AX66: 0 | AY66: 0 | AZ66: NOT Active in Centric | BA66: Essentials | BB66: Active Essentials | BD66: Softshell | BE66: Pant | BF66: Classic Softshell | BG66: N | BH66: In FW27 but not attributed there — proposed from FW27 rules; confirm
A67: SS28 | C67: FALSE | D67: 608821 | E67: Haglöfs Alpha Prototype Sweater Men | G67: Apparel | H67: F27 | I67: CANCELED | J67: Seasonal Brand Builder | M67: DAY | N67: Tops | O67: ABS Exclusive | P67: Men | Q67: LS Roundneck | R67: Top | V67: 0 | W67: 2.1 | X67: 0 | Y67: 0 | Z67: 0 | AA67: 0 | AE67: Polartec | AH67: 1 | AJ67: KA YO Collab | AL67: 0 | AM67: 0 | AN67: 0 | AO67: 0 | AP67: 0 | AQ67: 0 | AR67: 0 | AS67: 0 | AT67: 0 | AU67: 0 | AV67: 0 | AW67: 0 | AX67: 0 | AY67: 0 | AZ67: NOT Active in Centric | BA67: Essentials | BB67: Daily Essentials | BD67: Fleece/Midlayer | BE67: Pullover | BF67: Lightweight | BG67: N | BH67: Polartec Alpha = insulating midlayer, not Tops/Cotton. Set Fleece-Midlayer/Lightweight; prototype—confirm.
A68: SS28 | B68: Spring/Summer | C68: TRUE | D68: 608204 | E68: Haglöfs Bandana | G68: Apparel | H68: S27 | I68: CO | M68: DAY | N68: Accessories | O68: Inline | P68: Unisex | Q68: Neckwarmer | R68: Other | V68: 400 | W68: 2.1 | X68: 190 | Y68: 0.2 | Z68: 152 | AA68: 1 | AB68: Better | AC68: 0.6 | AE68: None | AF68: None | AG68: 3 | AH68: 3 | AK68: 900 | AL68: 907 | AM68: 957 | AN68: 0 | AO68: 0 | AP68: 171000 | AQ68: 172765.36 | AR68: 0 | AS68: 0 | AT68: 0 | AU68: 136800 | AV68: 162997.76 | AW68: 168644.28 | AX68: 0 | AY68: 0 | BA68: Essentials | BB68: Daily Essentials | BD68: Accessories | BE68: Headwear | BF68: Bandana | BG68: N
A69: SS28 | B69: Spring/Summer | C69: TRUE | D69: 607656 | E69: Haglöfs Cap | G69: Apparel | H69: S27 | I69: CO | M69: DAY | N69: Accessories | O69: Inline | P69: Unisex | Q69: Cap | R69: Other | V69: 400 | W69: 2.1 | X69: 190 | Y69: 0.2 | Z69: 152 | AA69: 1 | AB69: Good | AC69: 0.613 | AE69: None | AF69: None | AG69: 4 | AH69: 5 | AK69: 3000 | AL69: 2951 | AM69: 2398 | AN69: 0 | AO69: 16 | AP69: 570000 | AQ69: 562106.48 | AR69: 3040 | AS69: 0 | AT69: 3040 | AU69: 456000 | AV69: 451023.82 | AW69: 415798.19 | AX69: 0 | AY69: 2506.56 | BA69: Essentials | BB69: Daily Essentials | BD69: Accessories | BE69: Headwear | BF69: Cap | BG69: N
A70: SS28 | B70: All year | C70: TRUE | D70: 608164 | E70: Haglöfs Hoodie Men | G70: Apparel | H70: F27 | I70: CO | M70: DAY | N70: Midlayer | O70: Inline | P70: Men | Q70: Mid Hood | R70: Top | V70: 1500 | W70: 2.1 | X70: 714 | Y70: 0.2 | Z70: 571.2 | AA70: 1 | AB70: Better | AC70: 0.58 | AE70: None | AF70: None | AG70: 3 | AH70: 3 | AI70: request for more colors from sales. Charlotte: 4SCO. 1 New. | AK70: 1200 | AL70: 1214 | AM70: 0 | AN70: 813 | AO70: 1677 | AP70: 856800 | AQ70: 867148.06 | AR70: 1197378 | AS70: 0 | AT70: 1197378 | AU70: 685440 | AV70: 747496.26 | AW70: 0 | AX70: 476975.72 | AY70: 724897.29 | BA70: Essentials | BB70: Daily Essentials | BC70: Essentials / Essentials/Everyday [MATCH] | BD70: Fleece/Midlayer | BE70: Hooded Jacket | BF70: Midweight | BG70: N
A71: SS28 | B71: All year | C71: TRUE | D71: 608184 | E71: Haglöfs Hoodie Women | G71: Apparel | H71: F27 | I71: CO | M71: DAY | N71: Midlayer | O71: Inline | P71: Women | Q71: Mid Hood | R71: Top | V71: 1500 | W71: 2.1 | X71: 714 | Y71: 0.2 | Z71: 571.2 | AA71: 1 | AB71: Better | AC71: 0.6 | AE71: None | AF71: None | AG71: 3 | AH71: 3 | AI71: Women specific col? | AK71: 900 | AL71: 934 | AM71: 0 | AN71: 657 | AO71: 968 | AP71: 642600 | AQ71: 667146.86 | AR71: 691152 | AS71: 0 | AT71: 691152 | AU71: 514080 | AV71: 574493.09 | AW71: 0 | AX71: 400345.06 | AY71: 464200.02 | BA71: Essentials | BB71: Daily Essentials | BC71: Essentials / Essentials/Everyday [MATCH] | BD71: Fleece/Midlayer | BE71: Hooded Jacket | BF71: Midweight | BG71: N
A72: SS28 | B72: All year | C72: TRUE | D72: 607660 | E72: Haglöfs LS Tee Men | G72: Apparel | H72: F27 | I72: CO | M72: DAY | N72: Tops | O72: Inline | P72: Men | Q72: LS Tee | R72: Top | V72: 800 | W72: 2.1 | X72: 381 | Y72: 0.2 | Z72: 304.8 | AA72: 1 | AB72: Better | AC72: 0.611 | AE72: None | AF72: None | AG72: 4 | AH72: 4 | AI72: replace Lt Haze blue with a FW color. Charlotte: 4SCO. 1 New. Drop Maroon Trail. | AK72: 2300 | AL72: 2261 | AM72: 1559 | AN72: 2377 | AO72: 2036 | AP72: 876300 | AQ72: 861327.95 | AR72: 775716 | AS72: 0 | AT72: 775716 | AU72: 701040 | AV72: 669569.5 | AW72: 524915.31 | AX72: 656716.94 | AY72: 651356.09 | BA72: Essentials | BB72: Daily Essentials | BC72: Essentials / Essentials/Everyday [MATCH] | BD72: Tops | BE72: Long Sleeve | BF72: Cotton/Graphic Tee | BG72: N
A73: SS28 | B73: All year | C73: TRUE | D73: 607663 | E73: Haglöfs LS Tee Women | G73: Apparel | H73: F27 | I73: CO | M73: DAY | N73: Tops | O73: Inline | P73: Women | Q73: LS Tee | R73: Top | V73: 800 | W73: 2.1 | X73: 381 | Y73: 0.2 | Z73: 304.8 | AA73: 1 | AB73: Best | AC73: 0.63 | AE73: None | AF73: None | AG73: 4 | AH73: 4 | AI73: replace Lt Haze blue with a FW color. Charlotte: 4SCO. 1 New. Drop Misty Mauve. Add Dusty Rose to align with Tee. | AK73: 1700 | AL73: 1743 | AM73: 1336 | AN73: 1833 | AO73: 1329 | AP73: 647700 | AQ73: 663995.85 | AR73: 506349 | AS73: 0 | AT73: 506349 | AU73: 518160 | AV73: 531457.36 | AW73: 472976.7 | AX73: 520875.95 | AY73: 440180.57 | BA73: Essentials | BB73: Daily Essentials | BC73: Essentials / Essentials/Everyday [MATCH] | BD73: Tops | BE73: Long Sleeve | BF73: Cotton/Graphic Tee | BG73: N
A74: SS28 | B74: Spring/Summer | C74: TRUE | D74: 607868 | E74: Haglöfs LX Hat | G74: Apparel | H74: S27 | I74: CO | M74: DAY | N74: Accessories | O74: Inline | P74: Unisex | Q74: Hat | R74: Other | V74: 500 | W74: 2.1 | X74: 238 | Y74: 0.2 | Z74: 190.4 | AA74: 1 | AB74: Better | AC74: 0.524 | AE74: None | AF74: None | AG74: 4 | AH74: 4 | AK74: 3800 | AL74: 3793 | AM74: 2949 | AN74: 0 | AO74: 51 | AP74: 904400 | AQ74: 903113.3 | AR74: 12138 | AS74: 0 | AT74: 12138 | AU74: 723520 | AV74: 690099.73 | AW74: 555660.54 | AX74: 0 | AY74: 10007.73 | BA74: Essentials | BB74: Daily Essentials | BD74: Accessories | BE74: Headwear | BF74: Cap | BG74: N
A75: SS28 | B75: Fall/Winter | C75: FALSE | D75: 608858 | E75: Haglöfs Mimic Mitten | G75: Apparel | H75: F27 | I75: SEASONAL DROP | J75: FW-Style | M75: OUT | N75: Accessories | O75: ABS Exclusive | P75: Unisex | Q75: Insulated Glove | R75: Other | V75: 800 | W75: 2.1 | X75: 381 | Y75: 0 | Z75: 381 | AA75: 1 | AE75: Primaloft | AF75: Pertex | AH75: 3 | AJ75: DTC | AL75: 0 | AM75: 0 | AN75: 0 | AO75: 0 | AP75: 0 | AQ75: 0 | AR75: 0 | AS75: 0 | AT75: 0 | AU75: 0 | AV75: 0 | AW75: 0 | AX75: 0 | AY75: 0 | AZ75: NOT Active in Centric | BA75: Essentials | BB75: Active Essentials | BD75: Accessories | BE75: Handwear | BG75: N | BH75: Handwear (Mimic insulation) — confirm Subtype.
A76: SS28 | B76: All year | C76: TRUE | D76: 607658 | E76: Haglöfs Tee Men | G76: Apparel | H76: F27 | I76: CO | M76: DAY | N76: Tops | O76: Inline | P76: Men | Q76: SS Tee | R76: Top | V76: 700 | W76: 2.1 | X76: 333 | Y76: 0.2 | Z76: 266.4 | AA76: 1 | AB76: Best | AC76: 0.6 | AE76: None | AF76: None | AG76: 4 | AH76: 4 | AI76: Conslidate colors with LS Tee. Charlotte: 4SCO. 1 New. | AK76: 3700 | AL76: 3720 | AM76: 3260 | AN76: 1194 | AO76: 1149 | AP76: 1232100 | AQ76: 1239987.6 | AR76: 382617 | AS76: 0 | AT76: 382617 | AU76: 985680 | AV76: 1018063.2 | AW76: 862147.22 | AX76: 333056.15 | AY76: 329235.99 | BA76: Essentials | BB76: Daily Essentials | BC76: Essentials / Essentials/Everyday [MATCH] | BD76: Tops | BE76: Tee | BF76: Cotton/Graphic Tee | BG76: N
A77: SS28 | B77: All year | C77: TRUE | D77: 607665 | E77: Haglöfs Tee Women | G77: Apparel | H77: F27 | I77: CO | M77: DAY | N77: Tops | O77: Inline | P77: Women | Q77: SS Tee | R77: Top | V77: 700 | W77: 2.1 | X77: 333 | Y77: 0.2 | Z77: 266.4 | AA77: 1 | AB77: Best | AC77: 0.61 | AE77: None | AF77: None | AG77: 4 | AH77: 4 | AI77: Conslidate colors with LS Tee. Charlotte: 4SCO. 0 New. | AK77: 2200 | AL77: 2204 | AM77: 2604 | AN77: 877 | AO77: 874 | AP77: 732600 | AQ77: 734659.32 | AR77: 291042 | AS77: 0 | AT77: 291042 | AU77: 586080 | AV77: 620704.21 | AW77: 744981.09 | AX77: 262221.16 | AY77: 264892.75 | BA77: Essentials | BB77: Daily Essentials | BC77: Essentials / Essentials/Everyday [MATCH] | BD77: Tops | BE77: Tee | BF77: Cotton/Graphic Tee | BG77: N
A78: SS28 | B78: Spring/Summer | C78: TRUE | D78: 607867 | E78: Haglöfs Trucker Cap | G78: Apparel | H78: S27 | I78: CO | M78: DAY | N78: Accessories | O78: Inline | P78: Unisex | Q78: Cap | R78: Other | V78: 400 | W78: 2.1 | X78: 190 | Y78: 0.2 | Z78: 152 | AA78: 1 | AB78: Better | AC78: 0.61 | AE78: None | AF78: None | AG78: 3 | AH78: 2 | AJ78: XXL | AK78: 1500 | AL78: 1495 | AM78: 1355 | AN78: 0 | AO78: 22 | AP78: 285000 | AQ78: 284767.6 | AR78: 4180 | AS78: 0 | AT78: 4180 | AU78: 228000 | AV78: 242382.86 | AW78: 237912.41 | AX78: 0 | AY78: 3446.52 | BA78: Essentials | BB78: Daily Essentials | BD78: Accessories | BE78: Headwear | BF78: Cap | BG78: N
A79: SS28 | B79: Fall/Winter | C79: FALSE | D79: 608102 | E79: Hede Down Coat Women | G79: Apparel | H79: F27 | I79: SEASONAL DROP | J79: FW-Style | M79: DAY | N79: Insulation | O79: Inline | P79: Women | Q79: Parka | R79: Top | V79: 3500 | W79: 2.1 | X79: 1667 | Y79: 0 | Z79: 1667 | AA79: 1 | AB79: Better | AE79: Down | AF79: Pertex | AH79: 2 | AI79: replace Chalk beige? Charlotte: 3SCO. Drop Chalk Beige. 1 new | AL79: 0 | AM79: 0 | AN79: 567 | AO79: 572 | AP79: 0 | AQ79: 0 | AR79: 953524 | AS79: 0 | AT79: 953524 | AU79: 0 | AV79: 0 | AW79: 0 | AX79: 900138.17 | AY79: 880933.79 | AZ79: NOT Active in Centric | BA79: Essentials | BB79: Daily Essentials | BC79: Essentials / Essentials/Everyday [MATCH] | BD79: Insulation | BE79: Coat | BF79: Hi-loft Down | BG79: N
A80: SS28 | B80: All year | C80: TRUE | D80: 608097 | E80: Hede Down Hood Men | G80: Apparel | H80: F27 | I80: CO | M80: DAY | N80: Insulation | O80: Inline | P80: Men | Q80: Hood | R80: Top | V80: 2800 | W80: 2.1 | X80: 1333 | Y80: 0.2 | Z80: 1066.4 | AA80: 1 | AB80: Better | AC80: 0.6 | AE80: Down | AF80: None | AG80: 3 | AH80: 3 | AI80: replace Dew Green. Charlotte: 4SCO. 1 New. Drop Dew Green. | AK80: 600 | AL80: 603 | AM80: 652 | AN80: 1408 | AO80: 1343 | AP80: 799800 | AQ80: 803997.99 | AR80: 1790219 | AS80: 0 | AT80: 1790219 | AU80: 639840 | AV80: 693122.79 | AW80: 847217.52 | AX80: 1597010.1 | AY80: 1386947.6 | BA80: Essentials | BB80: Active Essentials | BC80: Essentials / Essentials/Everyday [MATCH] | BD80: Insulation | BE80: Hooded Jacket | BF80: Lightweight Down | BG80: N
A81: SS28 | B81: All year | C81: TRUE | D81: 608098 | E81: Hede Down Hood Women | G81: Apparel | H81: F27 | I81: CO | M81: DAY | N81: Insulation | O81: Inline | P81: Women | Q81: Hood | R81: Top | V81: 2800 | W81: 2.1 | X81: 1333 | Y81: 0.2 | Z81: 1066.4 | AA81: 1 | AB81: Better | AC81: 0.62 | AE81: Down | AF81: None | AG81: 3 | AH81: 3 | AI81: Charlotte: 4SCO. 1New. | AK81: 700 | AL81: 652 | AM81: 919 | AN81: 1485 | AO81: 1337 | AP81: 933100 | AQ81: 869331.16 | AR81: 1782221 | AS81: 0 | AT81: 1782221 | AU81: 746480 | AV81: 754466.79 | AW81: 1027118.3 | AX81: 1686781.8 | AY81: 1455404.3 | BA81: Essentials | BB81: Active Essentials | BC81: Essentials / Essentials/Everyday [MATCH] | BD81: Insulation | BE81: Hooded Jacket | BF81: Lightweight Down | BG81: N
A82: SS28 | C82: FALSE | D82: 608819 | E82: Hede Down Prototype Hood Men | G82: Apparel | H82: F27 | I82: CANCELED | J82: Seasonal Brand Builder | M82: DAY | N82: Insulation | O82: ABS Exclusive | P82: Men | Q82: Hood | R82: Top | V82: 0 | W82: 2.1 | X82: 0 | Y82: 0 | Z82: 0 | AA82: 0 | AE82: Down | AH82: 1 | AJ82: KA YO Collab | AL82: 0 | AM82: 0 | AN82: 0 | AO82: 0 | AP82: 0 | AQ82: 0 | AR82: 0 | AS82: 0 | AT82: 0 | AU82: 0 | AV82: 0 | AW82: 0 | AX82: 0 | AY82: 0 | AZ82: NOT Active in Centric | BA82: Essentials | BB82: Active Essentials | BC82: Essentials / Essentials/Everyday [MATCH] | BD82: Insulation | BE82: Hooded Jacket | BF82: Lightweight Down | BG82: N
A83: SS28 | B83: All year | C83: TRUE | D83: 608100 | E83: Hede Down Vest Men | G83: Apparel | H83: F27 | I83: CO | M83: DAY | N83: Insulation | O83: Inline | P83: Men | Q83: Vest | R83: Top | V83: 2000 | W83: 2.1 | X83: 952 | Y83: 0.2 | Z83: 761.6 | AA83: 1 | AB83: Better | AC83: 0.6 | AE83: Down | AF83: None | AG83: 2 | AH83: 2 | AI83: 2SCO. 2 NEW. Align w. Hood (Walnut Brown & Haze Blue) | AK83: 400 | AL83: 421 | AM83: 0 | AN83: 836 | AO83: 0 | AP83: 380800 | AQ83: 400951.98 | AR83: 0 | AS83: 0 | AT83: 0 | AU83: 304640 | AV83: 372920.54 | AW83: 0 | AX83: 740814.71 | AY83: 0 | BA83: Essentials | BB83: Active Essentials | BC83: Essentials / Essentials/Everyday [MATCH] | BD83: Insulation | BE83: Vest | BF83: Lightweight Down | BG83: N
